Workbook

Sheet Dashboard
A1: STOCK ANALYSIS DASHBOARD
A2: Ticker Symbol: | C2: =Analysis!$B$2 -> WMT | D2: Current Price: | E2: =Valuation!F29 -> 123.63 | G2: Signal: | I2: =IFERROR(IF(H20>0.25,"STRONG BUY",IF(H20>0.1,"BUY",IF(H20>-0.1,"HOLD",IF(H20>-0.25,"SELL","STRONG SELL")))),"N/A") -> STRONG SELL | K2: DCF CASES
D3: Market Cap: | E3: =Calculations!C16 -> 991759860 | G3: Last Updated: | I3: ='Raw Data Pasting'!E4 -> 46105 | K3: Scenario | L3: Intrinsic Value | M3: vs. Current Price | N3: IRR (5-Year) | O3: 5-Yr Total Return
A4: Fundamentals | K4: Bear Case | L4: =Valuation!K48 -> 9.2519813 | M4: =Valuation!K49 -> -0.92516395 | N4: =Valuation!K50 -> -0.4045817 | O4: =Valuation!K51 -> -0.92516395
A5: P/E Ratio | B5: =Calculations!C50 -> 45.285714 | C5: =IFERROR("Rating: "&TEXT(Analysis!E38,"0.0")&" / 5.0","N/A") -> Rating: 1.0 / 5.0 | K5: Base Case | L5: =Valuation!J48 -> 85.308313 | M5: =Valuation!J49 -> -0.30997077 | N5: =Valuation!J50 -> -0.071517981 | O5: =Valuation!J51 -> -0.30997077
A6: Debt/Equity | B6: =Analysis!B21 -> 0.63189866 | C6: =IFERROR("Rating: "&TEXT(Analysis!F21,"0.0")&" / 5.0","N/A") -> Rating: 3.5 / 5.0 | K6: Bull Case | L6: =Valuation!I48 -> 265.43046 | M6: =Valuation!I49 -> 1.1469746 | N6: =Valuation!I50 -> 0.16510584 | O6: =Valuation!I51 -> 1.1469746
A7: EV/EBITDA | B7: ='Data Schema'!B49 -> 21.63 | C7: =IFERROR("Rating: "&TEXT(Analysis!E41,"0.0")&" / 5.0","N/A") -> Rating: 1.0 / 5.0 | K7: Monte Carlo Mean | L7: =Valuation!B159 -> 96.290976 | M7: =IFERROR((Valuation!B159-Valuation!F29)/Valuation!F29,0) -> -0.22113584 | N7: =IFERROR((Valuation!J145/Valuation!F29)^(1/5)-1,0) -> -1 | O7: =IFERROR(Valuation!J145/Valuation!F29-1,0) -> -1
A8: Current Ratio | B8: =Analysis!B15 -> 0.78975332 | C8: =IFERROR("Rating: "&TEXT(Analysis!F15,"0.0")&" / 5.0","N/A") -> Rating: 2.5 / 5.0
A9: ROE | B9: =Analysis!B9 -> 0.20618761 | C9: =IFERROR("Rating: "&TEXT(Analysis!F9,"0.0")&" / 5.0","N/A") -> Rating: 5.0 / 5.0
A10: Operating Margin | B10: =Analysis!B7 -> 0.045246318 | C10: =IFERROR("Rating: "&TEXT(Analysis!F7,"0.0")&" / 5.0","N/A") -> Rating: 3.5 / 5.0
A11: ROIC | B11: =Analysis!B11 -> 0.15001864 | C11: =IFERROR("Rating: "&TEXT(Analysis!F11,"0.0")&" / 5.0","N/A") -> Rating: 5.0 / 5.0
A12: Rev Growth (YoY) | B12: =Analysis!B32 -> 0.047252142 | C12: =IFERROR("Rating: "&TEXT(Analysis!F32,"0.0")&" / 5.0","N/A") -> Rating: 1.5 / 5.0
A13: FINANCIAL HEALTH SCORECARD
A14: Profitability | B14: =Analysis!F12 -> 4.1666667 | C14: =IFERROR(REPT("█",ROUND(B14,0))&REPT("░",5-ROUND(B14,0))&" "&TEXT(B14,"0.0")&" / 5.0","N/A") -> ████░ 4.2 / 5.0
A15: Liquidity | B15: =Analysis!F18 -> 2.1666667 | C15: =IFERROR(REPT("█",ROUND(B15,0))&REPT("░",5-ROUND(B15,0))&" "&TEXT(B15,"0.0")&" / 5.0","N/A") -> ██░░░ 2.2 / 5.0
A16: Leverage/Risk | B16: =Analysis!F24 -> 4 | C16: =IFERROR(REPT("█",ROUND(B16,0))&REPT("░",5-ROUND(B16,0))&" "&TEXT(B16,"0.0")&" / 5.0","N/A") -> ████░ 4.0 / 5.0 | K16: MONTE CARLO SIMULATION FOR DCF
A17: Efficiency | B17: =Analysis!F29 -> 3.25 | C17: =IFERROR(REPT("█",ROUND(B17,0))&REPT("░",5-ROUND(B17,0))&" "&TEXT(B17,"0.0")&" / 5.0","N/A") -> ███░░ 3.3 / 5.0 | G17: VALUATIONS | K17: =Valuation!A174 -> Based on 1000 simulations with constraints, 795 valid scenarios were analyzed. There is a 27.7% chance that the intrinsic value exceeds the current market price of $123.63. The 80% confidence interval is $36.89 to $167.96.
A18: Growth | B18: =Analysis!F35 -> 2.3333333 | C18: =IFERROR(REPT("█",ROUND(B18,0))&REPT("░",5-ROUND(B18,0))&" "&TEXT(B18,"0.0")&" / 5.0","N/A") -> ██░░░ 2.3 / 5.0 | G18: DCF | H18: =Valuation!F28 -> 85.308313 | I18: Peer Multiples | J18: =IF(Valuation!F100="On",Valuation!D106,"Off") -> 76.106156
A19: Valuation | B19: =Analysis!E43 -> 1 | C19: =IFERROR(REPT("█",ROUND(B19,0))&REPT("░",5-ROUND(B19,0))&" "&TEXT(B19,"0.0")&" / 5.0","N/A") -> █░░░░ 1.0 / 5.0 | G19: Difference: | H19: =H18-E2 -> -38.321687 | I19: Difference: | J19: =J18-E2 -> -47.523844
A20: OVERALL SCORE | B20: =Analysis!D52 -> 3.0583333 | C20: / 5.0 | G20: Margin of Safety: | H20: =IFERROR((H18-E2)/H18,0) -> -0.44921397 | I20: Margin of Safety: | J20: =IFERROR((J18-E2)/J18,0) -> -0.62444153
G21: Graham Number | H21: =IF(Valuation!F108="On",Valuation!D112,"Off") -> 28.608299 | I21: DDM | J21: =IF(Valuation!F114="On",Valuation!D119,"Off") -> -9.4198386 | K21: Mean | L21: =Valuation!B159 -> 96.290976
G22: Difference: | H22: =H21-E2 -> -95.021701 | I22: Difference: | J22: =J21-E2 -> -133.04984 | K22: Median | L22: =Valuation!B160 -> 87.904047
G23: Margin of Safety: | H23: =IFERROR((H21-E2)/H21,0) -> -3.3214734 | I23: Margin of Safety: | J23: =IFERROR((J21-E2)/J21,0) -> 14.124429 | K23: Std Deviation | L23: =Valuation!B161 -> 49.228425
G24: ABV | H24: =IF(Valuation!F121="On",Valuation!D124,"Off") -> 12.417976 | I24: RIM | J24: =IF(Valuation!F126="On",Valuation!D130,"Off") -> 31.684029 | K24: 10th Percentile | L24: =Valuation!B162 -> 36.885697
G25: Difference: | H25: =H24-E2 -> -111.21202 | I25: Difference: | J25: =J24-E2 -> -91.945971 | K25: 25th Percentile | L25: =Valuation!B163 -> 55.645214
G26: Margin of Safety: | H26: =IFERROR((H24-E2)/H24,0) -> -8.955729 | I26: Margin of Safety: | J26: =IFERROR((J24-E2)/J24,0) -> -2.9019659 | K26: 75th Percentile | L26: =Valuation!B164 -> 129.02101
G27: MARKET-IMPLIED ASSUMPTIONS (REVERSE DCF) | K27: 90th Percentile | L27: =Valuation!B165 -> 167.96064
G28: Assumption | H28: Base Case | I28: Market-Implied | J28: % Change | K28: Min | L28: =Valuation!B166 -> 24.364502
G29: Terminal Growth (g) | H29: =Valuation!I14 -> 0.025 | I29: =Valuation!W9 -> 0.036109847 | J29: =IFERROR((I29-H29)/H29,"N/A") -> 0.44439387 | K29: Max | L29: =Valuation!B167 -> 223.4485
G30: WACC | H30: =Valuation!I13 -> 0.06 | I30: =Valuation!W20 -> 0.049875913 | J30: =IFERROR((I30-H30)/H30,"N/A") -> -0.16873479 | K30: Prob > Current Price | L30: =Valuation!B169 -> 0.27672956
G31: Revenue Growth | H31: =Valuation!I2 -> 0.1 | I31: =Valuation!W36 -> 0.19823985 | J31: =IFERROR((I31-H31)/H31,"N/A") -> 0.98239851 | K31: 80% CI Low | L31: =Valuation!B170 -> 36.885697
G32: Blended Intrinsic Value | H32: =Valuation!W47 -> 122.18853 | I32: vs Market: | J32: =Valuation!W48 -> -0.01165953 | K32: 80% CI High | L32: =Valuation!B171 -> 167.96064
A47: HISTORICAL FINANCIAL TRENDS
A48: Year | B48: ='Data Schema'!F1 -> 2023 | C48: ='Data Schema'!E1 -> 2024 | D48: ='Data Schema'!D1 -> 2025 | E48: ='Data Schema'!C1 -> 2026 | F48: TTM
A49: Revenue | B49: ='Data Schema'!F3 -> 611289000 | C49: ='Data Schema'!E3 -> 648125000 | D49: ='Data Schema'!D3 -> 680985000 | E49: ='Data Schema'!C3 -> 713163000 | F49: ='Data Schema'!B3 -> 713163000
A50: Net Income | B50: ='Data Schema'!F13 -> 11680000 | C50: ='Data Schema'!E13 -> 15511000 | D50: ='Data Schema'!D13 -> 19436000 | E50: ='Data Schema'!C13 -> 21893000 | F50: ='Data Schema'!B13 -> 21893000
A51: Op Income | B51: ='Data Schema'!F14 -> 19144000 | C51: ='Data Schema'!E14 -> 24531000 | D51: ='Data Schema'!D14 -> 29037000 | E51: ='Data Schema'!C14 -> 32268000 | F51: ='Data Schema'!B14 -> 32268000
A52: FCFF | B52: ='Data Schema'!B40 -> 14923000 | C52: ='Data Schema'!C40 -> 14923000 | D52: ='Data Schema'!D40 -> 12660000 | E52: ='Data Schema'!E40 -> 15120000 | F52: ='Data Schema'!F40 -> 11984000
A53: Gross Margin | B53: =Calculations!G37 -> 0.24140464 | C53: =Calculations!F37 -> 0.24375391 | D53: =Calculations!E37 -> 0.24851061 | E53: =Calculations!D37 -> 0.249267 | F53: =Calculations!C37 -> N/A
A54: Op Margin | B54: =Calculations!G38 -> 0.031317429 | C54: =Calculations!F38 -> 0.03784918 | D54: =Calculations!E38 -> 0.042639706 | E54: =Calculations!D38 -> 0.045246318 | F54: =Calculations!C38 -> N/A
A55: Net Margin | B55: =Calculations!G39 -> 0.019107165 | C55: =Calculations!F39 -> 0.023932112 | D55: =Calculations!E39 -> 0.02854101 | E55: =Calculations!D39 -> 0.030698452 | F55: =Calculations!C39 -> N/A
A56: Total Assets | B56: ='Data Schema'!F19 -> 243197000 | C56: ='Data Schema'!E19 -> 252399000 | D56: ='Data Schema'!D19 -> 260823000 | E56: ='Data Schema'!C19 -> 284668000 | F56: ='Data Schema'!B19 -> N/A
A57: Total Debt | B57: ='Data Schema'!F31 -> 58923000 | C57: ='Data Schema'!E31 -> 61321000 | D57: ='Data Schema'!D31 -> 60114000 | E57: ='Data Schema'!C31 -> 67095000 | F57: ='Data Schema'!B31 -> N/A
A58: Equity | B58: ='Data Schema'!F29 -> 83991000 | C58: ='Data Schema'!E29 -> 90571000 | D58: ='Data Schema'!D29 -> 97692000 | E58: ='Data Schema'!C29 -> 106180000 | F58: ='Data Schema'!B29 -> N/A

Sheet Analysis
A1: Financial Analysis & Ratings
A2: Company: | B2: ='Raw Data Pasting'!V3 -> WMT
A3: Date: | B3: As of Latest Filing
A5: Profitability Metrics | B5: Current Value | C5: Historical Avg | D5: Textbook Rating | E5: Trend Rating | F5: Final Rating
A6: Gross Margin | B6: =Calculations!D37 -> 0.249267 | C6: =Calculations!H37 -> 0.24573404 | D6: =IFERROR(IF(B6>=0.4,5,IF(B6>=0.3,4,IF(B6>=0.2,3,IF(B6>=0.1,2,1)))),"N/A") -> 3 | E6: =IFERROR(IF((B6-C6)/ABS(C6)>=0.1,5,IF((B6-C6)/ABS(C6)>=0.05,4,IF((B6-C6)/ABS(C6)>=-0.05,3,IF((B6-C6)/ABS(C6)>=-0.1,2,1)))),"N/A") -> 3 | F6: =IFERROR(ROUND(AVERAGE(D6,E6),1),"N/A") -> 3
A7: Operating Margin | B7: =Calculations!D38 -> 0.045246318 | C7: =Calculations!H38 -> 0.039263158 | D7: =IFERROR(IF(B7>=0.15,5,IF(B7>=0.1,4,IF(B7>=0.05,3,IF(B7>=0.02,2,1)))),"N/A") -> 2 | E7: =IFERROR(IF((B7-C7)/ABS(C7)>=0.1,5,IF((B7-C7)/ABS(C7)>=0.05,4,IF((B7-C7)/ABS(C7)>=-0.05,3,IF((B7-C7)/ABS(C7)>=-0.1,2,1)))),"N/A") -> 5 | F7: =IFERROR(ROUND(AVERAGE(D7,E7),1),"N/A") -> 3.5
A8: Net Margin | B8: =Calculations!D39 -> 0.030698452 | C8: =Calculations!H39 -> 0.025569685 | D8: =IFERROR(IF(B8>=0.1,5,IF(B8>=0.05,4,IF(B8>=0.02,3,IF(B8>=0,2,1)))),"N/A") -> 3 | E8: =IFERROR(IF((B8-C8)/ABS(C8)>=0.1,5,IF((B8-C8)/ABS(C8)>=0.05,4,IF((B8-C8)/ABS(C8)>=-0.05,3,IF((B8-C8)/ABS(C8)>=-0.1,2,1)))),"N/A") -> 5 | F8: =IFERROR(ROUND(AVERAGE(D8,E8),1),"N/A") -> 4
A9: ROE | B9: =Calculations!D41 -> 0.20618761 | C9: =Calculations!H41 -> 0.17886496 | D9: =IFERROR(IF(B9>=0.2,5,IF(B9>=0.15,4,IF(B9>=0.1,3,IF(B9>=0.05,2,1)))),"N/A") -> 5 | E9: =IFERROR(IF((B9-C9)/ABS(C9)>=0.1,5,IF((B9-C9)/ABS(C9)>=0.05,4,IF((B9-C9)/ABS(C9)>=-0.05,3,IF((B9-C9)/ABS(C9)>=-0.1,2,1)))),"N/A") -> 5 | F9: =IFERROR(ROUND(AVERAGE(D9,E9),1),"N/A") -> 5
A10: ROA | B10: =Calculations!D40 -> 0.076907134 | C10: =Calculations!H40 -> 0.065226574 | D10: =IFERROR(IF(B10>=0.1,5,IF(B10>=0.05,4,IF(B10>=0.02,3,IF(B10>=0,2,1)))),"N/A") -> 4 | E10: =IFERROR(IF((B10-C10)/ABS(C10)>=0.1,5,IF((B10-C10)/ABS(C10)>=0.05,4,IF((B10-C10)/ABS(C10)>=-0.05,3,IF((B10-C10)/ABS(C10)>=-0.1,2,1)))),"N/A") -> 5 | F10: =IFERROR(ROUND(AVERAGE(D10,E10),1),"N/A") -> 4.5
A11: ROIC | B11: =Calculations!D61 -> 0.15001864 | C11: =Calculations!H61 -> 0.13069707 | D11: =IFERROR(IF(B11>=0.15,5,IF(B11>=0.1,4,IF(B11>=0.05,3,IF(B11>=0.02,2,1)))),"N/A") -> 5 | E11: =IFERROR(IF((B11-C11)/ABS(C11)>=0.1,5,IF((B11-C11)/ABS(C11)>=0.05,4,IF((B11-C11)/ABS(C11)>=-0.05,3,IF((B11-C11)/ABS(C11)>=-0.1,2,1)))),"N/A") -> 5 | F11: =IFERROR(ROUND(AVERAGE(D11,E11),1),"N/A") -> 5
A12: Profitability Score | F12: =IFERROR(AVERAGE(F6:F11),"N/A") -> 4.1666667
A14: Liquidity Metrics | B14: Current Value | C14: Historical Avg | D14: Textbook Rating | E14: Trend Rating | F14: Final Rating
A15: Current Ratio | B15: =Calculations!D31 -> 0.78975332 | C15: =Calculations!H31 -> 0.81621856 | D15: =IFERROR(IF(B15>=2,5,IF(B15>=1.5,4,IF(B15>=1,3,IF(B15>=0.5,2,1)))),"N/A") -> 2 | E15: =IFERROR(IF((B15-C15)/ABS(C15)>=0.1,5,IF((B15-C15)/ABS(C15)>=0.05,4,IF((B15-C15)/ABS(C15)>=-0.05,3,IF((B15-C15)/ABS(C15)>=-0.1,2,1)))),"N/A") -> 3 | F15: =IFERROR(ROUND(AVERAGE(D15,E15),1),"N/A") -> 2.5
A16: Quick Ratio | B16: =Calculations!D32 -> 0.20377039 | C16: =Calculations!H32 -> 0.19553852 | D16: =IFERROR(IF(B16>=1.5,5,IF(B16>=1,4,IF(B16>=0.75,3,IF(B16>=0.5,2,1)))),"N/A") -> 1 | E16: =IFERROR(IF((B16-C16)/ABS(C16)>=0.1,5,IF((B16-C16)/ABS(C16)>=0.05,4,IF((B16-C16)/ABS(C16)>=-0.05,3,IF((B16-C16)/ABS(C16)>=-0.1,2,1)))),"N/A") -> 3 | F16: =IFERROR(ROUND(AVERAGE(D16,E16),1),"N/A") -> 2
A17: Cash Ratio | B17: =Calculations!D63 -> 0.09981483 | C17: =Calculations!H63 -> 0.098424525 | D17: =IFERROR(IF(B17>=1,5,IF(B17>=0.5,4,IF(B17>=0.25,3,IF(B17>=0.1,2,1)))),"N/A") -> 1 | E17: =IFERROR(IF((B17-C17)/ABS(C17)>=0.1,5,IF((B17-C17)/ABS(C17)>=0.05,4,IF((B17-C17)/ABS(C17)>=-0.05,3,IF((B17-C17)/ABS(C17)>=-0.1,2,1)))),"N/A") -> 3 | F17: =IFERROR(ROUND(AVERAGE(D17,E17),1),"N/A") -> 2
A18: Liquidity Score | F18: =IFERROR(AVERAGE(F15:F17),"N/A") -> 2.1666667
A20: Leverage/Risk Metrics | B20: Current Value | C20: Historical Avg | D20: Textbook Rating | E20: Trend Rating | F20: Final Rating
A21: Debt-to-Equity | B21: =Calculations!D33 -> 0.63189866 | C21: =Calculations!H33 -> 0.65645729 | D21: =IFERROR(IF(B21<=0.5,5,IF(B21<=1,4,IF(B21<=2,3,IF(B21<=3,2,1)))),"N/A") -> 4 | E21: =IFERROR(IF((C21-B21)/ABS(C21)>=0.1,5,IF((C21-B21)/ABS(C21)>=0.05,4,IF((C21-B21)/ABS(C21)>=-0.05,3,IF((C21-B21)/ABS(C21)>=-0.1,2,1)))),"N/A") -> 3 | F21: =IFERROR(ROUND(AVERAGE(D21,E21),1),"N/A") -> 3.5
A22: Debt-to-Assets | B22: =Calculations!D34 -> 0.23569562 | C22: =Calculations!H34 -> 0.23785286 | D22: =IFERROR(IF(B22<=0.3,5,IF(B22<=0.5,4,IF(B22<=0.7,3,IF(B22<=0.9,2,1)))),"N/A") -> 5 | E22: =IFERROR(IF((C22-B22)/ABS(C22)>=0.1,5,IF((C22-B22)/ABS(C22)>=0.05,4,IF((C22-B22)/ABS(C22)>=-0.05,3,IF((C22-B22)/ABS(C22)>=-0.1,2,1)))),"N/A") -> 3 | F22: =IFERROR(ROUND(AVERAGE(D22,E22),1),"N/A") -> 4
A23: Interest Coverage | B23: =Calculations!D35 -> 11.528403 | C23: =Calculations!H35 -> 10.710998 | D23: =IFERROR(IF(B23>=8,5,IF(B23>=5,4,IF(B23>=2.5,3,IF(B23>=1,2,1)))),"N/A") -> 5 | E23: =IFERROR(IF((B23-C23)/ABS(C23)>=0.1,5,IF((B23-C23)/ABS(C23)>=0.05,4,IF((B23-C23)/ABS(C23)>=-0.05,3,IF((B23-C23)/ABS(C23)>=-0.1,2,1)))),"N/A") -> 4 | F23: =IFERROR(ROUND(AVERAGE(D23,E23),1),"N/A") -> 4.5
A24: Leverage Score | F24: =IFERROR(AVERAGE(F21:F23),"N/A") -> 4
A26: Efficiency Metrics | B26: Current Value | C26: Historical Avg | D26: Textbook Rating | E26: Trend Rating | F26: Final Rating
A27: Asset Turnover | B27: =Calculations!D45 -> 2.6147562 | C27: =Calculations!H45 -> 2.7140206 | D27: =IFERROR(IF(B27>=2,5,IF(B27>=1.5,4,IF(B27>=1,3,IF(B27>=0.5,2,1)))),"N/A") -> 5 | E27: =IFERROR(IF((B27-C27)/ABS(C27)>=0.1,5,IF((B27-C27)/ABS(C27)>=0.05,4,IF((B27-C27)/ABS(C27)>=-0.05,3,IF((B27-C27)/ABS(C27)>=-0.1,2,1)))),"N/A") -> 3 | F27: =IFERROR(ROUND(AVERAGE(D27,E27),1),"N/A") -> 4
A28: Inventory Turnover | B28: =Calculations!D46 -> 9.2881182 | C28: =Calculations!H46 -> 10.917242 | D28: =IFERROR(IF(B28>=10,5,IF(B28>=7,4,IF(B28>=5,3,IF(B28>=3,2,1)))),"N/A") -> 4 | E28: =IFERROR(IF((B28-C28)/ABS(C28)>=0.1,5,IF((B28-C28)/ABS(C28)>=0.05,4,IF((B28-C28)/ABS(C28)>=-0.05,3,IF((B28-C28)/ABS(C28)>=-0.1,2,1)))),"N/A") -> 1 | F28: =IFERROR(ROUND(AVERAGE(D28,E28),1),"N/A") -> 2.5
A29: Efficiency Score | F29: =IFERROR(AVERAGE(F27:F28),"N/A") -> 3.25
A31: Growth Metrics | B31: Current Value | C31: Historical Avg | D31: Textbook Rating | E31: Trend Rating | F31: Final Rating
A32: Revenue Growth (YoY) | B32: =Calculations!D54 -> 0.047252142 | C32: =Calculations!H54 -> 0.052737263 | D32: =IFERROR(IF(B32>=0.2,5,IF(B32>=0.1,4,IF(B32>=0.05,3,IF(B32>=0,2,1)))),"N/A") -> 2 | E32: =IFERROR(IF((B32-C32)/ABS(C32)>=0.1,5,IF((B32-C32)/ABS(C32)>=0.05,4,IF((B32-C32)/ABS(C32)>=-0.05,3,IF((B32-C32)/ABS(C32)>=-0.1,2,1)))),"N/A") -> 1 | F32: =IFERROR(ROUND(AVERAGE(D32,E32),1),"N/A") -> 1.5
A33: Revenue CAGR (3Y) | B33: =Calculations!C64 -> 0.052722909 | C33: =Calculations!C64 -> 0.052722909 | D33: =IFERROR(IF(B33>=0.2,5,IF(B33>=0.1,4,IF(B33>=0.05,3,IF(B33>=0,2,1)))),"N/A") -> 3 | E33: =IFERROR(IF((B33-C33)/ABS(C33)>=0.1,5,IF((B33-C33)/ABS(C33)>=0.05,4,IF((B33-C33)/ABS(C33)>=-0.05,3,IF((B33-C33)/ABS(C33)>=-0.1,2,1)))),"N/A") -> 3 | F33: =IFERROR(ROUND(AVERAGE(D33,E33),1),"N/A") -> 3
A34: Earnings Growth | B34: =Calculations!D55 -> 0.1264149 | C34: =Calculations!H55 -> 0.23581923 | D34: =IFERROR(IF(B34>=0.2,5,IF(B34>=0.1,4,IF(B34>=0.05,3,IF(B34>=0,2,1)))),"N/A") -> 4 | E34: =IFERROR(IF((B34-C34)/ABS(C34)>=0.1,5,IF((B34-C34)/ABS(C34)>=0.05,4,IF((B34-C34)/ABS(C34)>=-0.05,3,IF((B34-C34)/ABS(C34)>=-0.1,2,1)))),"N/A") -> 1 | F34: =IFERROR(ROUND(AVERAGE(D34,E34),1),"N/A") -> 2.5
A35: Growth Score | F35: =IFERROR(AVERAGE(F32:F34),"N/A") -> 2.3333333
A37: Valuation vs Peers | B37: Company Value | C37: Peer Avg | D37: Ratio (Co/Peer) | E37: Relative Rating
A38: P/E | B38: ='Data Schema'!B44 -> 43.6 | C38: ='Data Schema'!F44 -> 27.556667 | D38: =IFERROR(B38/C38,"N/A") -> 1.5821943 | E38: =IFERROR(IF(D38<=0.5,5,IF(D38<=0.75,4,IF(D38<=1,3,IF(D38<=1.25,2,1)))),"N/A") -> 1
A39: P/B | B39: ='Data Schema'!B47 -> 9.53 | C39: ='Data Schema'!F47 -> 6.61 | D39: =IFERROR(B39/C39,"N/A") -> 1.4417549 | E39: =IFERROR(IF(D39<=0.5,5,IF(D39<=0.75,4,IF(D39<=1,3,IF(D39<=1.25,2,1)))),"N/A") -> 1
A40: P/S | B40: ='Data Schema'!B48 -> 1.34 | C40: ='Data Schema'!F48 -> 0.88 | D40: =IFERROR(B40/C40,"N/A") -> 1.5227273 | E40: =IFERROR(IF(D40<=0.5,5,IF(D40<=0.75,4,IF(D40<=1,3,IF(D40<=1.25,2,1)))),"N/A") -> 1
A41: EV/EBITDA | B41: ='Data Schema'!B49 -> 21.63 | C41: ='Data Schema'!F49 -> 16.943333 | D41: =IFERROR(B41/C41,"N/A") -> 1.2766083 | E41: =IFERROR(IF(D41<=0.5,5,IF(D41<=0.75,4,IF(D41<=1,3,IF(D41<=1.25,2,1)))),"N/A") -> 1
A42: P/FCF | B42: ='Data Schema'!B46 -> 63.98 | C42: ='Data Schema'!F46 -> 25.733333 | D42: =IFERROR(B42/C42,"N/A") -> 2.4862694 | E42: =IFERROR(IF(D42<=0.5,5,IF(D42<=0.75,4,IF(D42<=1,3,IF(D42<=1.25,2,1)))),"N/A") -> 1
A43: Valuation Score | E43: =IFERROR(AVERAGE(E38:E42),"N/A") -> 1
A45: Overall Score Summary | B45: Category Score | C45: Weight | D45: Weighted Score
A46: Profitability | B46: =F12 -> 4.1666667 | C46: 0.25 | D46: =IFERROR(B46*C46,0) -> 1.0416667
A47: Liquidity | B47: =F18 -> 2.1666667 | C47: 0.15 | D47: =IFERROR(B47*C47,0) -> 0.325
A48: Leverage/Risk | B48: =F24 -> 4 | C48: 0.2 | D48: =IFERROR(B48*C48,0) -> 0.8
A49: Efficiency | B49: =F29 -> 3.25 | C49: 0.1 | D49: =IFERROR(B49*C49,0) -> 0.325
A50: Growth | B50: =F35 -> 2.3333333 | C50: 0.2 | D50: =IFERROR(B50*C50,0) -> 0.46666667
A51: Valuation vs Peers | B51: =E43 -> 1 | C51: 0.1 | D51: =IFERROR(B51*C51,0) -> 0.1
A52: OVERALL WEIGHTED SCORE | D52: =IFERROR(SUM(D46:D51),"N/A") -> 3.0583333
A53: LETTER GRADE | D53: =IFERROR(IF(D52>=4.5,"A",IF(D52>=3.5,"B",IF(D52>=2.5,"C",IF(D52>=1.5,"D","F")))),"N/A") -> C

Sheet Valuation
A1: Base Case DCF | H1: Assumptions | I1: Value | J1: Selector Switch | K1: Manual Input | L1: Historical Average | M1: =Calculations!D1 -> 2026 | N1: =Calculations!E1 -> 2025 | O1: =Calculations!F1 -> 2024 | P1: =Calculations!G1 -> 2023 | R1: REVERSE DCF CALCULATIONS
A2: Forecasted Data all numbers in thousands | B2: ='Data Schema'!$C$1+1 -> 2027 | C2: ='Data Schema'!$C$1+2 -> 2028 | D2: ='Data Schema'!$C$1+3 -> 2029 | E2: ='Data Schema'!$C$1+4 -> 2030 | F2: ='Data Schema'!$C$1+5 -> 2031 | H2: Revenue Growth Rate | I2: {=_xlfn.SWITCH(J2,"Manual",K2,"Average",L2,"Manual +2.5%",K2*1.025, "Manual +5%",K2*1.05, "Manual +10%",K2*1.1, "Manual -2.5%",K2*0.975,"Manual -5%",K2*0.95, "Manual -10%",K2*0.9)} -> 0.1 | J2: Manual | K2: 0.1 | L2: =Calculations!H54 -> 0.052737263 | M2: =Calculations!D54 -> 0.047252142 | N2: =Calculations!E54 -> 0.050700096 | O2: =Calculations!F54 -> 0.06025955 | P2: =Calculations!G54 -> N/A
A3: Total Revenue (Net Sales)* | B3: ='Data Schema'!C3*(1+I2) -> 7.844793e+08 | C3: =B3*(1+$I$2) -> 8.6292723e+08 | D3: =C3*(1+$I$2) -> 9.4921995e+08 | E3: =D3*(1+$I$2) -> 1.0441419e+09 | F3: =E3*(1+$I$2) -> 1.1485561e+09 | H3: Expense Ratios (% of Rev) | R3: Target Enterprise Value | W3: =F29*F27+F25-F24 -> 1048127860
A4: less COGS/ Cost of Revenue | B4: =B3*$I$4 -> 5.8835948e+08 | C4: =C3*$I$4 -> 6.4719542e+08 | D4: =D3*$I$4 -> 7.1191496e+08 | E4: =E3*$I$4 -> 7.8310646e+08 | F4: =F3*$I$4 -> 8.6141711e+08 | H4: COGS as % of Revenue | I4: {=_xlfn.SWITCH(J4,"Manual",K4,"Average",L4,"Manual +2.5%",K4*1.025, "Manual +5%",K4*1.05, "Manual +10%",K4*1.1, "Manual -2.5%",K4*0.975,"Manual -5%",K4*0.95, "Manual -10%",K4*0.9)} -> 0.75 | J4: Manual | K4: 0.75 | L4: =Calculations!H9 -> 0.75426596 | M4: =Calculations!D9 -> 0.750733 | N4: =Calculations!E9 -> 0.75148939 | O4: =Calculations!F9 -> 0.75624609 | P4: =Calculations!G9 -> 0.75859536
A5: Gross Profit | B5: =B3-B4 -> 196119825 | C5: =C3-C4 -> 2.1573181e+08 | D5: =D3-D4 -> 2.3730499e+08 | E5: =E3-E4 -> 2.6103549e+08 | F5: =F3-F4 -> 2.8713904e+08 | H5: OpEx as % of Revenue | I5: {=_xlfn.SWITCH(J5,"Manual",K5,"Average",L5,"Manual +2.5%",K5*1.025, "Manual +5%",K5*1.05, "Manual +10%",K5*1.1, "Manual -2.5%",K5*0.975,"Manual -5%",K5*0.95, "Manual -10%",K5*0.9)} -> 0.207 | J5: Manual | K5: 0.207 | L5: =Calculations!H10 -> 0.20573099 | M5: =Calculations!D10 -> 0.20744626 | N5: =Calculations!E10 -> 0.20541422 | O5: =Calculations!F10 -> 0.20207676 | P5: =Calculations!G10 -> 0.20798673 | R5: Scenario 1: Implied Terminal Growth (g) — Analytical
A6: less OpEx | B6: =B3*$I$5 -> 1.6238722e+08 | C6: =C3*$I$5 -> 1.7862594e+08 | D6: =D3*$I$5 -> 1.9648853e+08 | E6: =E3*$I$5 -> 2.1613738e+08 | F6: =F3*$I$5 -> 2.3775112e+08 | H6: D&A as % of Revenue | I6: {=_xlfn.SWITCH(J6,"Manual",K6,"Average",L6,"Manual +2.5%",K6*1.025, "Manual +5%",K6*1.05, "Manual +10%",K6*1.1, "Manual -2.5%",K6*0.975,"Manual -5%",K6*0.95, "Manual -10%",K6*0.9)} -> 0.025 | J6: Manual | K6: 0.025 | L6: =Calculations!H11 -> 0.018789694 | M6: =Calculations!D11 -> 0.019915503 | N6: =Calculations!E11 -> 0.019050346 | O6: =Calculations!F11 -> 0.018288139 | P6: =Calculations!G11 -> 0.017904788 | R6: Sum of PV of FCFFs (from model) | W6: =SUM(B17:F17) -> 1.0148278e+08
A7: Operating Income (EBIT) | B7: =B5-B6 -> 33732610 | C7: =C5-C6 -> 37105871 | D7: =D5-D6 -> 40816458 | E7: =E5-E6 -> 44898104 | F7: =F5-F6 -> 49387914 | H7: Capital Structure Assumptions | R7: Required PV of Terminal Value | W7: =W3-W6 -> 9.4664508e+08
A8: less Interest Expense | B8: =$I$8*$I$9 -> 2400000 | C8: =$I$8*$I$9 -> 2400000 | D8: =$I$8*$I$9 -> 2400000 | E8: =$I$8*$I$9 -> 2400000 | F8: =$I$8*$I$9 -> 2400000 | H8: Total Debt | I8: {=_xlfn.SWITCH(J8,"Manual",K8,"Average",L8,"Manual +2.5%",K8*1.025, "Manual +5%",K8*1.05, "Manual +10%",K8*1.1, "Manual -2.5%",K8*0.975,"Manual -5%",K8*0.95, "Manual -10%",K8*0.9)} -> 60000000 | J8: Manual | K8: 60000000 | L8: =AVERAGE('Data Schema'!C31:F31) -> 61863250 | M8: ='Data Schema'!C31 -> 67095000 | N8: ='Data Schema'!D31 -> 60114000 | O8: ='Data Schema'!E31 -> 61321000 | P8: ='Data Schema'!F31 -> 58923000 | R8: Required Terminal Value | W8: =W7*(1+I13)^5 -> 1.2668247e+09
A9: EBT (Pretax Income) | B9: =B7-B8 -> 31332610 | C9: =C7-C8 -> 34705871 | D9: =D7-D8 -> 38416458 | E9: =E7-E8 -> 42498104 | F9: =F7-F8 -> 46987914 | H9: Interest Rate | I9: {=_xlfn.SWITCH(J9,"Manual",K9,"Average",L9,"Manual +2.5%",K9*1.025, "Manual +5%",K9*1.05, "Manual +10%",K9*1.1, "Manual -2.5%",K9*0.975,"Manual -5%",K9*0.95, "Manual -10%",K9*0.9)} -> 0.04 | J9: Manual | K9: 0.04 | L9: =Calculations!H8 -> 0.041741426 | M9: =Calculations!D8 -> 0.041716968 | N9: =Calculations!E8 -> 0.045380444 | O9: =Calculations!F8 -> 0.043753363 | P9: =Calculations!G8 -> 0.03611493 | R9: Implied g | W9: =(W8*I13-F16)/(W8+F16) -> 0.036109847
A10: less Income Tax Expense/Tax Provision | B10: =B9*$I$10 -> 7833152.5 | C10: =C9*$I$10 -> 8676467.7 | D10: =D9*$I$10 -> 9604114.5 | E10: =E9*$I$10 -> 10624526 | F10: =F9*$I$10 -> 11746979 | H10: Effective Tax Rate (T) | I10: {=_xlfn.SWITCH(J10,"Manual",K10,"Average",L10,"Manual +2.5%",K10*1.025, "Manual +5%",K10*1.05, "Manual +10%",K10*1.1, "Manual -2.5%",K10*0.975,"Manual -5%",K10*0.95, "Manual -10%",K10*0.9)} -> 0.25 | J10: Manual | K10: 0.25 | L10: =Calculations!H3 -> 0.26745641 | M10: =Calculations!D3 -> 0.24429061 | N10: =Calculations!E3 -> 0.23383633 | O10: =Calculations!F3 -> 0.25530941 | P10: =Calculations!G3 -> 0.33638928 | R10: Base g | W10: =I14 -> 0.025
A11: Net Income (Common Stockholders) | B11: =B9-B10 -> 23499457 | C11: =C9-C10 -> 26029403 | D11: =D9-D10 -> 28812343 | E11: =E9-E10 -> 31873578 | F11: =F9-F10 -> 35240936 | H11: CapEx as % of Revenue | I11: {=_xlfn.SWITCH(J11,"Manual",K11,"Average",L11,"Manual +2.5%",K11*1.025, "Manual +5%",K11*1.05, "Manual +10%",K11*1.1, "Manual -2.5%",K11*0.975,"Manual -5%",K11*0.95, "Manual -10%",K11*0.9)} -> 0.03 | J11: Manual | K11: 0.03 | L11: =Calculations!H12 -> 0.032912833 | M11: =Calculations!D12 -> 0.037357519 | N11: =Calculations!E12 -> 0.034924411 | O11: =Calculations!F12 -> 0.03179325 | P11: =Calculations!G12 -> 0.027576155 | R11: Δg (Implied − Base) | W11: =W9-W10 -> 0.011109847 | X11: =(W9/(W10))-1 -> 0.44439387
A12: add Interest expense | B12: =B8*(1-$I$10) -> 1800000 | C12: =C8*(1-$I$10) -> 1800000 | D12: =D8*(1-$I$10) -> 1800000 | E12: =E8*(1-$I$10) -> 1800000 | F12: =F8*(1-$I$10) -> 1800000 | H12: Change in Non-Cash WC (ΔWC) | I12: {=_xlfn.SWITCH(J12,"Manual",K12,"Average",L12,"Manual +2.5%",K12*1.025, "Manual +5%",K12*1.05, "Manual +10%",K12*1.1, "Manual -2.5%",K12*0.975,"Manual -5%",K12*0.95, "Manual -10%",K12*0.9)} -> 0.02 | J12: Manual | K12: 0.02 | L12: use 2-5% of Rev Growth or higher (depends on industry)
A13: add D&A | B13: =B3*$I$6 -> 19611983 | C13: =C3*$I$6 -> 21573181 | D13: =D3*$I$6 -> 23730499 | E13: =E3*$I$6 -> 26103549 | F13: =F3*$I$6 -> 28713904 | H13: WACC | I13: {=_xlfn.SWITCH(J13,"Manual",K13,"Calculated",N13,"Manual +2.5%",K13*1.025, "Manual +5%",K13*1.05, "Manual +10%",K13*1.1, "Manual -2.5%",K13*0.975,"Manual -5%",K13*0.95, "Manual -10%",K13*0.9)} -> 0.06 | J13: Manual | K13: 0.06 | L13: Imported from Calculations tab: | N13: =Calculations!C23 -> 0.096068137 | R13: Scenario 2: Implied WACC — Binary Search (20 Iterations)
A14: less Change in Non-Cash WC | B14: =(B3-'Data Schema'!C3)*$I$12 -> 1426326 | C14: =(C3-B3)*$I$12 -> 1568958.6 | D14: =(D3-C3)*$I$12 -> 1725854.5 | E14: =(E3-D3)*$I$12 -> 1898439.9 | F14: =(F3-E3)*$I$12 -> 2088283.9 | H14: Terminal Growth (g) | I14: {=_xlfn.SWITCH(J14,"Manual",K14,"Calculated",N14,"Manual +2.5%",K14*1.025, "Manual +5%",K14*1.05, "Manual +10%",K14*1.1, "Manual -2.5%",K14*0.975,"Manual -5%",K14*0.95, "Manual -10%",K14*0.9)} -> 0.025 | J14: Calculated | K14: 0.03 | L14: Imported from Calculations tab: | N14: =Calculations!C28 -> 0.025 | R14: Iteration | S14: Start | T14: 1 | U14: 2 | V14: 3 | W14: 4 | X14: 5 | Y14: 6 | Z14: 7 | AA14: 8 | AB14: 9 | AC14: 10 | AD14: 11 | AE14: 12 | AF14: 13 | AG14: 14 | AH14: 15 | AI14: 16 | AJ14: 17 | AK14: 18 | AL14: 19 | AM14: 20
A15: less Capital Expenditures (CapEx) | B15: =B3*$I$11 -> 23534379 | C15: =C3*$I$11 -> 25887817 | D15: =D3*$I$11 -> 28476599 | E15: =E3*$I$11 -> 31324258 | F15: =F3*$I$11 -> 34456684 | H15: Capital Structure Assumptions | R15: Low | S15: 0.01 | T15: =IF(S18>$W$3,S17,S15) -> 0.01 | U15: =IF(T18>$W$3,T17,T15) -> 0.01 | V15: =IF(U18>$W$3,U17,U15) -> 0.04625 | W15: =IF(V18>$W$3,V17,V15) -> 0.04625 | X15: =IF(W18>$W$3,W17,W15) -> 0.04625 | Y15: =IF(X18>$W$3,X17,X15) -> 0.04625 | Z15: =IF(Y18>$W$3,Y17,Y15) -> 0.048515625 | AA15: =IF(Z18>$W$3,Z17,Z15) -> 0.049648438 | ... AM15: =IF(AL18>$W$3,AL17,AL15) -> 0.049875774
A16: Free Cash Flow to the Firm (FCFF) | B16: =B11+B12+B13-B14-B15 -> 19950735 | C16: =C11+C12+C13-C14-C15 -> 21945808 | D16: =D11+D12+D13-D14-D15 -> 24140389 | E16: =E11+E12+E13-E14-E15 -> 26554428 | F16: =F11+F12+F13-F14-F15 -> 29209871 | H16: Operating Margin | I16: {=_xlfn.SWITCH(J16,"Forecasted",F18,"Manual",K16,"Average",L16,"Manual +2.5%",K16*1.025, "Manual +5%",K16*1.05, "Manual +10%",K16*1.1, "Manual -2.5%",K16*0.975,"Manual -5%",K16*0.95, "Manual -10%",K16*0.9)} -> 0.043 | J16: Forecasted | K16: 0.03 | L16: =Calculations!H13 -> 0.025569685 | M16: =Calculations!D13 -> 0.030698452 | N16: =Calculations!E13 -> 0.02854101 | O16: =Calculations!F13 -> 0.023932112 | P16: =Calculations!G13 -> 0.019107165 | R16: High | S16: 0.3 | T16: =IF(S18>$W$3,S16,S17) -> 0.155 | U16: =IF(T18>$W$3,T16,T17) -> 0.0825 | V16: =IF(U18>$W$3,U16,U17) -> 0.0825 | W16: =IF(V18>$W$3,V16,V17) -> 0.064375 | X16: =IF(W18>$W$3,W16,W17) -> 0.0553125 | Y16: =IF(X18>$W$3,X16,X17) -> 0.05078125 | Z16: =IF(Y18>$W$3,Y16,Y17) -> 0.05078125 | AA16: =IF(Z18>$W$3,Z16,Z17) -> 0.05078125 | ... AM16: =IF(AL18>$W$3,AL16,AL17) -> 0.049876051
A17: PV of FCFF [FCFFt / (1+WACC)t] | B17: =B16/(1+$I$13)^1 -> 18821448 | C17: =C16/(1+$I$13)^2 -> 19531691 | D17: =D16/(1+$I$13)^3 -> 20268736 | E17: =E16/(1+$I$13)^4 -> 21033594 | F17: =F16/(1+$I$13)^5 -> 21827315 | R17: Mid (Trial WACC) | S17: =(S15+S16)/2 -> 0.155 | T17: =(T15+T16)/2 -> 0.0825 | U17: =(U15+U16)/2 -> 0.04625 | V17: =(V15+V16)/2 -> 0.064375 | W17: =(W15+W16)/2 -> 0.0553125 | X17: =(X15+X16)/2 -> 0.05078125 | Y17: =(Y15+Y16)/2 -> 0.048515625 | Z17: =(Z15+Z16)/2 -> 0.049648438 | ... AM17: =(AM15+AM16)/2 -> 0.049875913
E18: Operating Margin | F18: =(F7/F3) -> 0.043 | R18: EV at Trial WACC | S18: =$B$16/(1+S17)^1+$C$16/(1+S17)^2+$D$16/(1+S17)^3+$E$16/(1+S17)^4+$F$16/(1+S17)^5+$F$16*(1+$I$14)/((S17-$I$14)*(1+S17)^5) -> 1.9057086e+08 | T18: =$B$16/(1+T17)^1+$C$16/(1+T17)^2+$D$16/(1+T17)^3+$E$16/(1+T17)^4+$F$16/(1+T17)^5+$F$16*(1+$I$14)/((T17-$I$14)*(1+T17)^5) -> 4.4548408e+08 | U18: =$B$16/(1+U17)^1+$C$16/(1+U17)^2+$D$16/(1+U17)^3+$E$16/(1+U17)^4+$F$16/(1+U17)^5+$F$16*(1+$I$14)/((U17-$I$14)*(1+U17)^5) -> 1.2295297e+09 | V18: =$B$16/(1+V17)^1+$C$16/(1+V17)^2+$D$16/(1+V17)^3+$E$16/(1+V17)^4+$F$16/(1+V17)^5+$F$16*(1+$I$14)/((V17-$I$14)*(1+V17)^5) -> 6.5682868e+08 | W18: =$B$16/(1+W17)^1+$C$16/(1+W17)^2+$D$16/(1+W17)^3+$E$16/(1+W17)^4+$F$16/(1+W17)^5+$F$16*(1+$I$14)/((W17-$I$14)*(1+W17)^5) -> 8.5749344e+08 | X18: =$B$16/(1+X17)^1+$C$16/(1+X17)^2+$D$16/(1+X17)^3+$E$16/(1+X17)^4+$F$16/(1+X17)^5+$F$16*(1+$I$14)/((X17-$I$14)*(1+X17)^5) -> 1.0107947e+09 | Y18: =$B$16/(1+Y17)^1+$C$16/(1+Y17)^2+$D$16/(1+Y17)^3+$E$16/(1+Y17)^4+$F$16/(1+Y17)^5+$F$16*(1+$I$14)/((Y17-$I$14)*(1+Y17)^5) -> 1.1096188e+09 | Z18: =$B$16/(1+Z17)^1+$C$16/(1+Z17)^2+$D$16/(1+Z17)^3+$E$16/(1+Z17)^4+$F$16/(1+Z17)^5+$F$16*(1+$I$14)/((Z17-$I$14)*(1+Z17)^5) -> 1.0579343e+09 | ... AM18: =$B$16/(1+AM17)^1+$C$16/(1+AM17)^2+$D$16/(1+AM17)^3+$E$16/(1+AM17)^4+$F$16/(1+AM17)^5+$F$16*(1+$I$14)/((AM17-$I$14)*(1+AM17)^5) -> 1.0481237e+09
A20: Base Case DCF | B20: Formula / Rationale | F20: Value | H20: Reverse DCF Summary | M20: Implied | N20: Base | O20: Diff. | P20: % | R20: Implied WACC | W20: =AM17 -> 0.049875913
A21: Terminal Value | B21: FCFfinal year * (1+g)/WACC-g | F21: =F16*(1+I14)/(I13-I14) -> 8.5543194e+08 | H21: Target EV | M21: =W3 -> 1048127860 | N21: =F23 -> 7.4071129e+08 | O21: =M21-N21 -> 3.0741657e+08 | P21: =(M21-N21)/N21 -> 0.41502887 | R21: Base WACC | W21: =I13 -> 0.06
A22: Present Value of Terminal Value | B22: Terminal Value / (1+WACC)n | F22: =F21/(1+I13)^5 -> 6.3922851e+08 | H22: Terminal Growth (g) Only | M22: =W9 -> 0.036109847 | N22: =I14 -> 0.025 | O22: =M22-N22 -> 0.011109847 | P22: =(M22-N22)/N22 -> 0.44439387 | R22: ΔWACC (Implied − Base) | W22: =W20-W21 -> -0.010124087 | X22: =(W20/(W21))-1 -> -0.16873479
A23: Enterprise Value (EV) | B23: PV of FCFs + PV of Terminal Value | F23: =SUM(B17:F17)+F22 -> 7.4071129e+08 | H23: WACC Only | M23: =W20 -> 0.049875913 | N23: =I13 -> 0.06 | O23: =M23-N23 -> -0.010124087 | P23: =(M23-N23)/N23 -> -0.16873479
A24: From Balance Sheet: Cash and Cash Equivalents | F24: ='Data Schema'!C21 -> 10727000 | H24: Revenue Growth Only | M24: =W36 -> 0.19823985 | N24: =W37 -> 0.1 | O24: =M24-N24 -> 0.098239851 | P24: =(M24-N24)/N24 -> 0.98239851 | R24: Scenario 3: Implied Revenue Growth — Shadow DCF + Binary Search
A25: From Balance Sheet: Total Debt | F25: ='Data Schema'!C31 -> 67095000 | H25: Blended Approach (1/3 weight from each) | M25: Implied | N25: Base | O25: Diff. | P25: %
A26: Equity Value | B26: EV - Total Debt + Cash and Cash Equipvalents | F26: =F23-F25+F24 -> 6.8434329e+08 | H26: g | M26: =W41 -> 0.028703282 | N26: =I14 -> 0.025 | O26: =M26-N26 -> 0.0037032823 | P26: =(M26-N26)/N26 -> 0.14813129 | R26: FCFF Margin Factor (m) | W26: =(1-I4-I5)*(1-I10)+I6-I11 -> 0.02725
A27: Shares Outstanding | F27: ='Data Schema'!B17 -> 8022000 | H27: WACC | M27: =W42 -> 0.056625304 | N27: =I13 -> 0.06 | O27: =M27-N27 -> -0.0033746958 | P27: =(M27-N27)/N27 -> -0.05624493 | R27: Base Revenue (R₀) | W27: =B3/(1+I2) -> 713163000
A28: Intrinsic Value per Share | B28: Equity Value / Shares Outstanding | F28: =F26/F27 -> 85.308313 | H28: Revenue Growth | M28: =W43 -> 0.13274662 | N28: =I2 -> 0.1 | O28: =M28-N28 -> 0.032746617 | P28: =(M28-N28)/N28 -> 0.32746617
A29: Current Stock Price | F29: =Calculations!B77 -> 123.63 | H29: Blended EV | M29: =W45 -> 1.0365644e+09 | N29: =F23 -> 7.4071129e+08 | O29: =M29-N29 -> 2.9585312e+08 | P29: =(M29-N29)/N29 -> 0.39941759 | R29: Iteration | S29: Start | T29: 1 | U29: 2 | V29: 3 | W29: 4 | X29: 5 | Y29: 6 | Z29: 7 | AA29: 8 | AB29: 9 | AC29: 10 | AD29: 11 | AE29: 12 | AF29: 13 | AG29: 14 | AH29: 15 | AI29: 16 | AJ29: 17 | AK29: 18 | AL29: 19 | AM29: 20
A30: Valuation Gap % | B30: (Intrinsic Value - Market Price) / Market Price | F30: =(F28-F29)/F29 -> -0.30997077 | H30: Blended Intrinsic Value | J30: VS Market Price: | L30: =W48 -> -0.01165953 | M30: =W47 -> 122.18853 | N30: =F28 -> 85.308313 | O30: =M30-N30 -> 36.880219 | P30: =(M30-N30)/N30 -> 0.43231682 | R30: Low | S30: 0 | T30: =IF(S34>$W$3,S30,S32) -> 0.15 | U30: =IF(T34>$W$3,T30,T32) -> 0.15 | V30: =IF(U34>$W$3,U30,U32) -> 0.1875 | W30: =IF(V34>$W$3,V30,V32) -> 0.1875 | X30: =IF(W34>$W$3,W30,W32) -> 0.196875 | Y30: =IF(X34>$W$3,X30,X32) -> 0.196875 | Z30: =IF(Y34>$W$3,Y30,Y32) -> 0.196875 | AA30: =IF(Z34>$W$3,Z30,Z32) -> 0.19804688 | ... AM30: =IF(AL34>$W$3,AL30,AL32) -> 0.19823971
A31: IRR (5-Year) | B31: (IV/Price)^(1/5) - 1 | F31: =IFERROR((F28/F29)^(1/5)-1,0) -> -0.071517981 | R31: High | S31: 0.3 | T31: =IF(S34>$W$3,S32,S31) -> 0.3 | U31: =IF(T34>$W$3,T32,T31) -> 0.225 | V31: =IF(U34>$W$3,U32,U31) -> 0.225 | W31: =IF(V34>$W$3,V32,V31) -> 0.20625 | X31: =IF(W34>$W$3,W32,W31) -> 0.20625 | Y31: =IF(X34>$W$3,X32,X31) -> 0.2015625 | Z31: =IF(Y34>$W$3,Y32,Y31) -> 0.19921875 | AA31: =IF(Z34>$W$3,Z32,Z31) -> 0.19921875 | ... AM31: =IF(AL34>$W$3,AL32,AL31) -> 0.19823999
A32: 5-Year Total Return % | B32: (IV/Price - 1) × 100% | F32: =F28/F29-1 -> -0.30997077 | R32: Mid (Trial Growth) | S32: =(S30+S31)/2 -> 0.15 | T32: =(T30+T31)/2 -> 0.225 | U32: =(U30+U31)/2 -> 0.1875 | V32: =(V30+V31)/2 -> 0.20625 | W32: =(W30+W31)/2 -> 0.196875 | X32: =(X30+X31)/2 -> 0.2015625 | Y32: =(Y30+Y31)/2 -> 0.19921875 | Z32: =(Z30+Z31)/2 -> 0.19804688 | ... AM32: =(AM30+AM31)/2 -> 0.19823985
R33: FCFF Factor (k) | S33: =(1+S32)*$W$26-S32*$I$12 -> 0.0283375 | T33: =(1+T32)*$W$26-T32*$I$12 -> 0.02888125 | U33: =(1+U32)*$W$26-U32*$I$12 -> 0.028609375 | V33: =(1+V32)*$W$26-V32*$I$12 -> 0.028745313 | W33: =(1+W32)*$W$26-W32*$I$12 -> 0.028677344 | X33: =(1+X32)*$W$26-X32*$I$12 -> 0.028711328 | Y33: =(1+Y32)*$W$26-Y32*$I$12 -> 0.028694336 | Z33: =(1+Z32)*$W$26-Z32*$I$12 -> 0.02868584 | ... AM33: =(1+AM32)*$W$26-AM32*$I$12 -> 0.028687239
A34: Bull Case DCF | H34: DCF Scenario Controller | R34: Shadow EV | S34: =$W$27*S33*(1/(1+$I$13)+(1+S32)/(1+$I$13)^2+(1+S32)^2/(1+$I$13)^3+(1+S32)^3/(1+$I$13)^4+(1+S32)^4/(1+$I$13)^5+(1+S32)^4*(1+$I$14)/(($I$13-$I$14)*(1+$I$13)^5)) -> 8.8646201e+08 | T34: =$W$27*T33*(1/(1+$I$13)+(1+T32)/(1+$I$13)^2+(1+T32)^2/(1+$I$13)^3+(1+T32)^3/(1+$I$13)^4+(1+T32)^4/(1+$I$13)^5+(1+T32)^4*(1+$I$14)/(($I$13-$I$14)*(1+$I$13)^5)) -> 1.147511e+09 | U34: =$W$27*U33*(1/(1+$I$13)+(1+U32)/(1+$I$13)^2+(1+U32)^2/(1+$I$13)^3+(1+U32)^3/(1+$I$13)^4+(1+U32)^4/(1+$I$13)^5+(1+U32)^4*(1+$I$14)/(($I$13-$I$14)*(1+$I$13)^5)) -> 1.0102379e+09 | V34: =$W$27*V33*(1/(1+$I$13)+(1+V32)/(1+$I$13)^2+(1+V32)^2/(1+$I$13)^3+(1+V32)^3/(1+$I$13)^4+(1+V32)^4/(1+$I$13)^5+(1+V32)^4*(1+$I$14)/(($I$13-$I$14)*(1+$I$13)^5)) -> 1.0771233e+09 | W34: =$W$27*W33*(1/(1+$I$13)+(1+W32)/(1+$I$13)^2+(1+W32)^2/(1+$I$13)^3+(1+W32)^3/(1+$I$13)^4+(1+W32)^4/(1+$I$13)^5+(1+W32)^4*(1+$I$14)/(($I$13-$I$14)*(1+$I$13)^5)) -> 1.0432509e+09 | X34: =$W$27*X33*(1/(1+$I$13)+(1+X32)/(1+$I$13)^2+(1+X32)^2/(1+$I$13)^3+(1+X32)^3/(1+$I$13)^4+(1+X32)^4/(1+$I$13)^5+(1+X32)^4*(1+$I$14)/(($I$13-$I$14)*(1+$I$13)^5)) -> 1.0600787e+09 | Y34: =$W$27*Y33*(1/(1+$I$13)+(1+Y32)/(1+$I$13)^2+(1+Y32)^2/(1+$I$13)^3+(1+Y32)^3/(1+$I$13)^4+(1+Y32)^4/(1+$I$13)^5+(1+Y32)^4*(1+$I$14)/(($I$13-$I$14)*(1+$I$13)^5)) -> 1.0516378e+09 | Z34: =$W$27*Z33*(1/(1+$I$13)+(1+Z32)/(1+$I$13)^2+(1+Z32)^2/(1+$I$13)^3+(1+Z32)^3/(1+$I$13)^4+(1+Z32)^4/(1+$I$13)^5+(1+Z32)^4*(1+$I$14)/(($I$13-$I$14)*(1+$I$13)^5)) -> 1.0474376e+09 | ... AM34: =$W$27*AM33*(1/(1+$I$13)+(1+AM32)/(1+$I$13)^2+(1+AM32)^2/(1+$I$13)^3+(1+AM32)^3/(1+$I$13)^4+(1+AM32)^4/(1+$I$13)^5+(1+AM32)^4*(1+$I$14)/(($I$13-$I$14)*(1+$I$13)^5)) -> 1.0481284e+09
A35: Bull Case Forecasted Data (in thousands) | B35: =B2+0 -> 2027 | C35: =B2+1 -> 2028 | D35: =B2+2 -> 2029 | E35: =B2+3 -> 2030 | F35: =B2+4 -> 2031 | H35: Parameter | I35: Bull Case Adj. | J35: Bear Case Adj. | K35: Description
A36: Total Revenue (Net Sales)* | B36: ='Data Schema'!C3*(1+$I$41) -> 8.0587419e+08 | C36: =B36*(1+$I$41) -> 9.1063783e+08 | D36: =C36*(1+$I$41) -> 1.0290208e+09 | E36: =D36*(1+$I$41) -> 1.1627935e+09 | F36: =E36*(1+$I$41) -> 1.3139566e+09 | H36: Revenue Growth % | I36: 0.3 | J36: -0.7 | K36: Multiplier on base growth | R36: Implied Rev Growth | W36: =AM32 -> 0.19823985
A37: less COGS/ Cost of Revenue | B37: =B36*$I$4 -> 6.0440564e+08 | C37: =C36*$I$4 -> 6.8297838e+08 | D37: =D36*$I$4 -> 7.7176556e+08 | E37: =E36*$I$4 -> 8.7209509e+08 | F37: =F36*$I$4 -> 9.8546745e+08 | H37: WACC % | I37: -0.15 | J37: 0.4 | K37: Multiplier on base WACC | R37: Base Rev Growth | W37: =I2 -> 0.1
A38: Gross Profit | B38: =B36-B37 -> 2.0146855e+08 | C38: =C36-C37 -> 2.2765946e+08 | D38: =D36-D37 -> 2.5725519e+08 | E38: =E36-E37 -> 2.9069836e+08 | F38: =F36-F37 -> 3.2848915e+08 | H38: Terminal Growth % | I38: 0.2 | J38: -0.4 | K38: Multiplier on base g | R38: ΔRev Growth (Implied − Base) | W38: =W36-W37 -> 0.098239851 | X38: =(W36/(W37))-1 -> 0.98239851
A39: less OpEx | B39: =B36*($I$5-$I$39) -> 1.5069847e+08 | C39: =C36*($I$5-$I$39) -> 1.7028928e+08 | D39: =D36*($I$5-$I$39) -> 1.9242688e+08 | E39: =E36*($I$5-$I$39) -> 2.1744238e+08 | F39: =F36*($I$5-$I$39) -> 2.4570988e+08 | H39: Op Margin % (abs) | I39: 0.02 | J39: -0.02 | K39: Absolute addition to margin
A40: Operating Income (EBIT) | B40: =B38-B39 -> 50770074 | C40: =C38-C39 -> 57370184 | D40: =D38-D39 -> 64828307 | E40: =E38-E39 -> 73255987 | F40: =F38-F39 -> 82779266 | H40: Adjusted Values | I40: Bull Case | J40: Bear Case | K40: Base Value | R40: Scenario 4: Blended Adjustment (1/3 Weight Each)
A41: less Interest Expense | B41: =$I$8*$I$9 -> 2400000 | C41: =$I$8*$I$9 -> 2400000 | D41: =$I$8*$I$9 -> 2400000 | E41: =$I$8*$I$9 -> 2400000 | F41: =$I$8*$I$9 -> 2400000 | H41: Revenue Growth | I41: =K41*(1+I36) -> 0.13 | J41: =K41*(1+J36) -> 0.03 | K41: =I2 -> 0.1 | R41: Blended g | W41: =I14+(W9-I14)/3 -> 0.028703282
A42: EBT (Pretax Income) | B42: =B40-B41 -> 48370074 | C42: =C40-C41 -> 54970184 | D42: =D40-D41 -> 62428307 | E42: =E40-E41 -> 70855987 | F42: =F40-F41 -> 80379266 | H42: WACC | I42: =K42*(1+I37) -> 0.051 | J42: =K42*(1+J37) -> 0.084 | K42: =I13 -> 0.06 | R42: Blended WACC | W42: =I13+(W20-I13)/3 -> 0.056625304
A43: less Income Tax Expense/Tax Provision | B43: =B42*$I$10 -> 12092518 | C43: =C42*$I$10 -> 13742546 | D43: =D42*$I$10 -> 15607077 | E43: =E42*$I$10 -> 17713997 | F43: =F42*$I$10 -> 20094816 | H43: Terminal Growth | I43: =K43*(1+I38) -> 0.03 | J43: =K43*(1+J38) -> 0.015 | K43: =I14 -> 0.025 | R43: Blended Rev Growth | W43: =I2+(W36-I2)/3 -> 0.13274662
A44: Net Income (Common Stockholders) | B44: =B42-B43 -> 36277555 | C44: =C42-C43 -> 41227638 | D44: =D42-D43 -> 46821231 | E44: =E42-E43 -> 53141991 | F44: =F42-F43 -> 60284449 | H44: Op Margin Effect | I44: =K44+I39 -> 0.063 | J44: =K44+J39 -> 0.023 | K44: =I16 -> 0.043 | R44: Blended FCFF Factor | W44: =(1+W43)*W26-W43*I12 -> 0.028212413
A45: add Interest expense | B45: =B41*(1-$I$10) -> 1800000 | C45: =C41*(1-$I$10) -> 1800000 | D45: =D41*(1-$I$10) -> 1800000 | E45: =E41*(1-$I$10) -> 1800000 | F45: =F41*(1-$I$10) -> 1800000 | R45: Blended Enterprise Value | W45: =W27*W44*(1/(1+W42)+(1+W43)/(1+W42)^2+(1+W43)^2/(1+W42)^3+(1+W43)^3/(1+W42)^4+(1+W43)^4/(1+W42)^5+(1+W43)^4*(1+W41)/((W42-W41)*(1+W42)^5)) -> 1.0365644e+09
A46: add D&A | B46: =B36*$I$6 -> 20146855 | C46: =C36*$I$6 -> 22765946 | D46: =D36*$I$6 -> 25725519 | E46: =E36*$I$6 -> 29069836 | F46: =F36*$I$6 -> 32848915 | R46: Blended Equity Value | W46: =W45-F25+F24 -> 9.8019641e+08
A47: less Change in Non-Cash WC | B47: =(B36-'Data Schema'!C3)*$I$12 -> 1854223.8 | C47: =(C36-B36)*$I$12 -> 2095272.9 | D47: =(D36-C36)*$I$12 -> 2367658.4 | E47: =(E36-D36)*$I$12 -> 2675454 | F47: =(F36-E36)*$I$12 -> 3023263 | H47: DCF Scenario Summary | I47: Bull Case | J47: Base Case | K47: Bear Case | R47: Blended Intrinsic Value/Share | W47: =W46/F27 -> 122.18853
A48: less Capital Expenditures (CapEx) | B48: =B36*$I$11 -> 24176226 | C48: =C36*$I$11 -> 27319135 | D48: =D36*$I$11 -> 30870623 | E48: =E36*$I$11 -> 34883804 | F48: =F36*$I$11 -> 39418698 | H48: Intrinsic Value | I48: =F60 -> 265.43046 | J48: =F28 -> 85.308313 | K48: =F92 -> 9.2519813 | R48: Blended vs. Market Price | W48: =(W47-F29)/F29 -> -0.01165953
A49: Free Cash Flow to the Firm (FCFF) | B49: =B44+B45+B46-B47-B48 -> 32193961 | C49: =C44+C45+C46-C47-C48 -> 36379176 | D49: =D44+D45+D46-D47-D48 -> 41108468 | E49: =E44+E45+E46-E47-E48 -> 46452569 | F49: =F44+F45+F46-F47-F48 -> 52491403 | H49: Valuation Gap % | I49: =F62 -> 1.1469746 | J49: =F30 -> -0.30997077 | K49: =F94 -> -0.92516395
A50: PV of FCFF [FCFFt / (1+WACC)^t] | B50: =B49/(1+$I$42)^1 -> 30631742 | C50: =C49/(1+$I$42)^2 -> 32934223 | D50: =D49/(1+$I$42)^3 -> 35409774 | E50: =E49/(1+$I$42)^4 -> 38071403 | F50: =F49/(1+$I$42)^5 -> 40933097 | H50: IRR (5-Year) | I50: =F63 -> 0.16510584 | J50: =IFERROR((F28/F29)^(1/5)-1,0) -> -0.071517981 | K50: =F95 -> -0.4045817
H51: 5-Yr Total Return | I51: =F64 -> 1.1469746 | J51: =F28/F29-1 -> -0.30997077 | K51: =F96 -> -0.92516395
A52: Bull Case DCF | B52: Formula / Rationale | F52: Value
A53: Terminal Value | B53: FCFF_final × (1+g)/(WACC-g) | F53: =F49*(1+$I$43)/($I$42-$I$43) -> 2.5745784e+09
A54: Present Value of Terminal Value | B54: TV / (1+WACC)^5 | F54: =F53/(1+$I$42)^5 -> 2.0076709e+09
A55: Enterprise Value (EV) | B55: PV of FCFs + PV of Terminal Value | F55: =SUM(B50:F50)+F54 -> 2.1856512e+09
A56: Cash and Cash Equivalents | B56: From Balance Sheet | F56: ='Data Schema'!C21 -> 10727000
A57: Total Debt | B57: From Balance Sheet | F57: ='Data Schema'!C31 -> 67095000
A58: Equity Value | B58: EV - Debt + Cash | F58: =F55-F57+F56 -> 2.1292832e+09
A59: Shares Outstanding | F59: ='Data Schema'!B17 -> 8022000
A60: Intrinsic Value per Share | B60: Equity Value / Shares | F60: =F58/F59 -> 265.43046
A61: Current Stock Price | F61: =F29 -> 123.63
A62: Valuation Gap % | B62: (Intrinsic - Market) / Market | F62: =(F60-F61)/F61 -> 1.1469746
A63: IRR (5-Year) | B63: (IV/Price)^(1/5) - 1 | F63: =IFERROR((F60/F61)^(1/5)-1,0) -> 0.16510584
A64: 5-Year Total Return % | B64: (IV/Price - 1) × 100% | F64: =F60/F61-1 -> 1.1469746
A66: Bear Case DCF
A67: Bear Case Forecasted Data (in thousands) | B67: =B2+0 -> 2027 | C67: =B2+1 -> 2028 | D67: =B2+2 -> 2029 | E67: =B2+3 -> 2030 | F67: =B2+4 -> 2031
A68: Total Revenue (Net Sales)* | B68: ='Data Schema'!C3*(1+$J$41) -> 734557890 | C68: =B68*(1+$J$41) -> 7.5659463e+08 | D68: =C68*(1+$J$41) -> 7.7929247e+08 | E68: =D68*(1+$J$41) -> 8.0267124e+08 | F68: =E68*(1+$J$41) -> 8.2675138e+08
A69: less COGS/ Cost of Revenue | B69: =B68*$I$4 -> 5.5091842e+08 | C69: =C68*$I$4 -> 5.6744597e+08 | D69: =D68*$I$4 -> 5.8446935e+08 | E69: =E68*$I$4 -> 6.0200343e+08 | F69: =F68*$I$4 -> 6.2006353e+08
A70: Gross Profit | B70: =B68-B69 -> 1.8363947e+08 | C70: =C68-C69 -> 1.8914866e+08 | D70: =D68-D69 -> 1.9482312e+08 | E70: =E68-E69 -> 2.0066781e+08 | F70: =F68-F69 -> 2.0668784e+08
A71: less OpEx | B71: =B68*($I$5-$J$39) -> 1.6674464e+08 | C71: =C68*($I$5-$J$39) -> 1.7174698e+08 | D71: =D68*($I$5-$J$39) -> 1.7689939e+08 | E71: =E68*($I$5-$J$39) -> 1.8220637e+08 | F71: =F68*($I$5-$J$39) -> 1.8767256e+08
A72: Operating Income (EBIT) | B72: =B70-B71 -> 16894831 | C72: =C70-C71 -> 17401676 | D72: =D70-D71 -> 17923727 | E72: =E70-E71 -> 18461439 | F72: =F70-F71 -> 19015282
A73: less Interest Expense | B73: =$I$8*$I$9 -> 2400000 | C73: =$I$8*$I$9 -> 2400000 | D73: =$I$8*$I$9 -> 2400000 | E73: =$I$8*$I$9 -> 2400000 | F73: =$I$8*$I$9 -> 2400000
A74: EBT (Pretax Income) | B74: =B72-B73 -> 14494831 | C74: =C72-C73 -> 15001676 | D74: =D72-D73 -> 15523727 | E74: =E72-E73 -> 16061439 | F74: =F72-F73 -> 16615282
A75: less Income Tax Expense/Tax Provision | B75: =B74*$I$10 -> 3623707.9 | C75: =C74*$I$10 -> 3750419.1 | D75: =D74*$I$10 -> 3880931.7 | E75: =E74*$I$10 -> 4015359.6 | F75: =F74*$I$10 -> 4153820.4
A76: Net Income (Common Stockholders) | B76: =B74-B75 -> 10871124 | C76: =C74-C75 -> 11251257 | D76: =D74-D75 -> 11642795 | E76: =E74-E75 -> 12046079 | F76: =F74-F75 -> 12461461
A77: add Interest expense | B77: =B73*(1-$I$10) -> 1800000 | C77: =C73*(1-$I$10) -> 1800000 | D77: =D73*(1-$I$10) -> 1800000 | E77: =E73*(1-$I$10) -> 1800000 | F77: =F73*(1-$I$10) -> 1800000
A78: add D&A | B78: =B68*$I$6 -> 18363947 | C78: =C68*$I$6 -> 18914866 | D78: =D68*$I$6 -> 19482312 | E78: =E68*$I$6 -> 20066781 | F78: =F68*$I$6 -> 20668784
A79: less Change in Non-Cash WC | B79: =(B68-'Data Schema'!C3)*$I$12 -> 427897.8 | C79: =(C68-B68)*$I$12 -> 440734.73 | D79: =(D68-C68)*$I$12 -> 453956.78 | E79: =(E68-D68)*$I$12 -> 467575.48 | F79: =(F68-E68)*$I$12 -> 481602.74
A80: less Capital Expenditures (CapEx) | B80: =B68*$I$11 -> 22036737 | C80: =C68*$I$11 -> 22697839 | D80: =D68*$I$11 -> 23378774 | E80: =E68*$I$11 -> 24080137 | F80: =F68*$I$11 -> 24802541
A81: Free Cash Flow to the Firm (FCFF) | B81: =B76+B77+B78-B79-B80 -> 8570436.4 | C81: =C76+C77+C78-C79-C80 -> 8827549.4 | D81: =D76+D77+D78-D79-D80 -> 9092375.9 | E81: =E76+E77+E78-E79-E80 -> 9365147.2 | F81: =F76+F77+F78-F79-F80 -> 9646101.6
A82: PV of FCFF [FCFFt / (1+WACC)^t] | B82: =B81/(1+$J$42)^1 -> 7906306.6 | C82: =C81/(1+$J$42)^2 -> 7512450 | D82: =D81/(1+$J$42)^3 -> 7138213.6 | E82: =E81/(1+$J$42)^4 -> 6782619.9 | F82: =F81/(1+$J$42)^5 -> 6444740.3
A84: Bear Case DCF | B84: Formula / Rationale | F84: Value
A85: Terminal Value | B85: FCFF_final × (1+g)/(WACC-g) | F85: =F81*(1+$J$43)/($J$42-$J$43) -> 1.4189555e+08
A86: Present Value of Terminal Value | B86: TV / (1+WACC)^5 | F86: =F85/(1+$J$42)^5 -> 94803064
A87: Enterprise Value (EV) | B87: PV of FCFs + PV of Terminal Value | F87: =SUM(B82:F82)+F86 -> 1.3058739e+08
A88: Cash and Cash Equivalents | B88: From Balance Sheet | F88: ='Data Schema'!C21 -> 10727000
A89: Total Debt | B89: From Balance Sheet | F89: ='Data Schema'!C31 -> 67095000
A90: Equity Value | B90: EV - Debt + Cash | F90: =F87-F89+F88 -> 74219394
A91: Shares Outstanding | F91: ='Data Schema'!B17 -> 8022000
A92: Intrinsic Value per Share | B92: Equity Value / Shares | F92: =F90/F91 -> 9.2519813
A93: Current Stock Price | F93: =F29 -> 123.63
A94: Valuation Gap % | B94: (Intrinsic - Market) / Market | F94: =(F92-F93)/F93 -> -0.92516395
A95: IRR (5-Year) | B95: (IV/Price)^(1/5) - 1 | F95: =IFERROR((F92/F93)^(1/5)-1,0) -> -0.4045817
A96: 5-Year Total Return % | B96: (IV/Price - 1) × 100% | F96: =F92/F93-1 -> -0.92516395
A99: Peer Multiples
A100: Method | B100: Formula | C100: Peer Avg Multiple | D100: Implied Value/Share | E100: Toggle → | F100: On
A101: P/E Method | B101: Peer Avg P/E × EPS | C101: ='Data Schema'!F44 -> 27.556667 | D101: =IF($F$100="Off","N/A",IFERROR('Data Schema'!F44*'Data Schema'!C16,"N/A")) -> 75.2297
A102: P/B Method | B102: Peer Avg P/B × BVPS | C102: ='Data Schema'!F47 -> 6.61 | D102: =IF($F$100="Off","N/A",IFERROR('Data Schema'!F47*Calculations!D2,"N/A")) -> 88.072506
A103: P/S Method | B103: Peer Avg P/S × Rev/Share | C103: ='Data Schema'!F48 -> 0.88 | D103: =IF($F$100="Off","N/A",IFERROR('Data Schema'!F48*'Data Schema'!C3/'Data Schema'!B17,"N/A")) -> 78.23279
A104: EV/EBITDA Method | B104: Peer Avg EV/EBITDA × EBITDA → Equity/Share | C104: ='Data Schema'!F49 -> 16.943333 | D104: =IF($F$100="Off","N/A",IFERROR(('Data Schema'!F49*'Data Schema'!C15-'Data Schema'!C31+'Data Schema'!C21)/'Data Schema'!B17,"N/A")) -> 91.125111
A105: P/FCF Method | B105: Peer Avg P/FCF × FCF/Share | C105: ='Data Schema'!F46 -> 25.733333 | D105: =IF($F$100="Off","N/A",IFERROR('Data Schema'!F46*'Data Schema'!C40/'Data Schema'!B17,"N/A")) -> 47.870672
...

Sheet Data Schema
A1: Historical Data from 10K all numbers in thousands | B1: TTM | C1: =D1+1 -> 2026 | D1: =E1+1 -> 2025 | E1: =F1+1 -> 2024 | F1: =YEAR('Raw Data Pasting'!A7) -> 2023 | G1: 0
A2: Income Statement Items (column A Data Tab) | G2: 0
A3: Total Revenue (Net Sales)* | B3: {=IFERROR(INDEX('Raw Data Pasting'!$A:$A, MATCH("Total Revenue", 'Raw Data Pasting'!$A:$A, 0) + MATCH(B$1, $B$1:$F$1, 0)),0)} -> 713163000 | C3: {=IFERROR(INDEX('Raw Data Pasting'!$A:$A, MATCH("Total Revenue", 'Raw Data Pasting'!$A:$A, 0) + MATCH(C$1, $B$1:$F$1, 0)),0)} -> 713163000 | D3: {=IFERROR(INDEX('Raw Data Pasting'!$A:$A, MATCH("Total Revenue", 'Raw Data Pasting'!$A:$A, 0) + MATCH(D$1, $B$1:$F$1, 0)),0)} -> 680985000 | E3: {=IFERROR(INDEX('Raw Data Pasting'!$A:$A, MATCH("Total Revenue", 'Raw Data Pasting'!$A:$A, 0) + MATCH(E$1, $B$1:$F$1, 0)),0)} -> 648125000 | F3: {=IFERROR(INDEX('Raw Data Pasting'!$A:$A, MATCH("Total Revenue", 'Raw Data Pasting'!$A:$A, 0) + MATCH(F$1, $B$1:$F$1, 0)),0)} -> 611289000 | G3: 0
A4: less COGS/ Cost of Revenue | B4: {=IFERROR(INDEX('Raw Data Pasting'!$A:$A, MATCH("Cost Of Revenue", 'Raw Data Pasting'!$A:$A, 0) + MATCH(B$1, $B$1:$F$1, 0)),0)} -> 535395000 | C4: {=IFERROR(INDEX('Raw Data Pasting'!$A:$A, MATCH("Cost Of Revenue", 'Raw Data Pasting'!$A:$A, 0) + MATCH(C$1, $B$1:$F$1, 0)),0)} -> 535395000 | D4: {=IFERROR(INDEX('Raw Data Pasting'!$A:$A, MATCH("Cost Of Revenue", 'Raw Data Pasting'!$A:$A, 0) + MATCH(D$1, $B$1:$F$1, 0)),0)} -> 511753000 | E4: {=IFERROR(INDEX('Raw Data Pasting'!$A:$A, MATCH("Cost Of Revenue", 'Raw Data Pasting'!$A:$A, 0) + MATCH(E$1, $B$1:$F$1, 0)),0)} -> 490142000 | F4: {=IFERROR(INDEX('Raw Data Pasting'!$A:$A, MATCH("Cost Of Revenue", 'Raw Data Pasting'!$A:$A, 0) + MATCH(F$1, $B$1:$F$1, 0)),0)} -> 463721000 | G4: 0
A5: Gross Profit | B5: {=IFERROR(INDEX('Raw Data Pasting'!$A:$A, MATCH("Gross Profit", 'Raw Data Pasting'!$A:$A, 0) + MATCH(B$1, $B$1:$F$1, 0)),0)} -> 177768000 | C5: {=IFERROR(INDEX('Raw Data Pasting'!$A:$A, MATCH("Gross Profit", 'Raw Data Pasting'!$A:$A, 0) + MATCH(C$1, $B$1:$F$1, 0)),0)} -> 177768000 | D5: {=IFERROR(INDEX('Raw Data Pasting'!$A:$A, MATCH("Gross Profit", 'Raw Data Pasting'!$A:$A, 0) + MATCH(D$1, $B$1:$F$1, 0)),0)} -> 169232000 | E5: {=IFERROR(INDEX('Raw Data Pasting'!$A:$A, MATCH("Gross Profit", 'Raw Data Pasting'!$A:$A, 0) + MATCH(E$1, $B$1:$F$1, 0)),0)} -> 157983000 | F5: {=IFERROR(INDEX('Raw Data Pasting'!$A:$A, MATCH("Gross Profit", 'Raw Data Pasting'!$A:$A, 0) + MATCH(F$1, $B$1:$F$1, 0)),0)} -> 147568000 | G5: 0
A6: less Op Ex / Non Interest Ex | B6: {=IFERROR( IF(INDEX('Raw Data Pasting'!$A:$A, MATCH("Operating Expense", 'Raw Data Pasting'!$A:$A, 0) + MATCH(B$1, $B$1:$F$1, 0))="--", 0, INDEX('Raw Data Pasting'!$A:$A, MATCH("Operating Expense", 'Raw Data Pasting'!$A:$A, 0) + MATCH(B$1, $B$1:$F$1, 0))), IFERROR( IF(INDEX('Raw Data Pasting'!$A:$A, MATCH("Non Interest Expense", 'Raw Data Pasting'!$A:$A, 0) + MATCH(B$1, $B$1:$F$1, 0))="--", 0, INDEX('Raw Data Pasting'!$A:$A, MATCH("Non Interest Expense", 'Raw Data Pasting'!$A:$A, 0) + MATCH(B$1, $B$1:$F$1, 0))), "N/A" ) )} -> 147943000 | C6: {=IFERROR( IF(INDEX('Raw Data Pasting'!$A:$A, MATCH("Operating Expense", 'Raw Data Pasting'!$A:$A, 0) + MATCH(C$1, $B$1:$F$1, 0))="--", 0, INDEX('Raw Data Pasting'!$A:$A, MATCH("Operating Expense", 'Raw Data Pasting'!$A:$A, 0) + MATCH(C$1, $B$1:$F$1, 0))), IFERROR( IF(INDEX('Raw Data Pasting'!$A:$A, MATCH("Non Interest Expense", 'Raw Data Pasting'!$A:$A, 0) + MATCH(C$1, $B$1:$F$1, 0))="--", 0, INDEX('Raw Data Pasting'!$A:$A, MATCH("Non Interest Expense", 'Raw Data Pasting'!$A:$A, 0) + MATCH(C$1, $B$1:$F$1, 0))), "N/A" ) )} -> 147943000 | D6: {=IFERROR( IF(INDEX('Raw Data Pasting'!$A:$A, MATCH("Operating Expense", 'Raw Data Pasting'!$A:$A, 0) + MATCH(D$1, $B$1:$F$1, 0))="--", 0, INDEX('Raw Data Pasting'!$A:$A, MATCH("Operating Expense", 'Raw Data Pasting'!$A:$A, 0) + MATCH(D$1, $B$1:$F$1, 0))), IFERROR( IF(INDEX('Raw Data Pasting'!$A:$A, MATCH("Non Interest Expense", 'Raw Data Pasting'!$A:$A, 0) + MATCH(D$1, $B$1:$F$1, 0))="--", 0, INDEX('Raw Data Pasting'!$A:$A, MATCH("Non Interest Expense", 'Raw Data Pasting'!$A:$A, 0) + MATCH(D$1, $B$1:$F$1, 0))), "N/A" ) )} -> 139884000 | E6: {=IFERROR( IF(INDEX('Raw Data Pasting'!$A:$A, MATCH("Operating Expense", 'Raw Data Pasting'!$A:$A, 0) + MATCH(E$1, $B$1:$F$1, 0))="--", 0, INDEX('Raw Data Pasting'!$A:$A, MATCH("Operating Expense", 'Raw Data Pasting'!$A:$A, 0) + MATCH(E$1, $B$1:$F$1, 0))), IFERROR( IF(INDEX('Raw Data Pasting'!$A:$A, MATCH("Non Interest Expense", 'Raw Data Pasting'!$A:$A, 0) + MATCH(E$1, $B$1:$F$1, 0))="--", 0, INDEX('Raw Data Pasting'!$A:$A, MATCH("Non Interest Expense", 'Raw Data Pasting'!$A:$A, 0) + MATCH(E$1, $B$1:$F$1, 0))), "N/A" ) )} -> 130971000 | F6: {=IFERROR( IF(INDEX('Raw Data Pasting'!$A:$A, MATCH("Operating Expense", 'Raw Data Pasting'!$A:$A, 0) + MATCH(F$1, $B$1:$F$1, 0))="--", 0, INDEX('Raw Data Pasting'!$A:$A, MATCH("Operating Expense", 'Raw Data Pasting'!$A:$A, 0) + MATCH(F$1, $B$1:$F$1, 0))), IFERROR( IF(INDEX('Raw Data Pasting'!$A:$A, MATCH("Non Interest Expense", 'Raw Data Pasting'!$A:$A, 0) + MATCH(F$1, $B$1:$F$1, 0))="--", 0, INDEX('Raw Data Pasting'!$A:$A, MATCH("Non Interest Expense", 'Raw Data Pasting'!$A:$A, 0) + MATCH(F$1, $B$1:$F$1, 0))), "N/A" ) )} -> 127140000 | G6: 0
A7: Operating Income (EBIT) | B7: {=IFERROR(INDEX('Raw Data Pasting'!$A:$A, MATCH("Operating Income", 'Raw Data Pasting'!$A:$A, 0) + MATCH(B$1, $B$1:$F$1, 0)),0)} -> 29825000 | C7: {=IFERROR(INDEX('Raw Data Pasting'!$A:$A, MATCH("Operating Income", 'Raw Data Pasting'!$A:$A, 0) + MATCH(C$1, $B$1:$F$1, 0)),0)} -> 29825000 | D7: {=IFERROR(INDEX('Raw Data Pasting'!$A:$A, MATCH("Operating Income", 'Raw Data Pasting'!$A:$A, 0) + MATCH(D$1, $B$1:$F$1, 0)),0)} -> 29348000 | E7: {=IFERROR(INDEX('Raw Data Pasting'!$A:$A, MATCH("Operating Income", 'Raw Data Pasting'!$A:$A, 0) + MATCH(E$1, $B$1:$F$1, 0)),0)} -> 27012000 | F7: {=IFERROR(INDEX('Raw Data Pasting'!$A:$A, MATCH("Operating Income", 'Raw Data Pasting'!$A:$A, 0) + MATCH(F$1, $B$1:$F$1, 0)),0)} -> 20428000 | G7: 0
A8: add Interest Income (Non Op) | B8: {=IFERROR(INDEX('Raw Data Pasting'!$A:$A, MATCH("Interest Income", 'Raw Data Pasting'!$A:$A, 0) + MATCH(B$1, $B$1:$F$1, 0)),0)} -> 368000 | C8: {=IFERROR(INDEX('Raw Data Pasting'!$A:$A, MATCH("Interest Income", 'Raw Data Pasting'!$A:$A, 0) + MATCH(C$1, $B$1:$F$1, 0)),0)} -> 368000 | D8: {=IFERROR(INDEX('Raw Data Pasting'!$A:$A, MATCH("Interest Income", 'Raw Data Pasting'!$A:$A, 0) + MATCH(D$1, $B$1:$F$1, 0)),0)} -> 483000 | E8: {=IFERROR(INDEX('Raw Data Pasting'!$A:$A, MATCH("Interest Income", 'Raw Data Pasting'!$A:$A, 0) + MATCH(E$1, $B$1:$F$1, 0)),0)} -> 546000 | F8: {=IFERROR(INDEX('Raw Data Pasting'!$A:$A, MATCH("Interest Income", 'Raw Data Pasting'!$A:$A, 0) + MATCH(F$1, $B$1:$F$1, 0)),0)} -> 254000 | G8: 0
A9: less Interest Expense (Non Op) | B9: {=IFERROR(INDEX('Raw Data Pasting'!$A:$A, MATCH("Interest Expense", 'Raw Data Pasting'!$A:$A, 0) + MATCH(B$1, $B$1:$F$1, 0)),0)} -> 2799000 | C9: {=IFERROR(INDEX('Raw Data Pasting'!$A:$A, MATCH("Interest Expense", 'Raw Data Pasting'!$A:$A, 0) + MATCH(C$1, $B$1:$F$1, 0)),0)} -> 2799000 | D9: {=IFERROR(INDEX('Raw Data Pasting'!$A:$A, MATCH("Interest Expense", 'Raw Data Pasting'!$A:$A, 0) + MATCH(D$1, $B$1:$F$1, 0)),0)} -> 2728000 | E9: {=IFERROR(INDEX('Raw Data Pasting'!$A:$A, MATCH("Interest Expense", 'Raw Data Pasting'!$A:$A, 0) + MATCH(E$1, $B$1:$F$1, 0)),0)} -> 2683000 | F9: {=IFERROR(INDEX('Raw Data Pasting'!$A:$A, MATCH("Interest Expense", 'Raw Data Pasting'!$A:$A, 0) + MATCH(F$1, $B$1:$F$1, 0)),0)} -> 2128000 | G9: 0
A10: add Other Special Income | B10: {=IFERROR(IF(INDEX('Raw Data Pasting'!$A:$A,MATCH("Other Income Expense",'Raw Data Pasting'!$A:$A,0)+MATCH(B$1,$B$1:$F$1,0))="--",0,(INDEX('Raw Data Pasting'!$A:$A,MATCH("Other Income Expense",'Raw Data Pasting'!$A:$A,0)+MATCH(B$1,$B$1:$F$1,0)))), "N/A")} -> 2075000 | C10: {=IFERROR(IF(INDEX('Raw Data Pasting'!$A:$A,MATCH("Other Income Expense",'Raw Data Pasting'!$A:$A,0)+MATCH(C$1,$B$1:$F$1,0))="--",0,(INDEX('Raw Data Pasting'!$A:$A,MATCH("Other Income Expense",'Raw Data Pasting'!$A:$A,0)+MATCH(C$1,$B$1:$F$1,0)))), "N/A")} -> 2075000 | D10: {=IFERROR(IF(INDEX('Raw Data Pasting'!$A:$A,MATCH("Other Income Expense",'Raw Data Pasting'!$A:$A,0)+MATCH(D$1,$B$1:$F$1,0))="--",0,(INDEX('Raw Data Pasting'!$A:$A,MATCH("Other Income Expense",'Raw Data Pasting'!$A:$A,0)+MATCH(D$1,$B$1:$F$1,0)))), "N/A")} -> -794000 | E10: {=IFERROR(IF(INDEX('Raw Data Pasting'!$A:$A,MATCH("Other Income Expense",'Raw Data Pasting'!$A:$A,0)+MATCH(E$1,$B$1:$F$1,0))="--",0,(INDEX('Raw Data Pasting'!$A:$A,MATCH("Other Income Expense",'Raw Data Pasting'!$A:$A,0)+MATCH(E$1,$B$1:$F$1,0)))), "N/A")} -> -3027000 | F10: {=IFERROR(IF(INDEX('Raw Data Pasting'!$A:$A,MATCH("Other Income Expense",'Raw Data Pasting'!$A:$A,0)+MATCH(F$1,$B$1:$F$1,0))="--",0,(INDEX('Raw Data Pasting'!$A:$A,MATCH("Other Income Expense",'Raw Data Pasting'!$A:$A,0)+MATCH(F$1,$B$1:$F$1,0)))), "N/A")} -> -1538000 | G10: 0
A11: Earnings Before Tax (Pretax Income) | B11: {=IFERROR(INDEX('Raw Data Pasting'!$A:$A, MATCH("Pretax Income", 'Raw Data Pasting'!$A:$A, 0) + MATCH(B$1, $B$1:$F$1, 0)),0)} -> 29469000 | C11: {=IFERROR(INDEX('Raw Data Pasting'!$A:$A, MATCH("Pretax Income", 'Raw Data Pasting'!$A:$A, 0) + MATCH(C$1, $B$1:$F$1, 0)),0)} -> 29469000 | D11: {=IFERROR(INDEX('Raw Data Pasting'!$A:$A, MATCH("Pretax Income", 'Raw Data Pasting'!$A:$A, 0) + MATCH(D$1, $B$1:$F$1, 0)),0)} -> 26309000 | E11: {=IFERROR(INDEX('Raw Data Pasting'!$A:$A, MATCH("Pretax Income", 'Raw Data Pasting'!$A:$A, 0) + MATCH(E$1, $B$1:$F$1, 0)),0)} -> 21848000 | F11: {=IFERROR(INDEX('Raw Data Pasting'!$A:$A, MATCH("Pretax Income", 'Raw Data Pasting'!$A:$A, 0) + MATCH(F$1, $B$1:$F$1, 0)),0)} -> 17016000 | G11: 0
A12: less Income Tax Expense/Tax Provision | B12: {=IFERROR(INDEX('Raw Data Pasting'!$A:$A, MATCH("Tax Provision", 'Raw Data Pasting'!$A:$A, 0) + MATCH(B$1, $B$1:$F$1, 0)),0)} -> 7199000 | C12: {=IFERROR(INDEX('Raw Data Pasting'!$A:$A, MATCH("Tax Provision", 'Raw Data Pasting'!$A:$A, 0) + MATCH(C$1, $B$1:$F$1, 0)),0)} -> 7199000 | D12: {=IFERROR(INDEX('Raw Data Pasting'!$A:$A, MATCH("Tax Provision", 'Raw Data Pasting'!$A:$A, 0) + MATCH(D$1, $B$1:$F$1, 0)),0)} -> 6152000 | E12: {=IFERROR(INDEX('Raw Data Pasting'!$A:$A, MATCH("Tax Provision", 'Raw Data Pasting'!$A:$A, 0) + MATCH(E$1, $B$1:$F$1, 0)),0)} -> 5578000 | F12: {=IFERROR(INDEX('Raw Data Pasting'!$A:$A, MATCH("Tax Provision", 'Raw Data Pasting'!$A:$A, 0) + MATCH(F$1, $B$1:$F$1, 0)),0)} -> 5724000 | G12: 0
A13: Net Income (Common Stockholders) | B13: {=IFERROR(INDEX('Raw Data Pasting'!$A:$A, MATCH("Net Income Common Stockholders", 'Raw Data Pasting'!$A:$A, 0) + MATCH(B$1, $B$1:$F$1, 0)),0)} -> 21893000 | C13: {=IFERROR(INDEX('Raw Data Pasting'!$A:$A, MATCH("Net Income Common Stockholders", 'Raw Data Pasting'!$A:$A, 0) + MATCH(C$1, $B$1:$F$1, 0)),0)} -> 21893000 | D13: {=IFERROR(INDEX('Raw Data Pasting'!$A:$A, MATCH("Net Income Common Stockholders", 'Raw Data Pasting'!$A:$A, 0) + MATCH(D$1, $B$1:$F$1, 0)),0)} -> 19436000 | E13: {=IFERROR(INDEX('Raw Data Pasting'!$A:$A, MATCH("Net Income Common Stockholders", 'Raw Data Pasting'!$A:$A, 0) + MATCH(E$1, $B$1:$F$1, 0)),0)} -> 15511000 | F13: {=IFERROR(INDEX('Raw Data Pasting'!$A:$A, MATCH("Net Income Common Stockholders", 'Raw Data Pasting'!$A:$A, 0) + MATCH(F$1, $B$1:$F$1, 0)),0)} -> 11680000 | G13: 0
A14: EBIT (Adjusted) | B14: {=IFERROR(INDEX('Raw Data Pasting'!$A:$A, MATCH("EBIT", 'Raw Data Pasting'!$A:$A, 0) + MATCH(B$1, $B$1:$F$1, 0)),0)} -> 32268000 | C14: {=IFERROR(INDEX('Raw Data Pasting'!$A:$A, MATCH("EBIT", 'Raw Data Pasting'!$A:$A, 0) + MATCH(C$1, $B$1:$F$1, 0)),0)} -> 32268000 | D14: {=IFERROR(INDEX('Raw Data Pasting'!$A:$A, MATCH("EBIT", 'Raw Data Pasting'!$A:$A, 0) + MATCH(D$1, $B$1:$F$1, 0)),0)} -> 29037000 | E14: {=IFERROR(INDEX('Raw Data Pasting'!$A:$A, MATCH("EBIT", 'Raw Data Pasting'!$A:$A, 0) + MATCH(E$1, $B$1:$F$1, 0)),0)} -> 24531000 | F14: {=IFERROR(INDEX('Raw Data Pasting'!$A:$A, MATCH("EBIT", 'Raw Data Pasting'!$A:$A, 0) + MATCH(F$1, $B$1:$F$1, 0)),0)} -> 19144000 | G14: 0
A15: EBITDA (Normalized) | B15: {=IFERROR(INDEX('Raw Data Pasting'!$A:$A, MATCH("Normalized EBITDA", 'Raw Data Pasting'!$A:$A, 0) + MATCH(B$1, $B$1:$F$1, 0)),0)} -> 46471000 | C15: {=IFERROR(INDEX('Raw Data Pasting'!$A:$A, MATCH("Normalized EBITDA", 'Raw Data Pasting'!$A:$A, 0) + MATCH(C$1, $B$1:$F$1, 0)),0)} -> 46471000 | D15: {=IFERROR(INDEX('Raw Data Pasting'!$A:$A, MATCH("Normalized EBITDA", 'Raw Data Pasting'!$A:$A, 0) + MATCH(D$1, $B$1:$F$1, 0)),0)} -> 42010000 | E15: {=IFERROR(INDEX('Raw Data Pasting'!$A:$A, MATCH("Normalized EBITDA", 'Raw Data Pasting'!$A:$A, 0) + MATCH(E$1, $B$1:$F$1, 0)),0)} -> 36384000 | F15: {=IFERROR(INDEX('Raw Data Pasting'!$A:$A, MATCH("Normalized EBITDA", 'Raw Data Pasting'!$A:$A, 0) + MATCH(F$1, $B$1:$F$1, 0)),0)} -> 30089000 | G15: 0
A16: EPS (Diluted) | B16: {=IFERROR(INDEX('Raw Data Pasting'!$A:$A, MATCH("Diluted EPS", 'Raw Data Pasting'!$A:$A, 0) + MATCH(B$1, $B$1:$F$1, 0)),0)} -> 2.73 | C16: {=IFERROR(INDEX('Raw Data Pasting'!$A:$A, MATCH("Diluted EPS", 'Raw Data Pasting'!$A:$A, 0) + MATCH(C$1, $B$1:$F$1, 0)),0)} -> 2.73 | D16: {=IFERROR(INDEX('Raw Data Pasting'!$A:$A, MATCH("Diluted EPS", 'Raw Data Pasting'!$A:$A, 0) + MATCH(D$1, $B$1:$F$1, 0)),0)} -> 2.41 | E16: {=IFERROR(INDEX('Raw Data Pasting'!$A:$A, MATCH("Diluted EPS", 'Raw Data Pasting'!$A:$A, 0) + MATCH(E$1, $B$1:$F$1, 0)),0)} -> 1.91 | F16: {=IFERROR(INDEX('Raw Data Pasting'!$A:$A, MATCH("Diluted EPS", 'Raw Data Pasting'!$A:$A, 0) + MATCH(F$1, $B$1:$F$1, 0)),0)} -> 1.42 | G16: 0
A17: Shares Outstanding (Diluted Average) | B17: {=IFERROR(INDEX('Raw Data Pasting'!$A:$A, MATCH("Diluted Average Shares", 'Raw Data Pasting'!$A:$A, 0) + MATCH(B$1, $B$1:$F$1, 0)),0)} -> 8022000 | C17: {=IFERROR(INDEX('Raw Data Pasting'!$A:$A, MATCH("Diluted Average Shares", 'Raw Data Pasting'!$A:$A, 0) + MATCH(C$1, $B$1:$F$1, 0)),0)} -> 8022000 | D17: {=IFERROR(INDEX('Raw Data Pasting'!$A:$A, MATCH("Diluted Average Shares", 'Raw Data Pasting'!$A:$A, 0) + MATCH(D$1, $B$1:$F$1, 0)),0)} -> 8081000 | E17: {=IFERROR(INDEX('Raw Data Pasting'!$A:$A, MATCH("Diluted Average Shares", 'Raw Data Pasting'!$A:$A, 0) + MATCH(E$1, $B$1:$F$1, 0)),0)} -> 8108000 | F17: {=IFERROR(INDEX('Raw Data Pasting'!$A:$A, MATCH("Diluted Average Shares", 'Raw Data Pasting'!$A:$A, 0) + MATCH(F$1, $B$1:$F$1, 0)),0)} -> 8202000 | G17: 0
A18: Balance Sheet Items (Column B)
A19: Total Assets | B19: {=IFERROR(INDEX('Raw Data Pasting'!$B:$B, MATCH("Total Assets", 'Raw Data Pasting'!$B:$B, 0) + MATCH(B$1, $C$1:$F$1, 0)),"N/A")} -> N/A | C19: {=IFERROR(INDEX('Raw Data Pasting'!$B:$B, MATCH("Total Assets", 'Raw Data Pasting'!$B:$B, 0) + MATCH(C$1, $C$1:$F$1, 0)),"N/A")} -> 284668000 | D19: {=IFERROR(INDEX('Raw Data Pasting'!$B:$B, MATCH("Total Assets", 'Raw Data Pasting'!$B:$B, 0) + MATCH(D$1, $C$1:$F$1, 0)),"N/A")} -> 260823000 | E19: {=IFERROR(INDEX('Raw Data Pasting'!$B:$B, MATCH("Total Assets", 'Raw Data Pasting'!$B:$B, 0) + MATCH(E$1, $C$1:$F$1, 0)),"N/A")} -> 252399000 | F19: {=IFERROR(INDEX('Raw Data Pasting'!$B:$B, MATCH("Total Assets", 'Raw Data Pasting'!$B:$B, 0) + MATCH(F$1, $C$1:$F$1, 0)),"N/A")} -> 243197000 | G19: 0
A20: Current Assets | B20: {=IFERROR(INDEX('Raw Data Pasting'!$B:$B, MATCH("Current Assets", 'Raw Data Pasting'!$B:$B, 0) + MATCH(B$1, $C$1:$F$1, 0)),"N/A")} -> N/A | C20: {=IFERROR(INDEX('Raw Data Pasting'!$B:$B, MATCH("Current Assets", 'Raw Data Pasting'!$B:$B, 0) + MATCH(C$1, $C$1:$F$1, 0)),"N/A")} -> 84874000 | D20: {=IFERROR(INDEX('Raw Data Pasting'!$B:$B, MATCH("Current Assets", 'Raw Data Pasting'!$B:$B, 0) + MATCH(D$1, $C$1:$F$1, 0)),"N/A")} -> 79458000 | E20: {=IFERROR(INDEX('Raw Data Pasting'!$B:$B, MATCH("Current Assets", 'Raw Data Pasting'!$B:$B, 0) + MATCH(E$1, $C$1:$F$1, 0)),"N/A")} -> 76877000 | F20: {=IFERROR(INDEX('Raw Data Pasting'!$B:$B, MATCH("Current Assets", 'Raw Data Pasting'!$B:$B, 0) + MATCH(F$1, $C$1:$F$1, 0)),"N/A")} -> 75655000 | G20: 0
A21: Cash, Cash Equivalents & Short Term Investments | B21: {=IFERROR(INDEX('Raw Data Pasting'!$B:$B, MATCH("Cash, Cash Equivalents & Short Term Investments", 'Raw Data Pasting'!$B:$B, 0) + MATCH(B$1, $C$1:$F$1, 0)),"N/A")} -> N/A | C21: {=IFERROR(INDEX('Raw Data Pasting'!$B:$B, MATCH("Cash, Cash Equivalents & Short Term Investments", 'Raw Data Pasting'!$B:$B, 0) + MATCH(C$1, $C$1:$F$1, 0)),"N/A")} -> 10727000 | D21: {=IFERROR(INDEX('Raw Data Pasting'!$B:$B, MATCH("Cash, Cash Equivalents & Short Term Investments", 'Raw Data Pasting'!$B:$B, 0) + MATCH(D$1, $C$1:$F$1, 0)),"N/A")} -> 9037000 | E21: {=IFERROR(INDEX('Raw Data Pasting'!$B:$B, MATCH("Cash, Cash Equivalents & Short Term Investments", 'Raw Data Pasting'!$B:$B, 0) + MATCH(E$1, $C$1:$F$1, 0)),"N/A")} -> 9867000 | F21: {=IFERROR(INDEX('Raw Data Pasting'!$B:$B, MATCH("Cash, Cash Equivalents & Short Term Investments", 'Raw Data Pasting'!$B:$B, 0) + MATCH(F$1, $C$1:$F$1, 0)),"N/A")} -> 8625000
A22: Cash Only (or Cash + Equivs only) | B22: {=IFERROR( IF(INDEX('Raw Data Pasting'!$B:$B,MATCH("Cash",'Raw Data Pasting'!$B:$B,0)+MATCH(B$1,$C$1:$F$1,0))="--",0,INDEX('Raw Data Pasting'!$B:$B,MATCH("Cash",'Raw Data Pasting'!$B:$B,0)+MATCH(B$1,$C$1:$F$1,0))), IFERROR( IF(INDEX('Raw Data Pasting'!$B:$B,MATCH("Cash And Cash Equivalents",'Raw Data Pasting'!$B:$B,0)+MATCH(B$1,$C$1:$F$1,0))="--",0,INDEX('Raw Data Pasting'!$B:$B,MATCH("Cash And Cash Equivalents",'Raw Data Pasting'!$B:$B,0)+MATCH(B$1,$C$1:$F$1,0))), "N/A" ))} -> N/A | C22: {=IFERROR( IF(INDEX('Raw Data Pasting'!$B:$B,MATCH("Cash",'Raw Data Pasting'!$B:$B,0)+MATCH(C$1,$C$1:$F$1,0))="--",0,INDEX('Raw Data Pasting'!$B:$B,MATCH("Cash",'Raw Data Pasting'!$B:$B,0)+MATCH(C$1,$C$1:$F$1,0))), IFERROR( IF(INDEX('Raw Data Pasting'!$B:$B,MATCH("Cash And Cash Equivalents",'Raw Data Pasting'!$B:$B,0)+MATCH(C$1,$C$1:$F$1,0))="--",0,INDEX('Raw Data Pasting'!$B:$B,MATCH("Cash And Cash Equivalents",'Raw Data Pasting'!$B:$B,0)+MATCH(C$1,$C$1:$F$1,0))), "N/A" ))} -> 10727000 | D22: {=IFERROR( IF(INDEX('Raw Data Pasting'!$B:$B,MATCH("Cash",'Raw Data Pasting'!$B:$B,0)+MATCH(D$1,$C$1:$F$1,0))="--",0,INDEX('Raw Data Pasting'!$B:$B,MATCH("Cash",'Raw Data Pasting'!$B:$B,0)+MATCH(D$1,$C$1:$F$1,0))), IFERROR( IF(INDEX('Raw Data Pasting'!$B:$B,MATCH("Cash And Cash Equivalents",'Raw Data Pasting'!$B:$B,0)+MATCH(D$1,$C$1:$F$1,0))="--",0,INDEX('Raw Data Pasting'!$B:$B,MATCH("Cash And Cash Equivalents",'Raw Data Pasting'!$B:$B,0)+MATCH(D$1,$C$1:$F$1,0))), "N/A" ))} -> 9037000 | E22: {=IFERROR( IF(INDEX('Raw Data Pasting'!$B:$B,MATCH("Cash",'Raw Data Pasting'!$B:$B,0)+MATCH(E$1,$C$1:$F$1,0))="--",0,INDEX('Raw Data Pasting'!$B:$B,MATCH("Cash",'Raw Data Pasting'!$B:$B,0)+MATCH(E$1,$C$1:$F$1,0))), IFERROR( IF(INDEX('Raw Data Pasting'!$B:$B,MATCH("Cash And Cash Equivalents",'Raw Data Pasting'!$B:$B,0)+MATCH(E$1,$C$1:$F$1,0))="--",0,INDEX('Raw Data Pasting'!$B:$B,MATCH("Cash And Cash Equivalents",'Raw Data Pasting'!$B:$B,0)+MATCH(E$1,$C$1:$F$1,0))), "N/A" ))} -> 9867000 | F22: {=IFERROR( IF(INDEX('Raw Data Pasting'!$B:$B,MATCH("Cash",'Raw Data Pasting'!$B:$B,0)+MATCH(F$1,$C$1:$F$1,0))="--",0,INDEX('Raw Data Pasting'!$B:$B,MATCH("Cash",'Raw Data Pasting'!$B:$B,0)+MATCH(F$1,$C$1:$F$1,0))), IFERROR( IF(INDEX('Raw Data Pasting'!$B:$B,MATCH("Cash And Cash Equivalents",'Raw Data Pasting'!$B:$B,0)+MATCH(F$1,$C$1:$F$1,0))="--",0,INDEX('Raw Data Pasting'!$B:$B,MATCH("Cash And Cash Equivalents",'Raw Data Pasting'!$B:$B,0)+MATCH(F$1,$C$1:$F$1,0))), "N/A" ))} -> 8625000 | G22: 0
A23: Accounts receivable | B23: {=IFERROR(INDEX('Raw Data Pasting'!$B:$B, MATCH("Accounts receivable", 'Raw Data Pasting'!$B:$B, 0) + MATCH(B$1, $C$1:$F$1, 0)),"N/A")} -> N/A | C23: {=IFERROR(INDEX('Raw Data Pasting'!$B:$B, MATCH("Accounts receivable", 'Raw Data Pasting'!$B:$B, 0) + MATCH(C$1, $C$1:$F$1, 0)),"N/A")} -> 11172000 | D23: {=IFERROR(INDEX('Raw Data Pasting'!$B:$B, MATCH("Accounts receivable", 'Raw Data Pasting'!$B:$B, 0) + MATCH(D$1, $C$1:$F$1, 0)),"N/A")} -> 9975000 | E23: {=IFERROR(INDEX('Raw Data Pasting'!$B:$B, MATCH("Accounts receivable", 'Raw Data Pasting'!$B:$B, 0) + MATCH(E$1, $C$1:$F$1, 0)),"N/A")} -> 8796000 | F23: {=IFERROR(INDEX('Raw Data Pasting'!$B:$B, MATCH("Accounts receivable", 'Raw Data Pasting'!$B:$B, 0) + MATCH(F$1, $C$1:$F$1, 0)),"N/A")} -> 7933000 | G23: 0
A24: Other Short Term Investments | B24: {=IFERROR(IF(INDEX('Raw Data Pasting'!$B:$B,MATCH("Other Short Term Investments",'Raw Data Pasting'!$B:$B,0)+MATCH(B$1,$C$1:$F$1,0))="--",0,(INDEX('Raw Data Pasting'!$B:$B,MATCH("Other Short Term Investments",'Raw Data Pasting'!$B:$B,0)+MATCH(B$1,$C$1:$F$1,0)))), 0)} -> 0 | C24: {=IFERROR(IF(INDEX('Raw Data Pasting'!$B:$B,MATCH("Other Short Term Investments",'Raw Data Pasting'!$B:$B,0)+MATCH(C$1,$C$1:$F$1,0))="--",0,(INDEX('Raw Data Pasting'!$B:$B,MATCH("Other Short Term Investments",'Raw Data Pasting'!$B:$B,0)+MATCH(C$1,$C$1:$F$1,0)))), 0)} -> 0 | D24: {=IFERROR(IF(INDEX('Raw Data Pasting'!$B:$B,MATCH("Other Short Term Investments",'Raw Data Pasting'!$B:$B,0)+MATCH(D$1,$C$1:$F$1,0))="--",0,(INDEX('Raw Data Pasting'!$B:$B,MATCH("Other Short Term Investments",'Raw Data Pasting'!$B:$B,0)+MATCH(D$1,$C$1:$F$1,0)))), 0)} -> 0 | E24: {=IFERROR(IF(INDEX('Raw Data Pasting'!$B:$B,MATCH("Other Short Term Investments",'Raw Data Pasting'!$B:$B,0)+MATCH(E$1,$C$1:$F$1,0))="--",0,(INDEX('Raw Data Pasting'!$B:$B,MATCH("Other Short Term Investments",'Raw Data Pasting'!$B:$B,0)+MATCH(E$1,$C$1:$F$1,0)))), 0)} -> 0 | F24: {=IFERROR(IF(INDEX('Raw Data Pasting'!$B:$B,MATCH("Other Short Term Investments",'Raw Data Pasting'!$B:$B,0)+MATCH(F$1,$C$1:$F$1,0))="--",0,(INDEX('Raw Data Pasting'!$B:$B,MATCH("Other Short Term Investments",'Raw Data Pasting'!$B:$B,0)+MATCH(F$1,$C$1:$F$1,0)))), 0)} -> 0 | G24: 0
A25: Inventory | B25: {=IFERROR(INDEX('Raw Data Pasting'!$B:$B, MATCH("Inventory", 'Raw Data Pasting'!$B:$B, 0) + MATCH(B$1, $C$1:$F$1, 0)),"N/A")} -> N/A | C25: {=IFERROR(INDEX('Raw Data Pasting'!$B:$B, MATCH("Inventory", 'Raw Data Pasting'!$B:$B, 0) + MATCH(C$1, $C$1:$F$1, 0)),"N/A")} -> 58851000 | D25: {=IFERROR(INDEX('Raw Data Pasting'!$B:$B, MATCH("Inventory", 'Raw Data Pasting'!$B:$B, 0) + MATCH(D$1, $C$1:$F$1, 0)),"N/A")} -> 56435000 | E25: {=IFERROR(INDEX('Raw Data Pasting'!$B:$B, MATCH("Inventory", 'Raw Data Pasting'!$B:$B, 0) + MATCH(E$1, $C$1:$F$1, 0)),"N/A")} -> 54892000 | F25: {=IFERROR(INDEX('Raw Data Pasting'!$B:$B, MATCH("Inventory", 'Raw Data Pasting'!$B:$B, 0) + MATCH(F$1, $C$1:$F$1, 0)),"N/A")} -> 56576000 | G25: 0
A26: Total Liabilities | B26: {=IFERROR(INDEX('Raw Data Pasting'!$B:$B, MATCH("Total Liabilities Net Minority Interest", 'Raw Data Pasting'!$B:$B, 0) + MATCH(B$1, $C$1:$F$1, 0)),"N/A")} -> N/A | C26: {=IFERROR(INDEX('Raw Data Pasting'!$B:$B, MATCH("Total Liabilities Net Minority Interest", 'Raw Data Pasting'!$B:$B, 0) + MATCH(C$1, $C$1:$F$1, 0)),"N/A")} -> 178488000 | D26: {=IFERROR(INDEX('Raw Data Pasting'!$B:$B, MATCH("Total Liabilities Net Minority Interest", 'Raw Data Pasting'!$B:$B, 0) + MATCH(D$1, $C$1:$F$1, 0)),"N/A")} -> 163131000 | E26: {=IFERROR(INDEX('Raw Data Pasting'!$B:$B, MATCH("Total Liabilities Net Minority Interest", 'Raw Data Pasting'!$B:$B, 0) + MATCH(E$1, $C$1:$F$1, 0)),"N/A")} -> 161828000 | F26: {=IFERROR(INDEX('Raw Data Pasting'!$B:$B, MATCH("Total Liabilities Net Minority Interest", 'Raw Data Pasting'!$B:$B, 0) + MATCH(F$1, $C$1:$F$1, 0)),"N/A")} -> 159206000 | G26: 0
A27: Current Liabilities | B27: {=IFERROR(INDEX('Raw Data Pasting'!$B:$B, MATCH("Current Liabilities", 'Raw Data Pasting'!$B:$B, 0) + MATCH(B$1, $C$1:$F$1, 0)),"N/A")} -> N/A | C27: {=IFERROR(INDEX('Raw Data Pasting'!$B:$B, MATCH("Current Liabilities", 'Raw Data Pasting'!$B:$B, 0) + MATCH(C$1, $C$1:$F$1, 0)),"N/A")} -> 107469000 | D27: {=IFERROR(INDEX('Raw Data Pasting'!$B:$B, MATCH("Current Liabilities", 'Raw Data Pasting'!$B:$B, 0) + MATCH(D$1, $C$1:$F$1, 0)),"N/A")} -> 96584000 | E27: {=IFERROR(INDEX('Raw Data Pasting'!$B:$B, MATCH("Current Liabilities", 'Raw Data Pasting'!$B:$B, 0) + MATCH(E$1, $C$1:$F$1, 0)),"N/A")} -> 92415000 | F27: {=IFERROR(INDEX('Raw Data Pasting'!$B:$B, MATCH("Current Liabilities", 'Raw Data Pasting'!$B:$B, 0) + MATCH(F$1, $C$1:$F$1, 0)),"N/A")} -> 92198000 | G27: 0
A28: Short Term (Current) Debt | B28: {=IFERROR(IF(INDEX('Raw Data Pasting'!$B:$B,MATCH("Current Debt",'Raw Data Pasting'!$B:$B,0)+MATCH(B$1,$C$1:$F$1,0))="--",0,(INDEX('Raw Data Pasting'!$B:$B,MATCH("Current Debt",'Raw Data Pasting'!$B:$B,0)+MATCH(B$1,$C$1:$F$1,0)))), "N/A")} -> N/A | C28: {=IFERROR(IF(INDEX('Raw Data Pasting'!$B:$B,MATCH("Current Debt",'Raw Data Pasting'!$B:$B,0)+MATCH(C$1,$C$1:$F$1,0))="--",0,(INDEX('Raw Data Pasting'!$B:$B,MATCH("Current Debt",'Raw Data Pasting'!$B:$B,0)+MATCH(C$1,$C$1:$F$1,0)))), "N/A")} -> 10138000 | D28: {=IFERROR(IF(INDEX('Raw Data Pasting'!$B:$B,MATCH("Current Debt",'Raw Data Pasting'!$B:$B,0)+MATCH(D$1,$C$1:$F$1,0))="--",0,(INDEX('Raw Data Pasting'!$B:$B,MATCH("Current Debt",'Raw Data Pasting'!$B:$B,0)+MATCH(D$1,$C$1:$F$1,0)))), "N/A")} -> 5666000 | E28: {=IFERROR(IF(INDEX('Raw Data Pasting'!$B:$B,MATCH("Current Debt",'Raw Data Pasting'!$B:$B,0)+MATCH(E$1,$C$1:$F$1,0))="--",0,(INDEX('Raw Data Pasting'!$B:$B,MATCH("Current Debt",'Raw Data Pasting'!$B:$B,0)+MATCH(E$1,$C$1:$F$1,0)))), "N/A")} -> 4325000 | F28: {=IFERROR(IF(INDEX('Raw Data Pasting'!$B:$B,MATCH("Current Debt",'Raw Data Pasting'!$B:$B,0)+MATCH(F$1,$C$1:$F$1,0))="--",0,(INDEX('Raw Data Pasting'!$B:$B,MATCH("Current Debt",'Raw Data Pasting'!$B:$B,0)+MATCH(F$1,$C$1:$F$1,0)))), "N/A")} -> 4563000 | G28: 0
A29: Total Equity Gross Minority Interest | B29: {=IFERROR(INDEX('Raw Data Pasting'!$B:$B, MATCH("Total Equity Gross Minority Interest", 'Raw Data Pasting'!$B:$B, 0) + MATCH(B$1, $C$1:$F$1, 0)),"N/A")} -> N/A | C29: {=IFERROR(INDEX('Raw Data Pasting'!$B:$B, MATCH("Total Equity Gross Minority Interest", 'Raw Data Pasting'!$B:$B, 0) + MATCH(C$1, $C$1:$F$1, 0)),"N/A")} -> 106180000 | D29: {=IFERROR(INDEX('Raw Data Pasting'!$B:$B, MATCH("Total Equity Gross Minority Interest", 'Raw Data Pasting'!$B:$B, 0) + MATCH(D$1, $C$1:$F$1, 0)),"N/A")} -> 97692000 | E29: {=IFERROR(INDEX('Raw Data Pasting'!$B:$B, MATCH("Total Equity Gross Minority Interest", 'Raw Data Pasting'!$B:$B, 0) + MATCH(E$1, $C$1:$F$1, 0)),"N/A")} -> 90571000 | F29: {=IFERROR(INDEX('Raw Data Pasting'!$B:$B, MATCH("Total Equity Gross Minority Interest", 'Raw Data Pasting'!$B:$B, 0) + MATCH(F$1, $C$1:$F$1, 0)),"N/A")} -> 83991000 | G29: 0
A30: Common Stock Equity (Book Value) | B30: {=IFERROR(INDEX('Raw Data Pasting'!$B:$B, MATCH("Common Stock Equity", 'Raw Data Pasting'!$B:$B, 0) + MATCH(B$1, $C$1:$F$1, 0)),"N/A")} -> N/A | C30: {=IFERROR(INDEX('Raw Data Pasting'!$B:$B, MATCH("Common Stock Equity", 'Raw Data Pasting'!$B:$B, 0) + MATCH(C$1, $C$1:$F$1, 0)),"N/A")} -> 99617000 | D30: {=IFERROR(INDEX('Raw Data Pasting'!$B:$B, MATCH("Common Stock Equity", 'Raw Data Pasting'!$B:$B, 0) + MATCH(D$1, $C$1:$F$1, 0)),"N/A")} -> 91013000 | E30: {=IFERROR(INDEX('Raw Data Pasting'!$B:$B, MATCH("Common Stock Equity", 'Raw Data Pasting'!$B:$B, 0) + MATCH(E$1, $C$1:$F$1, 0)),"N/A")} -> 83861000 | F30: {=IFERROR(INDEX('Raw Data Pasting'!$B:$B, MATCH("Common Stock Equity", 'Raw Data Pasting'!$B:$B, 0) + MATCH(F$1, $C$1:$F$1, 0)),"N/A")} -> 76693000 | G30: 0
A31: Total Debt | B31: {=IFERROR(INDEX('Raw Data Pasting'!$B:$B, MATCH("Total Debt", 'Raw Data Pasting'!$B:$B, 0) + MATCH(B$1, $C$1:$F$1, 0)),"N/A")} -> N/A | C31: {=IFERROR(INDEX('Raw Data Pasting'!$B:$B, MATCH("Total Debt", 'Raw Data Pasting'!$B:$B, 0) + MATCH(C$1, $C$1:$F$1, 0)),"N/A")} -> 67095000 | D31: {=IFERROR(INDEX('Raw Data Pasting'!$B:$B, MATCH("Total Debt", 'Raw Data Pasting'!$B:$B, 0) + MATCH(D$1, $C$1:$F$1, 0)),"N/A")} -> 60114000 | E31: {=IFERROR(INDEX('Raw Data Pasting'!$B:$B, MATCH("Total Debt", 'Raw Data Pasting'!$B:$B, 0) + MATCH(E$1, $C$1:$F$1, 0)),"N/A")} -> 61321000 | F31: {=IFERROR(INDEX('Raw Data Pasting'!$B:$B, MATCH("Total Debt", 'Raw Data Pasting'!$B:$B, 0) + MATCH(F$1, $C$1:$F$1, 0)),"N/A")} -> 58923000 | G31: 0
A32: Net Debt | B32: {=IFERROR(INDEX('Raw Data Pasting'!$B:$B, MATCH("Net Debt", 'Raw Data Pasting'!$B:$B, 0) + MATCH(B$1, $C$1:$F$1, 0)),"N/A")} -> N/A | C32: {=IFERROR(INDEX('Raw Data Pasting'!$B:$B, MATCH("Net Debt", 'Raw Data Pasting'!$B:$B, 0) + MATCH(C$1, $C$1:$F$1, 0)),"N/A")} -> 34035000 | D32: {=IFERROR(INDEX('Raw Data Pasting'!$B:$B, MATCH("Net Debt", 'Raw Data Pasting'!$B:$B, 0) + MATCH(D$1, $C$1:$F$1, 0)),"N/A")} -> 30030000 | E32: {=IFERROR(INDEX('Raw Data Pasting'!$B:$B, MATCH("Net Debt", 'Raw Data Pasting'!$B:$B, 0) + MATCH(E$1, $C$1:$F$1, 0)),"N/A")} -> 30590000 | F32: {=IFERROR(INDEX('Raw Data Pasting'!$B:$B, MATCH("Net Debt", 'Raw Data Pasting'!$B:$B, 0) + MATCH(F$1, $C$1:$F$1, 0)),"N/A")} -> 30587000 | G32: 0
A33: Share Issued (year end) | B33: {=IFERROR(INDEX('Raw Data Pasting'!$B:$B, MATCH("Share Issued", 'Raw Data Pasting'!$B:$B, 0) + MATCH(B$1, $C$1:$F$1, 0)),"N/A")} -> N/A | C33: {=IFERROR(INDEX('Raw Data Pasting'!$B:$B, MATCH("Share Issued", 'Raw Data Pasting'!$B:$B, 0) + MATCH(C$1, $C$1:$F$1, 0)),"N/A")} -> 7969000 | D33: {=IFERROR(INDEX('Raw Data Pasting'!$B:$B, MATCH("Share Issued", 'Raw Data Pasting'!$B:$B, 0) + MATCH(D$1, $C$1:$F$1, 0)),"N/A")} -> 8024000 | E33: {=IFERROR(INDEX('Raw Data Pasting'!$B:$B, MATCH("Share Issued", 'Raw Data Pasting'!$B:$B, 0) + MATCH(E$1, $C$1:$F$1, 0)),"N/A")} -> 8054000 | F33: {=IFERROR(INDEX('Raw Data Pasting'!$B:$B, MATCH("Share Issued", 'Raw Data Pasting'!$B:$B, 0) + MATCH(F$1, $C$1:$F$1, 0)),"N/A")} -> 8100000 | G33: 0
A34: Goodwill & Other Intangibles | B34: {=IFERROR(INDEX('Raw Data Pasting'!$B:$B, MATCH("Goodwill And Other Intangible Assets", 'Raw Data Pasting'!$B:$B, 0) + MATCH(B$1, $C$1:$F$1, 0)),"N/A")} -> N/A | C34: {=IFERROR(INDEX('Raw Data Pasting'!$B:$B, MATCH("Goodwill And Other Intangible Assets", 'Raw Data Pasting'!$B:$B, 0) + MATCH(C$1, $C$1:$F$1, 0)),"N/A")} -> 28735000 | D34: {=IFERROR(INDEX('Raw Data Pasting'!$B:$B, MATCH("Goodwill And Other Intangible Assets", 'Raw Data Pasting'!$B:$B, 0) + MATCH(D$1, $C$1:$F$1, 0)),"N/A")} -> 28792000 | E34: {=IFERROR(INDEX('Raw Data Pasting'!$B:$B, MATCH("Goodwill And Other Intangible Assets", 'Raw Data Pasting'!$B:$B, 0) + MATCH(E$1, $C$1:$F$1, 0)),"N/A")} -> 28113000 | F34: {=IFERROR(INDEX('Raw Data Pasting'!$B:$B, MATCH("Goodwill And Other Intangible Assets", 'Raw Data Pasting'!$B:$B, 0) + MATCH(F$1, $C$1:$F$1, 0)),"N/A")} -> 28174000 | G34: 0
A35: Cashflow Statement Items (Column C)
A36: Depreciation & Amortization | B36: {=IFERROR(INDEX('Raw Data Pasting'!$C:$C, MATCH("Depreciation & Amortization", 'Raw Data Pasting'!$C:$C, 0) + MATCH(B$1, $B$1:$F$1, 0)),0)} -> 14203000 | C36: {=IFERROR(INDEX('Raw Data Pasting'!$C:$C, MATCH("Depreciation & Amortization", 'Raw Data Pasting'!$C:$C, 0) + MATCH(C$1, $B$1:$F$1, 0)),0)} -> 14203000 | D36: {=IFERROR(INDEX('Raw Data Pasting'!$C:$C, MATCH("Depreciation & Amortization", 'Raw Data Pasting'!$C:$C, 0) + MATCH(D$1, $B$1:$F$1, 0)),0)} -> 12973000 | E36: {=IFERROR(INDEX('Raw Data Pasting'!$C:$C, MATCH("Depreciation & Amortization", 'Raw Data Pasting'!$C:$C, 0) + MATCH(E$1, $B$1:$F$1, 0)),0)} -> 11853000 | F36: {=IFERROR(INDEX('Raw Data Pasting'!$C:$C, MATCH("Depreciation & Amortization", 'Raw Data Pasting'!$C:$C, 0) + MATCH(F$1, $B$1:$F$1, 0)),0)} -> 10945000 | G36: 0
A37: Operating Cash Flow | B37: {=IFERROR(INDEX('Raw Data Pasting'!$C:$C, MATCH("Operating Cash Flow", 'Raw Data Pasting'!$C:$C, 0) + MATCH(B$1, $B$1:$F$1, 0)),0)} -> 41565000 | C37: {=IFERROR(INDEX('Raw Data Pasting'!$C:$C, MATCH("Operating Cash Flow", 'Raw Data Pasting'!$C:$C, 0) + MATCH(C$1, $B$1:$F$1, 0)),0)} -> 41565000 | D37: {=IFERROR(INDEX('Raw Data Pasting'!$C:$C, MATCH("Operating Cash Flow", 'Raw Data Pasting'!$C:$C, 0) + MATCH(D$1, $B$1:$F$1, 0)),0)} -> 36443000 | E37: {=IFERROR(INDEX('Raw Data Pasting'!$C:$C, MATCH("Operating Cash Flow", 'Raw Data Pasting'!$C:$C, 0) + MATCH(E$1, $B$1:$F$1, 0)),0)} -> 35726000 | F37: {=IFERROR(INDEX('Raw Data Pasting'!$C:$C, MATCH("Operating Cash Flow", 'Raw Data Pasting'!$C:$C, 0) + MATCH(F$1, $B$1:$F$1, 0)),0)} -> 28841000 | G37: 0
A38: Capital Expenditures (CapEx) | B38: {=IFERROR(INDEX('Raw Data Pasting'!$C:$C, MATCH("Capital Expenditure", 'Raw Data Pasting'!$C:$C, 0) + MATCH(B$1, $B$1:$F$1, 0)),0)} -> -26642000 | C38: {=IFERROR(INDEX('Raw Data Pasting'!$C:$C, MATCH("Capital Expenditure", 'Raw Data Pasting'!$C:$C, 0) + MATCH(C$1, $B$1:$F$1, 0)),0)} -> -26642000 | D38: {=IFERROR(INDEX('Raw Data Pasting'!$C:$C, MATCH("Capital Expenditure", 'Raw Data Pasting'!$C:$C, 0) + MATCH(D$1, $B$1:$F$1, 0)),0)} -> -23783000 | E38: {=IFERROR(INDEX('Raw Data Pasting'!$C:$C, MATCH("Capital Expenditure", 'Raw Data Pasting'!$C:$C, 0) + MATCH(E$1, $B$1:$F$1, 0)),0)} -> -20606000 | F38: {=IFERROR(INDEX('Raw Data Pasting'!$C:$C, MATCH("Capital Expenditure", 'Raw Data Pasting'!$C:$C, 0) + MATCH(F$1, $B$1:$F$1, 0)),0)} -> -16857000 | G38: 0
A39: Dividends Paid (Common Stock Payments) | B39: {=IFERROR(INDEX('Raw Data Pasting'!$C:$C, MATCH("Common Stock Payments", 'Raw Data Pasting'!$C:$C, 0) + MATCH(B$1, $B$1:$F$1, 0)),0)} -> -8088000 | C39: {=IFERROR(INDEX('Raw Data Pasting'!$C:$C, MATCH("Common Stock Payments", 'Raw Data Pasting'!$C:$C, 0) + MATCH(C$1, $B$1:$F$1, 0)),0)} -> -8088000 | D39: {=IFERROR(INDEX('Raw Data Pasting'!$C:$C, MATCH("Common Stock Payments", 'Raw Data Pasting'!$C:$C, 0) + MATCH(D$1, $B$1:$F$1, 0)),0)} -> -4494000 | E39: {=IFERROR(INDEX('Raw Data Pasting'!$C:$C, MATCH("Common Stock Payments", 'Raw Data Pasting'!$C:$C, 0) + MATCH(E$1, $B$1:$F$1, 0)),0)} -> -2779000 | F39: {=IFERROR(INDEX('Raw Data Pasting'!$C:$C, MATCH("Common Stock Payments", 'Raw Data Pasting'!$C:$C, 0) + MATCH(F$1, $B$1:$F$1, 0)),0)} -> -9920000 | G39: 0
A40: Free Cash Flow (FCF) | B40: {=IFERROR(INDEX('Raw Data Pasting'!$C:$C, MATCH("Free Cash Flow", 'Raw Data Pasting'!$C:$C, 0) + MATCH(B$1, $B$1:$F$1, 0)),0)} -> 14923000 | C40: {=IFERROR(INDEX('Raw Data Pasting'!$C:$C, MATCH("Free Cash Flow", 'Raw Data Pasting'!$C:$C, 0) + MATCH(C$1, $B$1:$F$1, 0)),0)} -> 14923000 | D40: {=IFERROR(INDEX('Raw Data Pasting'!$C:$C, MATCH("Free Cash Flow", 'Raw Data Pasting'!$C:$C, 0) + MATCH(D$1, $B$1:$F$1, 0)),0)} -> 12660000 | E40: {=IFERROR(INDEX('Raw Data Pasting'!$C:$C, MATCH("Free Cash Flow", 'Raw Data Pasting'!$C:$C, 0) + MATCH(E$1, $B$1:$F$1, 0)),0)} -> 15120000 | F40: {=IFERROR(INDEX('Raw Data Pasting'!$C:$C, MATCH("Free Cash Flow", 'Raw Data Pasting'!$C:$C, 0) + MATCH(F$1, $B$1:$F$1, 0)),0)} -> 11984000 | G40: 0
A42: Peer Valuation Multiples
A43: Metric | B43: ='Raw Data Pasting'!V3 -> WMT | C43: ='Raw Data Pasting'!W3 -> COST | D43: ='Raw Data Pasting'!X3 -> TGT | E43: ='Raw Data Pasting'!Y3 -> DG | F43: Peer Avg (ex-current stock)
A44: P/E | B44: ='Raw Data Pasting'!V5 -> 43.6 | C44: ='Raw Data Pasting'!W5 -> 50.56 | D44: ='Raw Data Pasting'!X5 -> 13.93 | E44: ='Raw Data Pasting'!Y5 -> 18.18 | F44: =AVERAGE(C44:E44) -> 27.556667
A45: Forward P/E | B45: ='Raw Data Pasting'!V6 -> 40.32 | C45: ='Raw Data Pasting'!W6 -> 48.08 | D45: ='Raw Data Pasting'!X6 -> 14.16 | E45: ='Raw Data Pasting'!Y6 -> 17.33 | F45: =AVERAGE(C45:E45) -> 26.523333
A46: P/FCF | B46: ='Raw Data Pasting'!V7 -> 63.98 | C46: ='Raw Data Pasting'!W7 -> 47.51 | D46: ='Raw Data Pasting'!X7 -> 18.2 | E46: ='Raw Data Pasting'!Y7 -> 11.49 | F46: =AVERAGE(C46:E46) -> 25.733333
A47: P/B | B47: ='Raw Data Pasting'!V8 -> 9.53 | C47: ='Raw Data Pasting'!W8 -> 13.44 | D47: ='Raw Data Pasting'!X8 -> 3.17 | E47: ='Raw Data Pasting'!Y8 -> 3.22 | F47: =AVERAGE(C47:E47) -> 6.61
A48: P/S | B48: ='Raw Data Pasting'!V9 -> 1.34 | C48: ='Raw Data Pasting'!W9 -> 1.51 | D48: ='Raw Data Pasting'!X9 -> 0.49 | E48: ='Raw Data Pasting'!Y9 -> 0.64 | F48: =AVERAGE(C48:E48) -> 0.88
A49: EV/EBITDA | B49: ='Raw Data Pasting'!V10 -> 21.63 | C49: ='Raw Data Pasting'!W10 -> 29.96 | D49: ='Raw Data Pasting'!X10 -> 7.92 | E49: ='Raw Data Pasting'!Y10 -> 12.95 | F49: =AVERAGE(C49:E49) -> 16.943333

Sheet Calculations
A1: Trend Metrics | B1: Formula | C1: TTM | D1: ='Data Schema'!C1 -> 2026 | E1: ='Data Schema'!D1 -> 2025 | F1: ='Data Schema'!E1 -> 2024 | G1: ='Data Schema'!F1 -> 2023 | H1: Average
A2: Book Value per Share | B2: (Total Asset - Total Liabilities) / Total Outstanding Shares | C2: =IFERROR(('Data Schema'!B19-'Data Schema'!B26)/'Data Schema'!B33,"N/A") -> N/A | D2: =IFERROR(('Data Schema'!C19-'Data Schema'!C26)/'Data Schema'!C33,"N/A") -> 13.324131 | E2: =IFERROR(('Data Schema'!D19-'Data Schema'!D26)/'Data Schema'!D33,"N/A") -> 12.174975 | F2: =IFERROR(('Data Schema'!E19-'Data Schema'!E26)/'Data Schema'!E33,"N/A") -> 11.245468 | G2: =IFERROR(('Data Schema'!F19-'Data Schema'!F26)/'Data Schema'!F33,"N/A") -> 10.369259 | H2: =IFERROR(AVERAGE(C2:G2), "N/A") -> 11.778458
A3: Effective Tax Rate (T) | B3: Tax Provision/Pretax Income | C3: =IF(ABS('Data Schema'!B12/'Data Schema'!B11)=D3,"N/A",ABS('Data Schema'!B12/'Data Schema'!B11)) -> N/A | D3: =ABS('Data Schema'!C12/'Data Schema'!C11) -> 0.24429061 | E3: =ABS('Data Schema'!D12/'Data Schema'!D11) -> 0.23383633 | F3: =ABS('Data Schema'!E12/'Data Schema'!E11) -> 0.25530941 | G3: =ABS('Data Schema'!F12/'Data Schema'!F11) -> 0.33638928 | H3: =IFERROR(AVERAGE(C3:G3), "N/A") -> 0.26745641
A4: Working Capital (WC) | B4: Current Assets - Current Liability | C4: =IFERROR(('Data Schema'!B20-'Data Schema'!B27),"N/A") -> N/A | D4: =IFERROR(('Data Schema'!C20-'Data Schema'!C27),"N/A") -> -22595000 | E4: =IFERROR(('Data Schema'!D20-'Data Schema'!D27),"N/A") -> -17126000 | F4: =IFERROR(('Data Schema'!E20-'Data Schema'!E27),"N/A") -> -15538000 | G4: =IFERROR(('Data Schema'!F20-'Data Schema'!F27),"N/A") -> -16543000 | H4: =IFERROR(AVERAGE(C4:G4), "N/A") -> -17950500
A5: Change in Working Capital (ΔWC) | B5: WC current year - WC prior year | C5: =IFERROR(C4-D4,"N/A") -> N/A | D5: =IFERROR(D4-E4,"N/A") -> -5469000 | E5: =IFERROR(E4-F4,"N/A") -> -1588000 | F5: =IFERROR(F4-G4,"N/A") -> 1005000 | G5: Base | H5: =IFERROR(AVERAGE(C5:G5), "N/A") -> -2017333.3
A6: Non-Cash WC | B6: (Current Asset - Cash) - (Current Liabilities - ST Debts) | C6: =IFERROR(('Data Schema'!B20-'Data Schema'!B22)-('Data Schema'!B27-'Data Schema'!B28), "N/A") -> N/A | D6: =IFERROR(('Data Schema'!C20-'Data Schema'!C22)-('Data Schema'!C27-'Data Schema'!C28), "N/A") -> -23184000 | E6: =IFERROR(('Data Schema'!D20-'Data Schema'!D22)-('Data Schema'!D27-'Data Schema'!D28), "N/A") -> -20497000 | F6: =IFERROR(('Data Schema'!E20-'Data Schema'!E22)-('Data Schema'!E27-'Data Schema'!E28), "N/A") -> -21080000 | G6: =IFERROR(('Data Schema'!F20-'Data Schema'!F22)-('Data Schema'!F27-'Data Schema'!F28), "N/A") -> -20605000 | H6: =IFERROR(AVERAGE(C6:G6), "N/A") -> -21341500
A7: Change in Non-Cash WC | B7: WC current year - WC prior year | C7: =IFERROR(C6-D6,"N/A") -> N/A | D7: =IFERROR(D6-E6,"N/A") -> -2687000 | E7: =IFERROR(E6-F6,"N/A") -> 583000 | F7: =IFERROR(F6-G6,"N/A") -> -475000 | G7: Base | H7: =IFERROR(AVERAGE(C7:G7), "N/A") -> -859666.67
A8: Cost of Debt (Kd) (AVG Int. Rate) | B8: Interest Expense/ Total Debt (VD) | C8: =IFERROR('Data Schema'!B9/'Data Schema'!B31,"N/A") -> N/A | D8: ='Data Schema'!C9/'Data Schema'!C31 -> 0.041716968 | E8: ='Data Schema'!D9/'Data Schema'!D31 -> 0.045380444 | F8: ='Data Schema'!E9/'Data Schema'!E31 -> 0.043753363 | G8: ='Data Schema'!F9/'Data Schema'!F31 -> 0.03611493 | H8: =IFERROR(AVERAGE(C8:G8), "N/A") -> 0.041741426
A9: COGS as % of Rev | B9: COGS / Rev | C9: =IF(('Data Schema'!B4/'Data Schema'!B3) = D9, "N/A", 'Data Schema'!B4/'Data Schema'!B3) -> N/A | D9: =IFERROR('Data Schema'!C4/'Data Schema'!C3,"N/A") -> 0.750733 | E9: =IFERROR('Data Schema'!D4/'Data Schema'!D3,"N/A") -> 0.75148939 | F9: =IFERROR('Data Schema'!E4/'Data Schema'!E3,"N/A") -> 0.75624609 | G9: =IFERROR('Data Schema'!F4/'Data Schema'!F3,"N/A") -> 0.75859536 | H9: =IFERROR(AVERAGE(C9:G9), "N/A") -> 0.75426596
A10: Operating Expense as % of Rev | B10: Op Ex/Rev | C10: =IF(('Data Schema'!B6/'Data Schema'!B3) = D10, "N/A", 'Data Schema'!B6/'Data Schema'!B3) -> N/A | D10: =IFERROR('Data Schema'!C6/'Data Schema'!C3,"N/A") -> 0.20744626 | E10: =IFERROR('Data Schema'!D6/'Data Schema'!D3,"N/A") -> 0.20541422 | F10: =IFERROR('Data Schema'!E6/'Data Schema'!E3,"N/A") -> 0.20207676 | G10: =IFERROR('Data Schema'!F6/'Data Schema'!F3,"N/A") -> 0.20798673 | H10: =IFERROR(AVERAGE(C10:G10), "N/A") -> 0.20573099
A11: D&A as % of Rev | B11: D&A/Revenue | C11: =IF(('Data Schema'!B36/'Data Schema'!B3) = D11, "N/A", 'Data Schema'!B36/'Data Schema'!B3) -> N/A | D11: ='Data Schema'!C36/'Data Schema'!C3 -> 0.019915503 | E11: ='Data Schema'!D36/'Data Schema'!D3 -> 0.019050346 | F11: ='Data Schema'!E36/'Data Schema'!E3 -> 0.018288139 | G11: ='Data Schema'!F36/'Data Schema'!F3 -> 0.017904788 | H11: =IFERROR(AVERAGE(C11:G11), "N/A") -> 0.018789694
A12: CapEx as % of Rev | B12: CapEx/Revenue | C12: =IF(ABS('Data Schema'!B38/'Data Schema'!B3) = D12, "N/A", ABS('Data Schema'!B38/'Data Schema'!B3)) -> N/A | D12: =ABS('Data Schema'!C38/'Data Schema'!C3) -> 0.037357519 | E12: =ABS('Data Schema'!D38/'Data Schema'!D3) -> 0.034924411 | F12: =ABS('Data Schema'!E38/'Data Schema'!E3) -> 0.03179325 | G12: =ABS('Data Schema'!F38/'Data Schema'!F3) -> 0.027576155 | H12: =IFERROR(AVERAGE(C12:G12), "N/A") -> 0.032912833
A13: Operating Margin | B13: Net Income / Revenue | C13: =IF(('Data Schema'!B13/'Data Schema'!B3) = D13, "N/A", 'Data Schema'!B13/'Data Schema'!B3) -> N/A | D13: ='Data Schema'!C13/'Data Schema'!C3 -> 0.030698452 | E13: ='Data Schema'!D13/'Data Schema'!D3 -> 0.02854101 | F13: ='Data Schema'!E13/'Data Schema'!E3 -> 0.023932112 | G13: ='Data Schema'!F13/'Data Schema'!F3 -> 0.019107165 | H13: =IFERROR(AVERAGE(C13:G13), "N/A") -> 0.025569685
A14: Payout Ratio | B14: Total Dividends/Net Income (DPS/EPS) | C14: =IF(ABS('Data Schema'!B39/'Data Schema'!B13)=D14,"N/A",ABS('Data Schema'!B39/'Data Schema'!B13)) -> N/A | D14: =ABS('Data Schema'!C39/'Data Schema'!C13) -> 0.36943315 | E14: =ABS('Data Schema'!D39/'Data Schema'!D13) -> 0.23122042 | F14: =ABS('Data Schema'!E39/'Data Schema'!E13) -> 0.17916317 | G14: =ABS('Data Schema'!F39/'Data Schema'!F13) -> 0.84931507 | H14: =IFERROR(AVERAGE(C14:G14), "N/A") -> 0.40728295
A15: FCFF | B15: EBIT * (1-T) + D&A -ΔWC -CapEx | C15: =IFERROR('Data Schema'!B14*(1-Calculations!C3)+'Data Schema'!B36-Calculations!C5-ABS('Data Schema'!B38),"N/A") -> N/A | D15: =IFERROR('Data Schema'!C14*(1-Calculations!D3)+'Data Schema'!C36-Calculations!D5-ABS('Data Schema'!C38),"N/A") -> 17415231 | E15: =IFERROR('Data Schema'!D14*(1-Calculations!E3)+'Data Schema'!D36-Calculations!E5-ABS('Data Schema'!D38),"N/A") -> 13025094 | F15: =IFERROR('Data Schema'!E14*(1-Calculations!F3)+'Data Schema'!E36-Calculations!F5-ABS('Data Schema'!E38),"N/A") -> 8510004.9 | G15: =IFERROR('Data Schema'!F14*(1-Calculations!G3)+'Data Schema'!F36-Calculations!G5-ABS('Data Schema'!F38),"N/A") -> N/A | H15: =IFERROR(AVERAGE(C15:G15), "N/A") -> 12983443
A16: Market Cap (VE) | B16: Price * Diluted Shares | C16: =B77*'Data Schema'!B17 -> 991759860 | D16: =_xlfn.XLOOKUP(DATE(D1, 12, 31), $A$76:$A$211, $B$76:$B$211, , -1)*'Data Schema'!C17 -> 991759860 | E16: =_xlfn.XLOOKUP(DATE(E1, 12, 31), $A$76:$A$211, $B$76:$B$211, , 1)*'Data Schema'!D17 -> 960830900 | F16: =_xlfn.XLOOKUP(DATE(F1, 12, 31), $A$76:$A$211, $B$76:$B$211, , 1)*'Data Schema'!E17 -> 786719240 | G16: =_xlfn.XLOOKUP(DATE(G1, 12, 31), $A$76:$A$211, $B$76:$B$211, , 1)*'Data Schema'!F17 -> 441267600 | H16: =IFERROR(AVERAGE(C16:G16), "N/A") -> 834467492
A18: Components Calculations | B18: Formula | C18: Current Value
A19: Market Debt Valuation (VD) | B19: Use Total Debt as Proxy | C19: ='Data Schema'!C31 -> 67095000
A20: Equity Risk Premium | B20: Rm - Rf | C20: =C27-C26 -> 0.0492
A21: Cost of Equity (Ke) | B21: Rf + β * (Rm - Rf) | C21: =C26+(C24*C27) -> 0.10043458
A22: Total Capital (V) | B22: VE + VD | C22: =C16+C19 -> 1058854860
A23: WACC | B23: (VE/V * Ke) + (VD/V * Kd *(1-T)) | C23: =((C16/C22)*C21)+((C19/C22)*D8*(1-D3)) -> 0.096068137
A24: Beta(β) | B24: Covariance(Rs,RSPY) / Variance (RSPY) | C24: =_xlfn.COVARIANCE.P(C77:C138,G77:G138)/_xlfn.VAR.P(G77:G138) -> 0.66260642
A25: Macro and Market Components | B25: Rationale | C25: Current Value
A26: Risk-Free Rate (Rf) | B26: Current 10-Year Treasury Yield | C26: 0.0408
A27: Expected Market Return (Rm) | B27: Historical S&P 500 CAGR (~8-10%) | C27: 0.09
A28: Terminal Growth (g) | B28: Inflation or GDP proxy (2-3%) | C28: 0.025
A30: Liquidity & Solvency | B30: Formula | C30: TTM | D30: ='Data Schema'!C1 -> 2026 | E30: ='Data Schema'!D1 -> 2025 | F30: ='Data Schema'!E1 -> 2024 | G30: ='Data Schema'!F1 -> 2023 | H30: Average
A31: Current Ratio | B31: Current Assets / Current Liability | C31: =IFERROR('Data Schema'!B20/'Data Schema'!B27,"N/A") -> N/A | D31: =IFERROR('Data Schema'!C20/'Data Schema'!C27,"N/A") -> 0.78975332 | E31: =IFERROR('Data Schema'!D20/'Data Schema'!D27,"N/A") -> 0.82268285 | F31: =IFERROR('Data Schema'!E20/'Data Schema'!E27,"N/A") -> 0.83186712 | G31: =IFERROR('Data Schema'!F20/'Data Schema'!F27,"N/A") -> 0.82057095 | H31: =IFERROR(AVERAGE(C31:G31),"N/A") -> 0.81621856
A32: Quick Ratio | B32: (AR +Cash&Equiv + ST Investments / Current Liabilities | C32: =IFERROR((('Data Schema'!B21+'Data Schema'!B23+'Data Schema'!B24)/'Data Schema'!B27),"N/A") -> N/A | D32: =IFERROR((('Data Schema'!C21+'Data Schema'!C23+'Data Schema'!C24)/'Data Schema'!C27),"N/A") -> 0.20377039 | E32: =IFERROR((('Data Schema'!D21+'Data Schema'!D23+'Data Schema'!D24)/'Data Schema'!D27),"N/A") -> 0.1968442 | F32: =IFERROR((('Data Schema'!E21+'Data Schema'!E23+'Data Schema'!E24)/'Data Schema'!E27),"N/A") -> 0.20194774 | G32: =IFERROR((('Data Schema'!F21+'Data Schema'!F23+'Data Schema'!F24)/'Data Schema'!F27),"N/A") -> 0.17959175 | H32: =IFERROR(AVERAGE(C32:G32),"N/A") -> 0.19553852
A33: Debt-to-Equity Ratio | B33: Total Debt / Total Equity | C33: =IFERROR('Data Schema'!B31/'Data Schema'!B29,"N/A") -> N/A | D33: =IFERROR('Data Schema'!C31/'Data Schema'!C29,"N/A") -> 0.63189866 | E33: =IFERROR('Data Schema'!D31/'Data Schema'!D29,"N/A") -> 0.6153421 | F33: =IFERROR('Data Schema'!E31/'Data Schema'!E29,"N/A") -> 0.67704895 | G33: =IFERROR('Data Schema'!F31/'Data Schema'!F29,"N/A") -> 0.70153945 | H33: =IFERROR(AVERAGE(C33:G33),"N/A") -> 0.65645729
A34: Debt to Assets Ratio | B34: Total Debt / Total Assets | C34: =IFERROR('Data Schema'!B31/'Data Schema'!B19,"N/A") -> N/A | D34: =IFERROR('Data Schema'!C31/'Data Schema'!C19,"N/A") -> 0.23569562 | E34: =IFERROR('Data Schema'!D31/'Data Schema'!D19,"N/A") -> 0.23047814 | F34: =IFERROR('Data Schema'!E31/'Data Schema'!E19,"N/A") -> 0.24295263 | G34: =IFERROR('Data Schema'!F31/'Data Schema'!F19,"N/A") -> 0.24228506 | H34: =IFERROR(AVERAGE(C34:G34),"N/A") -> 0.23785286
A35: Interest Coverage Ratio | B35: EBIT / Interest Expense | C35: =IFERROR('Data Schema'!A14/'Data Schema'!A9,"N/A") -> N/A | D35: =IFERROR('Data Schema'!B14/'Data Schema'!B9,"N/A") -> 11.528403 | E35: =IFERROR('Data Schema'!C14/'Data Schema'!C9,"N/A") -> 11.528403 | F35: =IFERROR('Data Schema'!D14/'Data Schema'!D9,"N/A") -> 10.644062 | G35: =IFERROR('Data Schema'!E14/'Data Schema'!E9,"N/A") -> 9.1431234 | H35: =IFERROR(AVERAGE(C35:G35),"N/A") -> 10.710998
A36: Profitability & Cash Flow | B36: Formula | C36: TTM | D36: ='Data Schema'!C1 -> 2026 | E36: ='Data Schema'!D1 -> 2025 | F36: ='Data Schema'!E1 -> 2024 | G36: ='Data Schema'!F1 -> 2023 | H36: Average
A37: Gross Margin % | B37: Gross Profit / Revenue | C37: =IF('Data Schema'!B5/'Data Schema'!B3=D37,"N/A",'Data Schema'!B5/'Data Schema'!B3) -> N/A | D37: ='Data Schema'!C5/'Data Schema'!C3 -> 0.249267 | E37: ='Data Schema'!D5/'Data Schema'!D3 -> 0.24851061 | F37: ='Data Schema'!E5/'Data Schema'!E3 -> 0.24375391 | G37: ='Data Schema'!F5/'Data Schema'!F3 -> 0.24140464 | H37: =IFERROR(AVERAGE(C37:G37),"N/A") -> 0.24573404
A38: Operating Margin % | B38: EBIT / Revenue | C38: =IF('Data Schema'!B14/'Data Schema'!B3=D38,"N/A",'Data Schema'!B14/'Data Schema'!B3) -> N/A | D38: ='Data Schema'!C14/'Data Schema'!C3 -> 0.045246318 | E38: ='Data Schema'!D14/'Data Schema'!D3 -> 0.042639706 | F38: ='Data Schema'!E14/'Data Schema'!E3 -> 0.03784918 | G38: ='Data Schema'!F14/'Data Schema'!F3 -> 0.031317429 | H38: =IFERROR(AVERAGE(C38:G38),"N/A") -> 0.039263158
A39: Net Profit Margin | B39: Net Income / Revenue | C39: =IF('Data Schema'!B13/'Data Schema'!B3=D39,"N/A",'Data Schema'!B13/'Data Schema'!B3) -> N/A | D39: ='Data Schema'!C13/'Data Schema'!C3 -> 0.030698452 | E39: ='Data Schema'!D13/'Data Schema'!D3 -> 0.02854101 | F39: ='Data Schema'!E13/'Data Schema'!E3 -> 0.023932112 | G39: ='Data Schema'!F13/'Data Schema'!F3 -> 0.019107165 | H39: =IFERROR(AVERAGE(C39:G39),"N/A") -> 0.025569685
A40: Return on Asset (ROA) | B40: Net Income / Total Assets | C40: =IFERROR('Data Schema'!B13/'Data Schema'!B19,"N/A") -> N/A | D40: =IFERROR('Data Schema'!C13/'Data Schema'!C19,"N/A") -> 0.076907134 | E40: =IFERROR('Data Schema'!D13/'Data Schema'!D19,"N/A") -> 0.074517968 | F40: =IFERROR('Data Schema'!E13/'Data Schema'!E19,"N/A") -> 0.061454285 | G40: =IFERROR('Data Schema'!F13/'Data Schema'!F19,"N/A") -> 0.048026908 | H40: =IFERROR(AVERAGE(C40:G40),"N/A") -> 0.065226574
A41: Return on Equity (ROE) | B41: Net Income / Total Equity | C41: =IFERROR('Data Schema'!B13/'Data Schema'!B29,"N/A") -> N/A | D41: =IFERROR('Data Schema'!C13/'Data Schema'!C29,"N/A") -> 0.20618761 | E41: =IFERROR('Data Schema'!D13/'Data Schema'!D29,"N/A") -> 0.19895181 | F41: =IFERROR('Data Schema'!E13/'Data Schema'!E29,"N/A") -> 0.17125791 | G41: =IFERROR('Data Schema'!F13/'Data Schema'!F29,"N/A") -> 0.13906252 | H41: =IFERROR(AVERAGE(C41:G41),"N/A") -> 0.17886496
A42: FCF Margin | B42: FCFF / Revenue | C42: =IFERROR(C15/'Data Schema'!B3,"N/A") -> N/A | D42: =IFERROR(D15/'Data Schema'!C3,"N/A") -> 0.024419706 | E42: =IFERROR(E15/'Data Schema'!D3,"N/A") -> 0.019126845 | F42: =IFERROR(F15/'Data Schema'!E3,"N/A") -> 0.013130191 | G42: =IFERROR(G15/'Data Schema'!F3,"N/A") -> N/A | H42: =IFERROR(AVERAGE(C42:G42),"N/A") -> 0.018892247
A43: OCF/ Net Income | B43: Operating Cash Flow / Net Income | C43: =IF('Data Schema'!B40/'Data Schema'!B13=D43,"N/A",'Data Schema'!B40/'Data Schema'!B13) -> N/A | D43: ='Data Schema'!C40/'Data Schema'!C13 -> 0.6816334 | E43: ='Data Schema'!D40/'Data Schema'!D13 -> 0.65136859 | F43: ='Data Schema'!E40/'Data Schema'!E13 -> 0.97479208 | G43: ='Data Schema'!F40/'Data Schema'!F13 -> 1.0260274 | H43: =IFERROR(AVERAGE(C43:G43),"N/A") -> 0.83345537
A44: Efficiency & Leverage Ratios | B44: Formula | C44: TTM | D44: ='Data Schema'!C1 -> 2026 | E44: ='Data Schema'!D1 -> 2025 | F44: ='Data Schema'!E1 -> 2024 | G44: ='Data Schema'!F1 -> 2023 | H44: Average
A45: Asset Turnover | B45: Revenue / Average Total Assets | C45: =IFERROR('Data Schema'!A3/(('Data Schema'!B19+'Data Schema'!C19)/2),"N/A") -> N/A | D45: =IFERROR('Data Schema'!B3/(('Data Schema'!C19+'Data Schema'!D19)/2),"N/A") -> 2.6147562 | E45: =IFERROR('Data Schema'!C3/(('Data Schema'!D19+'Data Schema'!E19)/2),"N/A") -> 2.7791599 | F45: =IFERROR('Data Schema'!D3/(('Data Schema'!E19+'Data Schema'!F19)/2),"N/A") -> 2.7481457 | G45: Base | H45: =IFERROR(AVERAGE(C45:G45),"N/A") -> 2.7140206
A46: Inventory Turnover | B46: COGS / Average Inventory | C46: =IFERROR('Data Schema'!B4/(('Data Schema'!B25+'Data Schema'!C25)/2),"N/A") -> N/A | D46: =IFERROR('Data Schema'!C4/(('Data Schema'!C25+'Data Schema'!D25)/2),"N/A") -> 9.2881182 | E46: =IFERROR('Data Schema'!D4/(('Data Schema'!D25+'Data Schema'!E25)/2),"N/A") -> 9.1936907 | F46: =IFERROR('Data Schema'!E4/(('Data Schema'!E25+'Data Schema'!F25)/2),"N/A") -> 8.7943087 | G46: =IFERROR('Data Schema'!F4/(('Data Schema'!F25+'Data Schema'!G25)/2),"N/A") -> 16.392852 | H46: =IFERROR(AVERAGE(C46:G46),"N/A") -> 10.917242
A47: Equity Multiplier | B47: Total Assets / Total Equity | C47: =IFERROR('Data Schema'!B19/'Data Schema'!B29,"N/A") -> N/A | D47: =IFERROR('Data Schema'!C19/'Data Schema'!C29,"N/A") -> 2.6809945 | E47: =IFERROR('Data Schema'!D19/'Data Schema'!D29,"N/A") -> 2.6698501 | F47: =IFERROR('Data Schema'!E19/'Data Schema'!E29,"N/A") -> 2.7867529 | G47: =IFERROR('Data Schema'!F19/'Data Schema'!F29,"N/A") -> 2.8955126 | H47: =IFERROR(AVERAGE(C47:G47),"N/A") -> 2.7582776
A48: Market/Valuation Ratios | B48: Formula | C48: TTM | D48: ='Data Schema'!C1 -> 2026 | E48: ='Data Schema'!D1 -> 2025 | F48: ='Data Schema'!E1 -> 2024 | G48: ='Data Schema'!F1 -> 2023 | H48: Average
A49: Book Value per Share | B49: Total Equity / Average Diluted Shares | C49: =IFERROR('Data Schema'!B29/'Data Schema'!B17,"N/A") -> N/A | D49: =IFERROR('Data Schema'!C29/'Data Schema'!C17,"N/A") -> 13.236101 | E49: =IFERROR('Data Schema'!D29/'Data Schema'!D17,"N/A") -> 12.089098 | F49: =IFERROR('Data Schema'!E29/'Data Schema'!E17,"N/A") -> 11.170572 | G49: =IFERROR('Data Schema'!F29/'Data Schema'!F17,"N/A") -> 10.240307 | H49: =AVERAGE(C49:G49) -> 11.68402
A50: Price to Earnings Ratio (P/E) | B50: Share price / EPS | C50: =B77/'Data Schema'!B16 -> 45.285714 | D50: =_xlfn.XLOOKUP(DATE(D48, 12, 31), $A$76:$A$211, $B$76:$B$211, , -1)/'Data Schema'!C16 -> 45.285714 | E50: =_xlfn.XLOOKUP(DATE(E48, 12, 31), $A$76:$A$211, $B$76:$B$211, , 1)/'Data Schema'!D16 -> 49.3361 | F50: =_xlfn.XLOOKUP(DATE(F48, 12, 31), $A$76:$A$211, $B$76:$B$211, , 1)/'Data Schema'!E16 -> 50.801047 | G50: =_xlfn.XLOOKUP(DATE(G48, 12, 31), $A$76:$A$211, $B$76:$B$211, , 1)/'Data Schema'!F16 -> 37.887324 | H50: =AVERAGE(C50:G50) -> 45.71918
A51: Price to Book Ratio (P/B) | B51: Share price / Book Value per share | C51: =IFERROR(IF(OR(B77/C2=D51,(B77/C2=0)),"N/A",B77/C2), "N/A") -> N/A | D51: =_xlfn.XLOOKUP(DATE(D48, 12, 31), $A$76:$A$211, $B$76:$B$211, , -1)/D2 -> 9.2786539 | E51: =_xlfn.XLOOKUP(DATE(E48, 12, 31), $A$76:$A$211, $B$76:$B$211, , 1)/E2 -> 9.7659338 | F51: =_xlfn.XLOOKUP(DATE(F48, 12, 31), $A$76:$A$211, $B$76:$B$211, , 1)/F2 -> 8.6283647 | G51: =_xlfn.XLOOKUP(DATE(G48, 12, 31), $A$76:$A$211, $B$76:$B$211, , 1)/G2 -> 5.188413 | H51: =AVERAGE(C51:G51) -> 8.2153413
A52: Price to Sales (P/S) | B52: Market Cap / Total Revenue | C52: =IFERROR(IF(OR(C16/'Data Schema'!B3=D52,(C16/'Data Schema'!B3=0)),"N/A",C16/'Data Schema'!B3), "N/A") -> N/A | D52: =D16/'Data Schema'!C3 -> 1.3906496 | E52: =E16/'Data Schema'!D3 -> 1.4109428 | F52: =F16/'Data Schema'!E3 -> 1.2138388 | G52: =G16/'Data Schema'!F3 -> 0.72186413 | H52: =AVERAGE(C52:G52) -> 1.1843238
A53: Growth Rates | B53: Formula | C53: TTM | D53: ='Data Schema'!C1 -> 2026 | E53: ='Data Schema'!D1 -> 2025 | F53: ='Data Schema'!E1 -> 2024 | G53: ='Data Schema'!F1 -> 2023 | H53: Average
A54: Revenue Growth | B54: (Metrict / Metrict-1) -1 | C54: =IF(IFERROR(('Data Schema'!B3/'Data Schema'!C3)-1,"N/A")=0,"N/A",(IFERROR(('Data Schema'!B3/'Data Schema'!C3)-1,"N/A"))) -> N/A | D54: =IFERROR(('Data Schema'!C3/'Data Schema'!D3)-1,"N/A") -> 0.047252142 | E54: =IFERROR(('Data Schema'!D3/'Data Schema'!E3)-1,"N/A") -> 0.050700096 | F54: =IFERROR(('Data Schema'!E3/'Data Schema'!F3)-1,"N/A") -> 0.06025955 | G54: =IFERROR(('Data Schema'!F3/'Data Schema'!G3)-1,"N/A") -> N/A | H54: =AVERAGE(C54:G54) -> 0.052737263
A55: Net Income Growth | C55: =IF(IFERROR(('Data Schema'!B13/'Data Schema'!C13)-1,"N/A")=0,"N/A",(IFERROR(('Data Schema'!B13/'Data Schema'!C13)-1,"N/A"))) -> N/A | D55: =IFERROR(('Data Schema'!C13/'Data Schema'!D13)-1,"N/A") -> 0.1264149 | E55: =IFERROR(('Data Schema'!D13/'Data Schema'!E13)-1,"N/A") -> 0.25304623 | F55: =IFERROR(('Data Schema'!E13/'Data Schema'!F13)-1,"N/A") -> 0.32799658 | G55: =IFERROR(('Data Schema'!F13/'Data Schema'!G13)-1,"N/A") -> N/A | H55: =AVERAGE(C55:G55) -> 0.23581923
A56: EPS Growth | C56: =IF(IFERROR(('Data Schema'!B16/'Data Schema'!C16)-1,"N/A")=0,"N/A",(IFERROR(('Data Schema'!B16/'Data Schema'!C16)-1,"N/A"))) -> N/A | D56: =IFERROR(('Data Schema'!C16/'Data Schema'!D16)-1,"N/A") -> 0.13278008 | E56: =IFERROR(('Data Schema'!D16/'Data Schema'!E16)-1,"N/A") -> 0.2617801 | F56: =IFERROR(('Data Schema'!E16/'Data Schema'!F16)-1,"N/A") -> 0.34507042 | G56: =IFERROR(('Data Schema'!F16/'Data Schema'!G16)-1,"N/A") -> N/A | H56: =AVERAGE(C56:G56) -> 0.24654354
A57: Assets Growth | C57: =IF(IFERROR(('Data Schema'!B19/'Data Schema'!C19)-1,"N/A")=0,"N/A",(IFERROR(('Data Schema'!B19/'Data Schema'!C19)-1,"N/A"))) -> N/A | D57: =IFERROR(('Data Schema'!C19/'Data Schema'!D19)-1,"N/A") -> 0.091422152 | E57: =IFERROR(('Data Schema'!D19/'Data Schema'!E19)-1,"N/A") -> 0.033375727 | F57: =IFERROR(('Data Schema'!E19/'Data Schema'!F19)-1,"N/A") -> 0.037837638 | G57: =IFERROR(('Data Schema'!F19/'Data Schema'!G19)-1,"N/A") -> N/A | H57: =AVERAGE(C57:G57) -> 0.054211839
A58: Dividends Growth | C58: =IF(IFERROR(('Data Schema'!B39/'Data Schema'!C39)-1,"N/A")=0,"N/A",(IFERROR(('Data Schema'!B39/'Data Schema'!C39)-1,"N/A"))) -> N/A | D58: =IFERROR(('Data Schema'!C39/'Data Schema'!D39)-1,"N/A") -> 0.79973298 | E58: =IFERROR(('Data Schema'!D39/'Data Schema'!E39)-1,"N/A") -> 0.61712846 | F58: =IFERROR(('Data Schema'!E39/'Data Schema'!F39)-1,"N/A") -> -0.71985887 | G58: =IFERROR(('Data Schema'!F39/'Data Schema'!G39)-1,"N/A") -> N/A | H58: =AVERAGE(C58:G58) -> 0.23233419
A60: Additional Ratios | B60: Formula | C60: TTM | D60: ='Data Schema'!C1 -> 2026 | E60: ='Data Schema'!D1 -> 2025 | F60: ='Data Schema'!E1 -> 2024 | G60: ='Data Schema'!F1 -> 2023 | H60: Average
A61: ROIC (Return on Invested Capital) | B61: EBIT*(1-T)/(Equity+Debt-Cash) | C61: =IFERROR('Data Schema'!B14*(1-Calculations!C3)/('Data Schema'!B29+'Data Schema'!B31-'Data Schema'!B21),"N/A") -> N/A | D61: =IFERROR('Data Schema'!C14*(1-Calculations!D3)/('Data Schema'!C29+'Data Schema'!C31-'Data Schema'!C21),"N/A") -> 0.15001864 | E61: =IFERROR('Data Schema'!D14*(1-Calculations!E3)/('Data Schema'!D29+'Data Schema'!D31-'Data Schema'!D21),"N/A") -> 0.1495412 | F61: =IFERROR('Data Schema'!E14*(1-Calculations!F3)/('Data Schema'!E29+'Data Schema'!E31-'Data Schema'!E21),"N/A") -> 0.12862528 | G61: =IFERROR('Data Schema'!F14*(1-Calculations!G3)/('Data Schema'!F29+'Data Schema'!F31-'Data Schema'!F21),"N/A") -> 0.094603159 | H61: =IFERROR(AVERAGE(D61:G61),"N/A") -> 0.13069707
A62: EBITDA Margin | B62: EBITDA / Revenue | C62: =IFERROR('Data Schema'!B15/'Data Schema'!B3,"N/A") -> 0.065161821 | D62: =IFERROR('Data Schema'!C15/'Data Schema'!C3,"N/A") -> 0.065161821 | E62: =IFERROR('Data Schema'!D15/'Data Schema'!D3,"N/A") -> 0.061690052 | F62: =IFERROR('Data Schema'!E15/'Data Schema'!E3,"N/A") -> 0.056137319 | G62: =IFERROR('Data Schema'!F15/'Data Schema'!F3,"N/A") -> 0.049222217 | H62: =IFERROR(AVERAGE(D62:G62),"N/A") -> 0.058052852
A63: Cash Ratio | B63: Cash / Current Liabilities | C63: =IFERROR('Data Schema'!B21/'Data Schema'!B27,"N/A") -> N/A | D63: =IFERROR('Data Schema'!C21/'Data Schema'!C27,"N/A") -> 0.09981483 | E63: =IFERROR('Data Schema'!D21/'Data Schema'!D27,"N/A") -> 0.093566222 | F63: =IFERROR('Data Schema'!E21/'Data Schema'!E27,"N/A") -> 0.10676838 | G63: =IFERROR('Data Schema'!F21/'Data Schema'!F27,"N/A") -> 0.093548667 | H63: =IFERROR(AVERAGE(D63:G63),"N/A") -> 0.098424525
A64: Revenue CAGR (3-Year) | B64: (Rev_latest/Rev_oldest)^(1/3)-1 | C64: =IFERROR(('Data Schema'!C3/'Data Schema'!F3)^(1/3)-1,"N/A") -> 0.052722909
A65: Earnings Growth (Avg) | B65: Average Net Income Growth | C65: =H55 -> 0.23581923
A67: Metric | B67: WMT Value | C67: Peer Avg | D67: Premium/Discount % | E67: Peer-Implied Price
A68: P/E | B68: ='Data Schema'!B44 -> 43.6 | C68: ='Data Schema'!F44 -> 27.556667 | D68: =IFERROR((B68-C68)/C68,"N/A") -> 0.58219427 | E68: =IFERROR(C68*'Data Schema'!C16,"N/A") -> 75.2297
A69: Forward P/E | B69: ='Data Schema'!B45 -> 40.32 | C69: ='Data Schema'!F45 -> 26.523333 | D69: =IFERROR((B69-C69)/C69,"N/A") -> 0.52017092 | E69: =IFERROR(C69*'Data Schema'!C16,"N/A") -> 72.4087
A70: P/FCF | B70: ='Data Schema'!B46 -> 63.98 | C70: ='Data Schema'!F46 -> 25.733333 | D70: =IFERROR((B70-C70)/C70,"N/A") -> 1.4862694 | E70: =IFERROR(C70*'Data Schema'!C40/'Data Schema'!B17,"N/A") -> 47.870672
A71: P/B | B71: ='Data Schema'!B47 -> 9.53 | C71: ='Data Schema'!F47 -> 6.61 | D71: =IFERROR((B71-C71)/C71,"N/A") -> 0.44175492 | E71: =IFERROR(C71*Calculations!D2,"N/A") -> 88.072506
A72: P/S | B72: ='Data Schema'!B48 -> 1.34 | C72: ='Data Schema'!F48 -> 0.88 | D72: =IFERROR((B72-C72)/C72,"N/A") -> 0.52272727 | E72: =IFERROR(C72*'Data Schema'!C3/'Data Schema'!B17,"N/A") -> 78.23279
A73: EV/EBITDA | B73: ='Data Schema'!B49 -> 21.63 | C73: ='Data Schema'!F49 -> 16.943333 | D73: =IFERROR((B73-C73)/C73,"N/A") -> 0.2766083 | E73: =IFERROR((C73*'Data Schema'!C15-'Data Schema'!C31+'Data Schema'!C21)/'Data Schema'!B17,"N/A") -> 91.125111
A75: Stock Price History | E75: SPY Price History
A76: Date | B76: Price | C76: Rate | E76: Date | F76: Price | G76: Rate
A77: {=_xlfn._xlws.FILTER(CHOOSE({1,2}, 'Raw Data Pasting'!E:E, 'Raw Data Pasting'!J:J), ISNUMBER('Raw Data Pasting'!J:J))} -> 46105 | B77: 123.63 | C77: =IFERROR(LN(B77/B78),"") -> 0.040020191 | E77: {=_xlfn._xlws.FILTER(CHOOSE({1,2}, 'Raw Data Pasting'!M:M, 'Raw Data Pasting'!R:R), ISNUMBER('Raw Data Pasting'!R:R))} -> 46097 | F77: 668.81 | G77: =IFERROR(LN(F77/F78),"") -> 0.0097964873
A78: 46082 | B78: 118.78 | C78: =IFERROR(LN(B78/B79),"") -> -0.072332409 | E78: 46082 | F78: 662.29 | G78: =IFERROR(LN(F78/F79),"") -> -0.035159524
A79: 46054 | B79: 127.69 | C79: =IFERROR(LN(B79/B80),"") -> 0.071322648 | E79: 46054 | F79: 685.99 | G79: =IFERROR(LN(F79/F80),"") -> -0.0086795517
A80: 46023 | B80: 118.9 | C80: =IFERROR(LN(B80/B81),"") -> 0.069113028 | E80: 46023 | F80: 691.97 | G80: =IFERROR(LN(F80/F81),"") -> 0.017582166
A81: 45992 | B81: 110.96 | C81: =IFERROR(LN(B81/B82),"") -> 0.0081441044 | E81: 45992 | F81: 679.91 | G81: =IFERROR(LN(F81/F82),"") -> -0.002159717
A82: 45962 | B82: 110.06 | C82: =IFERROR(LN(B82/B83),"") -> 0.088184979 | E82: 45962 | F82: 681.38 | G82: =IFERROR(LN(F82/F83),"") -> 0.0019538286
A83: 45931 | B83: 100.77 | C83: =IFERROR(LN(B83/B84),"") -> -0.018387028 | E83: 45931 | F83: 680.05 | G83: =IFERROR(LN(F83/F84),"") -> 0.026326916
A84: 45901 | B84: 102.64 | C84: =IFERROR(LN(B84/B85),"") -> 0.063136543 | E84: 45901 | F84: 662.38 | G84: =IFERROR(LN(F84/F85),"") -> 0.032232896
A85: 45870 | B85: 96.36 | C85: =IFERROR(LN(B85/B86),"") -> -0.010221554 | E85: 45870 | F85: 641.37 | G85: =IFERROR(LN(F85/F86),"") -> 0.020302308
A86: 45839 | B86: 97.35 | C86: =IFERROR(LN(B86/B87),"") -> 0.002056556 | E86: 45839 | F86: 628.48 | G86: =IFERROR(LN(F86/F87),"") -> 0.025722611
A87: 45809 | B87: 97.15 | C87: =IFERROR(LN(B87/B88),"") -> -0.007179518 | E87: 45809 | F87: 612.52 | G87: =IFERROR(LN(F87/F88),"") -> 0.047167045
A88: 45778 | B88: 97.85 | C88: =IFERROR(LN(B88/B89),"") -> 0.015033232 | E88: 45778 | F88: 584.3 | G88: =IFERROR(LN(F88/F89),"") -> 0.06095092
A89: 45748 | B89: 96.39 | C89: =IFERROR(LN(B89/B90),"") -> 0.10502628 | E89: 45748 | F89: 549.75 | G89: =IFERROR(LN(F89/F90),"") -> -0.0057135239
... A137: 44287 | B137: 43.67 | C137: =IFERROR(LN(B137/B138),"") | E137: 44287 | F137: 390.82 | G137: =IFERROR(LN(F137/F138),"")
C138: =IFERROR(LN(B138/B139),"") | G138: =IFERROR(LN(F138/F139),"")
C139: =IFERROR(LN(B139/B140),"") | G139: =IFERROR(LN(F139/F140),"")
C140: =IFERROR(LN(B140/B141),"") | G140: =IFERROR(LN(F140/F141),"")
C141: =IFERROR(LN(B141/B142),"") | G141: =IFERROR(LN(F141/F142),"")
C142: =IFERROR(LN(B142/B143),"") | G142: =IFERROR(LN(F142/F143),"")
C143: =IFERROR(LN(B143/B144),"") | G143: =IFERROR(LN(F143/F144),"")
C144: =IFERROR(LN(B144/B145),"") | G144: =IFERROR(LN(F144/F145),"")
C145: =IFERROR(LN(B145/B146),"") | G145: =IFERROR(LN(F145/F146),"")
C146: =IFERROR(LN(B146/B147),"") | G146: =IFERROR(LN(F146/F147),"")
C147: =IFERROR(LN(B147/B148),"")

Sheet Raw Data Pasting
A1: Income Statement PASTE ON A2 | B1: Balance Sheet PASTE ON B2 | C1: Cash Flow PASTE ON C2 | E1: Historical Price of Stock PASTE ON E2 | J1: Using this Adj price | M1: Historical SPY Data for Beta Calculations PASTE ON M2 | U1: Peer Comparison PASTE ON U2 | AA1: Current Stock Valuation PASTE ON AA2
A2: Breakdown | B2: Breakdown | C2: Breakdown | E2: Date | F2: Open | G2: High | H2: Low | I2: Close | J2: Adj Close | K2: Volume | M2: Date | N2: Open | O2: High | P2: Low | Q2: Close | R2: Adj Close | S2: Volume | U2: Valuation Measures | AA2: Current | AB2: 46053 | AC2: 45961 | AD2: 45869 | AE2: 45777 | AF2: 45688
A3: TTM | B3: 46053 | C3: TTM | E3: Date | F3: Open | G3: High | H3: Low | I3: Close | J3: Adj Close | K3: Volume | M3: 46097 | N3: 669.27 | O3: 669.08 | P3: 667.69 | Q3: 668.81 | R3: 668.81 | S3: 6197383 | U3: As of Mar 31, 2026 | V3: WMT | W3: COST | X3: TGT | Y3: DG | AA3: Market Cap | AB3: 810.84B | AC3: 949.57B | AD3: 806.61B | AE3: 781.39B | AF3: 776.64B | AG3: 787.64B
A4: 46053 | B4: 45688 | C4: 46053 | E4: 46105 | F4: 120.63 | G4: 124.11 | H4: 120.5 | I4: 123.63 | J4: 123.63 | K4: 7857448 | M4: 46082 | N4: 678.7 | O4: 688.62 | P4: 661.36 | Q4: 662.29 | R4: 662.29 | S4: 937358000 | V4: Walmart Inc. | W4: Costco Wholesale Corporation | X4: Target Corporation | Y4: Dollar General Corporation | AA4: Enterprise Value | AB4: 866.42B | AC4: 1.01T | AD4: 862.19B | AE4: 839.28B | AF4: 827.72B | AG4: 839.34B
A5: 45688 | B5: 45322 | C5: 45688 | E5: 46101 | F5: 0.248 Dividend | M5: 46054 | N5: 689.58 | O5: 697.14 | P5: 675.78 | Q5: 685.99 | R5: 685.99 | S5: 1614970000 | U5: Price to Earnings Per Share | V5: 43.6 | W5: 50.56 | X5: 13.93 | Y5: 18.18 | AA5: Trailing P/E | AB5: 38.38 | AC5: 41.66 | AD5: 38.18 | AE5: 41.87 | AF5: 40.35 | AG5: 40.56
A6: 45322 | B6: 44957 | C6: 45322 | E6: 46082 | F6: 127.46 | G6: 128.75 | H6: 118.02 | I6: 119.02 | J6: 118.78 | K6: 329012500 | M6: 46023 | N6: 685.71 | O6: 697.84 | P6: 676.57 | Q6: 691.97 | R6: 691.97 | S6: 1600537800 | U6: Forward Price to Earnings Per Share | V6: 40.32 | W6: 48.08 | X6: 14.16 | Y6: 17.33 | AA6: Forward P/E | AB6: 33.67 | AC6: 39.22 | AD6: 33.56 | AE6: 37.59 | AF6: 36.9 | AG6: 35.59
A7: 44957 | B7: Total Assets | C7: 44957 | E7: 46054 | F7: 119.5 | G7: 134.69 | H7: 119.05 | I7: 127.95 | J7: 127.69 | K7: 540115800 | M7: 46010 | N7: 1.993 Dividend | U7: Price to Free Cash Flow Per Share | V7: 63.98 | W7: 47.51 | X7: 18.2 | Y7: 11.49 | AA7: PEG Ratio (5yr expected) | AB7: 3.37 | AC7: 4.33 | AD7: 3.92 | AE7: 3.75 | AF7: 3.86 | AG7: 2.96
A8: Total Revenue | B8: 284668000 | C8: Operating Cash Flow | E8: 46023 | F8: 111.43 | G8: 121.62 | H8: 109.81 | I8: 119.14 | J8: 118.9 | K8: 909083600 | M8: 45992 | N8: 678.81 | O8: 691.66 | P8: 671.2 | Q8: 681.92 | R8: 679.91 | S8: 1656188700 | U8: Price to Book Value Per Share | V8: 9.53 | W8: 13.44 | X8: 3.17 | Y8: 3.22 | AA8: Price/Sales | AB8: 1.18 | AC8: 1.36 | AD8: 1.18 | AE8: 1.15 | AF8: 1.15 | AG8: 1.18
A9: 713163000 | B9: 260823000 | C9: 41565000 | E9: 46003 | F9: 0.235 Dividend | M9: 45962 | N9: 685.67 | O9: 685.8 | P9: 650.85 | Q9: 683.39 | R9: 681.38 | S9: 1664668300 | U9: Price to Sales Ratio | V9: 1.34 | W9: 1.51 | X9: 0.49 | Y9: 0.64 | AA9: Price/Book | AB9: 9 | AC9: 9.88 | AD9: 8.95 | AE9: 9.33 | AF9: 8.53 | AG9: 8.94
A10: 713163000 | B10: 252399000 | C10: 41565000 | E10: 45992 | F10: 110.51 | G10: 117.45 | H10: 110.36 | I10: 111.41 | J10: 110.96 | K10: 442913500 | M10: 45931 | N10: 663.17 | O10: 689.7 | P10: 652.84 | Q10: 682.06 | R10: 680.05 | S10: 1781815100 | U10: EV/EBITDA | V10: 21.63 | W10: 29.96 | X10: 7.92 | Y10: 12.95 | AA10: Enterprise Value/Revenue | AB10: 1.25 | AC10: 1.43 | AD10: 1.24 | AE10: 1.23 | AF10: 1.22 | AG10: 1.25
A11: 680985000 | B11: 243197000 | C11: 36443000 | E11: 45962 | F11: 100.82 | G11: 110.7 | H11: 98.88 | I11: 110.51 | J11: 110.06 | K11: 391415900 | M11: 45919 | N11: 1.831 Dividend | AA11: Enterprise Value/EBITDA | AB11: 19.42 | AC11: 21.39 | AD11: 19.33 | AE11: 20.4 | AF11: 19.7 | AG11: 19.85
A12: 648125000 | B12: Current Assets | C12: 35726000 | E12: 45931 | F12: 102.56 | G12: 109.58 | H12: 99.87 | I12: 101.18 | J12: 100.77 | K12: 348809500 | M12: 45901 | N12: 637.5 | O12: 667.34 | P12: 634.92 | Q12: 666.18 | R12: 662.38 | S12: 1606348500
A13: 611289000 | B13: 84874000 | C13: 28841000 | E13: 45901 | F13: 97.23 | G13: 106.11 | H13: 96.51 | I13: 103.06 | J13: 102.64 | K13: 326990400 | M13: 45870 | N13: 626.3 | O13: 649.48 | P13: 619.29 | Q13: 645.05 | R13: 641.37 | S13: 1424047400
A14: Operating Revenue | B14: 79458000 | C14: Cash Flow from Continuing Operating Activities | E14: 45884 | F14: 0.235 Dividend | M14: 45839 | N14: 616.36 | O14: 639.85 | P14: 615.52 | Q14: 632.08 | R14: 628.48 | S14: 1479850800
A15: 713163000 | B15: 76877000 | C15: 41565000 | E15: 45870 | F15: 98 | G15: 104.72 | H15: 95.42 | I15: 96.98 | J15: 96.36 | K15: 397878500 | M15: 45828 | N15: 1.761 Dividend
A16: 713163000 | B16: 75655000 | C16: 41565000 | E16: 45839 | F16: 97.6 | G16: 99.35 | H16: 94.23 | I16: 97.98 | J16: 97.35 | K16: 289967200 | M16: 45809 | N16: 587.76 | O16: 619.22 | P16: 585.06 | Q16: 617.85 | R16: 612.52 | S16: 1495410200
A17: 680985000 | B17: Cash, Cash Equivalents & Short Term Investments | C17: 36443000 | E17: 45809 | F17: 98.84 | G17: 100.89 | H17: 93.43 | I17: 97.78 | J17: 97.15 | K17: 343221000 | M17: 45778 | N17: 560.37 | O17: 595.54 | P17: 556.04 | Q17: 589.39 | R17: 584.3 | S17: 1402172600
A18: 648125000 | B18: 10727000 | C18: 35726000 | E18: 45786 | F18: 0.235 Dividend | M18: 45748 | N18: 557.45 | O18: 567.42 | P18: 481.8 | Q18: 554.54 | R18: 549.75 | S18: 2237015100
A19: 611289000 | B19: 9037000 | C19: 28841000 | E19: 45778 | F19: 97.02 | G19: 99.74 | H19: 91.89 | I19: 98.72 | J19: 97.85 | K19: 393144900 | M19: 45737 | N19: 1.696 Dividend
A20: Cost of Revenue | B20: 9867000 | C20: Net Income from Continuing Operations | E20: 45748 | F20: 87.54 | G20: 97.78 | H20: 79.81 | I20: 97.25 | J20: 96.39 | K20: 509882700 | M20: 45717 | N20: 596.18 | O20: 597.34 | P20: 546.87 | Q20: 559.39 | R20: 552.9 | S20: 1496591400
A21: 535395000 | B21: 8625000 | C21: 22270000 | E21: 45737 | F21: 0.235 Dividend | M21: 45689 | N21: 592.67 | O21: 613.23 | P21: 582.44 | Q21: 594.18 | R21: 587.28 | S21: 871641300
A22: 535395000 | B22: Cash And Cash Equivalents | C22: 22270000 | E22: 45717 | F22: 97.98 | G22: 99.49 | H22: 83.87 | I22: 87.79 | J22: 86.78 | K22: 529824400 | M22: 45658 | N22: 589.39 | O22: 610.78 | P22: 575.35 | Q22: 601.82 | R22: 594.83 | S22: 995501600
A23: 511753000 | B23: 10727000 | C23: 20157000 | E23: 45689 | F23: 96.77 | G23: 105.3 | H23: 92.12 | I23: 98.61 | J23: 97.48 | K23: 393516500 | M23: 45646 | N23: 1.966 Dividend
A24: 490142000 | B24: 9037000 | C24: 16270000 | E24: 45658 | F24: 89.98 | G24: 99 | H24: 89.52 | I24: 98.16 | J24: 97.03 | K24: 301831600 | M24: 45627 | N24: 602.97 | O24: 609.07 | P24: 580.91 | Q24: 586.08 | R24: 577.33 | S24: 1059516700
A25: 463721000 | B25: 9867000 | C25: 11292000 | E25: 45639 | F25: 0.208 Dividend | M25: 45597 | N25: 571.32 | O25: 603.35 | P25: 567.89 | Q25: 602.55 | R25: 593.56 | S25: 901760600
A26: Gross Profit | B26: 8625000 | C26: Operating Gains Losses | E26: 45627 | F26: 92.82 | G26: 96.18 | H26: 88.91 | I26: 90.35 | J26: 89.11 | K26: 382128400 | M26: 45566 | N26: 573.4 | O26: 586.12 | P26: 565.27 | Q26: 568.64 | R26: 560.15 | S26: 976068800
A27: 177768000 | B27: Receivables | C27: -2016000 | E27: 45597 | F27: 82.53 | G27: 92.64 | H27: 81.54 | I27: 92.5 | J27: 91.23 | K27: 340242300 | M27: 45555 | N27: 1.746 Dividend
A28: 177768000 | B28: 11172000 | C28: -2016000 | E28: 45566 | F28: 80.68 | G28: 83.34 | H28: 78.98 | I28: 81.95 | J28: 80.83 | K28: 274951500 | M28: 45536 | N28: 558.35 | O28: 574.71 | P28: 539.44 | Q28: 573.76 | R28: 563.47 | S28: 1044988300
A29: 169232000 | B29: 9975000 | C29: 878000 | E29: 45536 | F29: 77.33 | G29: 81.6 | H29: 76.3 | I29: 80.75 | J29: 79.64 | K29: 358154100 | M29: 45505 | N29: 552.57 | O29: 564.2 | P29: 510.27 | Q29: 563.68 | R29: 553.57 | S29: 1244599000
A30: 157983000 | B30: 8796000 | C30: 3193000 | E30: 45520 | F30: 0.208 Dividend | M30: 45474 | N30: 545.63 | O30: 565.16 | P30: 537.45 | Q30: 550.81 | R30: 540.93 | S30: 1038465500
A31: 147568000 | B31: 7933000 | C31: 1683000 | E31: 45505 | F31: 68.91 | G31: 77.47 | H31: 66.67 | I31: 77.23 | J31: 75.96 | K31: 395298400 | M31: 45464 | N31: 1.759 Dividend
A32: Operating Expense | B32: Accounts receivable | C32: Gain Loss On Sale of Business | E32: 45474 | F32: 67.89 | G32: 71.33 | H32: 67.25 | I32: 68.64 | J32: 67.51 | K32: 288053200 | M32: 45444 | N32: 529.02 | O32: 550.28 | P32: 522.6 | Q32: 544.22 | R32: 532.74 | S32: 888367600
A33: 147943000 | B33: 11172000 | C33: -- | E33: 45444 | F33: 65.51 | G33: 69.04 | H33: 65.16 | I33: 67.71 | J33: 66.59 | K33: 288503100 | M33: 45413 | N33: 501.38 | O33: 533.07 | P33: 499.55 | Q33: 527.37 | R33: 516.25 | S33: 1153206200
A34: 147943000 | B34: 9975000 | C34: -- | E34: 45421 | F34: 0.208 Dividend | M34: 45383 | N34: 523.83 | O34: 524.38 | P34: 493.86 | Q34: 501.98 | R34: 491.39 | S34: 1593138700
A35: 139884000 | B35: 8796000 | C35: -- | E35: 45413 | F35: 59.31 | G35: 65.9 | H35: 58.58 | I35: 65.76 | J35: 64.45 | K35: 401568100 | M35: 45366 | N35: 1.595 Dividend
A36: 130971000 | B36: 7933000 | C36: 0 | E36: 45383 | F36: 60.31 | G36: 60.89 | H36: 58.56 | I36: 59.35 | J36: 58.17 | K36: 304730200 | M36: 45352 | N36: 508.98 | O36: 524.61 | P36: 504.91 | Q36: 523.07 | R36: 510.45 | S36: 1473501100
A37: 127140000 | B37: Inventory | C37: 0 | E37: 45365 | F37: 0.208 Dividend | M37: 45323 | N37: 484.63 | O37: 510.13 | P37: 483.8 | Q37: 508.08 | R37: 495.82 | S37: 1393307200
A38: Selling General and Administrative | B38: 58851000 | C38: Gain Loss On Investment Securities | E38: 45352 | F38: 58.8 | G38: 61.66 | H38: 58.2 | I38: 60.17 | J38: 58.77 | K38: 339293600 | M38: 45292 | N38: 472.16 | O38: 491.62 | P38: 466.43 | Q38: 482.88 | R38: 471.23 | S38: 1700872500
A39: -- | B39: 56435000 | C39: -2016000 | E39: 45348 | F39: 3:1 Stock Splits | M39: 45275 | N39: 1.906 Dividend
A40: -- | B40: 54892000 | C40: -2016000 | E40: 45323 | F40: 55.23 | G40: 60.45 | H40: 55.06 | I40: 58.61 | J40: 57.25 | K40: 523190700 | M40: 45261 | N40: 455.77 | O40: 477.55 | P40: 454.31 | Q40: 475.31 | R40: 461.97 | S40: 1643624300
A41: 139884000 | B41: 56576000 | C41: 878000 | E41: 45292 | F41: 52.42 | G41: 55.93 | H41: 51.87 | I41: 55.08 | J41: 53.8 | K41: 385322100 | M41: 45231 | N41: 419.2 | O41: 458.32 | P41: 418.65 | Q41: 456.4 | R41: 443.59 | S41: 1500017600
A42: 130971000 | B42: Other Current Assets | C42: 3193000 | E42: 45267 | F42: 0.19 Dividend | M42: 45200 | N42: 426.62 | O42: 438.14 | P42: 409.21 | Q42: 418.2 | R42: 406.46 | S42: 1999294400
A43: 127140000 | B43: 4124000 | C43: 1683000 | E43: 45261 | F43: 51.79 | G43: 52.78 | H43: 49.85 | I43: 52.55 | J43: 51.14 | K43: 543923100 | M43: 45184 | N43: 1.583 Dividend
A44: General & Administrative Expense | B44: 4011000 | C44: Depreciation Amortization Depletion | E44: 45231 | F44: 54.74 | G44: 56.65 | H44: 51.38 | I44: 51.9 | J44: 50.5 | K44: 536482200 | M44: 45170 | N44: 453.17 | O44: 453.67 | P44: 422.29 | Q44: 427.48 | R44: 414.02 | S44: 1588981600
A45: -- | B45: 3322000 | C45: 14203000 | E45: 45200 | F45: 53.16 | G45: 54.78 | H45: 50.55 | I45: 54.47 | J45: 53.01 | K45: 344001900 | M45: 45139 | N45: 456.27 | O45: 457.25 | P45: 433.01 | Q45: 450.35 | R45: 436.17 | S45: 1754892500
A46: -- | B46: 2521000 | C46: 14203000 | E46: 45170 | F46: 54.29 | G46: 55.28 | H46: 53.06 | I46: 53.31 | J46: 51.88 | K46: 331229700 | M46: 45108 | N46: 442.92 | O46: 459.44 | P46: 437.06 | Q46: 457.79 | R46: 443.38 | S46: 1374698500
A47: -- | B47: Total non-current assets | C47: 12973000 | E47: 45148 | F47: 0.19 Dividend | M47: 45093 | N47: 1.638 Dividend
A48: -- | B48: 199794000 | C48: 11853000 | E48: 45139 | F48: 53.32 | G48: 54.33 | H48: 51.67 | I48: 54.2 | J48: 52.56 | K48: 391674900 | M48: 45078 | N48: 418.09 | O48: 444.3 | P48: 416.79 | Q48: 443.28 | R48: 427.74 | S48: 1749901500
A49: -- | B49: 181365000 | C49: 10945000 | E49: 45108 | F49: 52.27 | G49: 53.65 | H49: 51.15 | I49: 53.29 | J49: 51.67 | K49: 272185500 | M49: 45047 | N49: 415.47 | O49: 422.58 | P49: 403.74 | Q49: 417.85 | R49: 403.2 | S49: 1780909100
A50: Other G and A | B50: 175522000 | C50: Depreciation & amortization | E50: 45078 | F50: 48.74 | G50: 52.74 | H50: 48.65 | I50: 52.39 | J50: 50.81 | K50: 390332400 | M50: 45017 | N50: 408.85 | O50: 415.94 | P50: 403.78 | Q50: 415.93 | R50: 401.35 | S50: 1395780500
A51: -- | B51: 167542000 | C51: 14203000 | E51: 45050 | F51: 0.19 Dividend | M51: 45002 | N51: 1.506 Dividend
A52: -- | B52: Net PPE | C52: 14203000 | E52: 45047 | F52: 50.35 | G52: 51.45 | H52: 48.34 | I52: 48.96 | J52: 47.29 | K52: 406453500 | M52: 44986 | N52: 395.41 | O52: 409.7 | P52: 380.65 | Q52: 409.39 | R52: 393.53 | S52: 2515995800
A53: -- | B53: 156956000 | C53: 12973000 | E53: 45017 | F53: 49.24 | G53: 51.25 | H53: 49.01 | I53: 50.32 | J53: 48.61 | K53: 301894800 | M53: 44958 | N53: 405.21 | O53: 418.31 | P53: 393.64 | Q53: 396.26 | R53: 380.91 | S53: 1603094700
A54: -- | B54: 139704000 | C54: 11853000 | E54: 45001 | F54: 0.19 Dividend | M54: 44927 | N54: 384.37 | O54: 408.16 | P54: 377.83 | Q54: 406.48 | R54: 390.74 | S54: 1575450100
A55: -- | B55: 130338000 | C55: 10945000 | E55: 44986 | F55: 47.02 | G55: 49.48 | H55: 45.36 | I55: 49.15 | J55: 47.29 | K55: 524648700 | M55: 44911 | N55: 1.781 Dividend
A56: Selling & Marketing Expense | B56: 119234000 | C56: Deferred Tax | E56: 44958 | F56: 47.89 | G56: 49.45 | H56: 46.23 | I56: 47.38 | J56: 45.58 | K56: 368553300 | M56: 44896 | N56: 408.77 | O56: 410.49 | P56: 374.77 | Q56: 382.43 | R56: 365.94 | S56: 1735973600
A57: -- | B57: Gross PPE | C57: 2277000 | E57: 44927 | F57: 47.52 | G57: 49.29 | H57: 46.06 | I57: 47.96 | J57: 46.14 | K57: 324054600 | M57: 44866 | N57: 390.14 | O57: 407.68 | P57: 368.79 | Q57: 407.68 | R57: 390.1 | S57: 1745985300
A58: -- | B58: 277294000 | C58: 2277000 | E58: 44903 | F58: 0.186667 Dividend | M58: 44835 | N58: 361.08 | O58: 389.52 | P58: 348.11 | Q58: 386.21 | R58: 369.55 | S58: 2024732000
A59: -- | B59: 251328000 | C59: -635000 | E59: 44896 | F59: 50.68 | G59: 51.2 | H59: 46.94 | I59: 47.26 | J59: 45.3 | K59: 382125300 | M59: 44820 | N59: 1.596 Dividend
A60: -- | B60: 239387000 | C60: -175000 | E60: 44866 | F60: 47.66 | G60: 51.55 | H60: 46.09 | I60: 50.81 | J60: 48.7 | K60: 454982100 | M60: 44805 | N60: 392.89 | O60: 411.73 | P60: 357.04 | Q60: 357.18 | R60: 340.38 | S60: 1998908600
A61: -- | B61: 220844000 | C61: 449000 | E61: 44835 | F61: 43.41 | G61: 47.69 | H61: 42.69 | I61: 47.44 | J61: 45.47 | K61: 350685000 | M61: 44774 | N61: 409.15 | O61: 431.73 | P61: 395.04 | Q61: 395.18 | R61: 376.59 | S61: 1443394400
A62: Research & Development | B62: Properties | C62: Deferred Income Tax | E62: 44805 | F62: 44.18 | G62: 46.08 | H62: 42.76 | I62: 43.23 | J62: 41.44 | K62: 416526900 | M62: 44743 | N62: 376.56 | O62: 413.03 | P62: 371.04 | Q62: 411.99 | R62: 392.61 | S62: 1437748400
A63: -- | B63: 0 | C63: 2277000 | E63: 44784 | F63: 0.186667 Dividend | M63: 44729 | N63: 1.577 Dividend
A64: -- | B64: 0 | C64: 2277000 | E64: 44774 | F64: 43.69 | G64: 47.57 | H64: 41.71 | I64: 44.18 | J64: 42.17 | K64: 623681700 | M64: 44713 | N64: 415.17 | O64: 417.44 | P64: 362.17 | Q64: 377.25 | R64: 357.96 | S64: 1958611900
A65: -- | B65: 0 | C65: -635000 | E65: 44743 | F65: 40.65 | G65: 44.46 | H65: 40.02 | I65: 44.02 | J65: 42.01 | K65: 472936800 | M65: 44682 | N65: 412.07 | O65: 429.66 | P65: 380.54 | Q65: 412.93 | R65: 391.81 | S65: 2418478100
A66: -- | B66: 0 | C66: -175000 | E66: 44713 | F66: 42.83 | G66: 42.97 | H66: 39.3 | I66: 40.53 | J66: 38.68 | K66: 512761800 | M66: 44652 | N66: 453.31 | O66: 457.83 | P66: 411.21 | Q66: 412 | R66: 390.93 | S66: 1856757400
A67: -- | B67: Land And Improvements | C67: 449000 | E67: 44686 | F67: 0.186667 Dividend | M67: 44638 | N67: 1.366 Dividend
A68: Operating Income | B68: 20754000 | C68: Other non-cash items | E68: 44682 | F68: 51.65 | G68: 51.66 | H68: 39.09 | I68: 42.88 | J68: 40.77 | K68: 816439800 | M68: 44621 | N68: 435.04 | O68: 462.07 | P68: 415.12 | Q68: 451.64 | R68: 427.22 | S68: 2380929500
A69: 29825000 | B69: 19342000 | C69: 4079000 | E69: 44652 | F69: 49.89 | G69: 53.59 | H69: 49.61 | I69: 51 | J69: 48.49 | K69: 427213500 | M69: 44593 | N69: 450.68 | O69: 458.12 | P69: 410.64 | Q69: 436.63 | R69: 413.02 | S69: 2297975100
A70: 29825000 | B70: 19562000 | C70: 4079000 | E70: 44637 | F70: 0.186667 Dividend | M70: 44562 | N70: 476.3 | O70: 479.98 | P70: 420.76 | Q70: 449.91 | R70: 425.58 | S70: 2485167800
A71: 29348000 | B71: 19317000 | C71: 2889000 | E71: 44621 | F71: 45.29 | G71: 50.18 | H71: 45.01 | I71: 49.64 | J71: 47.02 | K71: 557647500 | M71: 44547 | N71: 1.633 Dividend
A72: 27012000 | B72: Buildings And Improvements | C72: 2642000 | E72: 44593 | F72: 46.4 | G72: 47.33 | H72: 44 | I72: 45.05 | J72: 42.68 | K72: 487764300 | M72: 44531 | N72: 461.64 | O72: 479 | P72: 448.92 | Q72: 474.96 | R72: 447.7 | S72: 1927433900
A73: 20428000 | B73: 128472000 | C73: 1919000 | E73: 44562 | F73: 48 | G73: 48.88 | H73: 44.65 | I73: 46.6 | J73: 44.14 | K73: 497216100 | M73: 44501 | N73: 460.3 | O73: 473.54 | P73: 455.3 | Q73: 455.56 | R73: 429.41 | S73: 1335351500
A74: Net Non Operating Interest Income Expense | B74: 117973000 | C74: Change in working capital | E74: 44539 | F74: 0.183333 Dividend | M74: 44470 | N74: 430.98 | O74: 459.56 | P74: 426.36 | Q74: 459.25 | R74: 432.89 | S74: 1508665200
A75: -2431000 | B75: 111767000 | C75: 752000 | E75: 44531 | F75: 46.84 | G75: 48.84 | H75: 45.08 | I75: 48.23 | J75: 45.5 | K75: 716247600 | M75: 44456 | N75: 1.428 Dividend
A76: -2431000 | B76: 104554000 | C76: 752000 | E76: 44501 | F76: 49.99 | G76: 50.67 | H76: 46.67 | I76: 46.88 | J76: 44.22 | K76: 534258600 | M76: 44440 | N76: 452.56 | O76: 454.05 | P76: 428.78 | Q76: 429.14 | R76: 403.22 | S76: 1745559600
A77: -2245000 | B77: Machinery Furniture Equipment | C77: 181000 | E77: 44470 | F77: 46.42 | G77: 50.18 | H77: 44.9 | I77: 49.81 | J77: 46.99 | K77: 413998800 | M77: 44409 | N77: 440.34 | O77: 453.07 | P77: 436.1 | Q77: 451.56 | R77: 424.28 | S77: 1254001400
A78: -2137000 | B78: 88467000 | C78: 1943000 | E78: 44440 | F78: 49.19 | G78: 49.88 | H78: 46.42 | I78: 46.46 | J78: 43.83 | K78: 453765600 | M78: 44378 | N78: 428.87 | O78: 441.8 | P78: 421.97 | Q78: 438.51 | R78: 412.02 | S78: 1422104700
A79: -1874000 | B79: 78899000 | C79: 2553000 | E79: 44420 | F79: 0.183333 Dividend | M79: 44365 | N79: 1.376 Dividend
A80: Interest Income Non Operating | B80: 75140000 | C80: Change in Receivables | E80: 44409 | F80: 47.61 | G80: 50.86 | H80: 47.22 | I80: 49.37 | J80: 46.4 | K80: 544199400 | M80: 44348 | N80: 422.57 | O80: 428.78 | P80: 414.7 | Q80: 428.06 | R80: 400.89 | S80: 1282152400
A81: 368000 | B81: 67697000 | C81: -1136000 | E81: 44378 | F81: 46.8 | G81: 47.95 | H81: 46.07 | I81: 47.52 | J81: 44.66 | K81: 395649300 | M81: 44317 | N81: 419.43 | O81: 422.82 | P81: 404 | Q81: 420.04 | R81: 393.38 | S81: 1547235900
A82: 368000 | B82: Other Properties | C82: -1136000 | E82: 44348 | F82: 47.4 | G82: 47.6 | H82: 44.8 | I82: 47.01 | J82: 44.18 | K82: 507321000 | M82: 44287 | N82: 398.4 | O82: 420.72 | P82: 398.18 | Q82: 417.3 | R82: 390.82 | S82: 1462106600
A83: 483000 | B83: 20873000 | C83: -1106000 | E83: 44322 | F83: 0.183333 Dividend
A84: 546000 | B84: 19711000 | C84: -797000 | E84: 44317 | F84: 46.56 | G84: 48.19 | H84: 45.25 | I84: 47.34 | J84: 44.33 | K84: 524333400
A85: 254000 | B85: 19528000 | C85: 240000 | E85: 44287 | F85: 45.31 | G85: 47.26 | H85: 45.11 | I85: 46.64 | J85: 43.67 | K85: 459365700
A86: Interest Expense Non Operating | B86: 18474000 | C86: Change in Inventory
A87: 2799000 | B87: Construction in Progress | C87: -1443000
A88: 2799000 | B88: 18728000 | C88: -1443000
A89: 2728000 | B89: 15403000 | C89: -2755000
A90: 2683000 | B90: 13390000 | C90: 2017000
A91: 2128000 | B91: 10802000 | C91: -528000
A92: Other Income Expense | B92: Accumulated Depreciation | C92: Change in Payables And Accrued Expense
A93: 2075000 | B93: -120338000 | C93: 3331000
A94: 2075000 | B94: -111624000 | C94: 3331000
A95: -794000 | B95: -109049000 | C95: 4042000
A96: -3027000 | B96: -101610000 | C96: 723000
A97: -1538000 | B97: Goodwill And Other Intangible Assets | C97: 2841000
A98: Special Income Charges | B98: 28735000 | C98: Change in Payable
A99: -- | B99: 28792000 | C99: 1724000
A100: -- | B100: 28113000 | C100: 1724000
...
